Workbook

Sheet README
A1: Circular Subscription Unit-Economics Simulation Model (Weekly Apparel)
A3: Purpose: model weekly apparel subscription economics where revenue is time-based (user-week) and costs accrue per reuse cycle with explicit logistics, cleaning, labor, loss/damage, and retirement.
A5: How to use:
A6: 1) Inputs: adjust blue manual assumptions OR set Scenario_Mode=1 and choose Scenario_Select (1=Best, 2=Base, 3=Failure).
A7: 2) Scale: set Active_Users and review contribution, break-even, inventory required, capital, and replacement flow.
A8: 3) UnitEconomics: review per-cycle revenue, cost stack, and contribution margin (with/without capital charge).
A9: 4) MonteCarlo: review distribution of per-cycle CM under variance and discrete friction events.
A10: 5) KillConditions: check structural viability flags.
A11: 6) Trajectory: simulate week-by-week dynamics (growth, churn, capacity steps, inventory ordering, and cash runway).
A12: Notes:
A13: - This workbook models friction explicitly (mis-ships, late returns, loss, damage, repairs) and includes safety stock inflation from cycle-time variance.
A14: - Scale effects are optional and controlled by ENABLE_SCALE_EFFECTS.
A15: - RAND()-based Monte Carlo will change on recalculation; copy/paste values if you want to freeze a run.

Sheet Inputs
A1: Inputs (blue = editable manual). Effective values feed the model.
A3: Scenario_Mode (0=Manual, 1=Use Scenario Library) | B3: 1
A4: Scenario_Select (1=Best, 2=Base, 3=Failure) | B4: 2
A6: Parameter | B6: Manual | C6: Effective | D6: Units | E6: Notes
A7: PRICE_WEEKLY_USD | B7: 39 | C7: =IF($B$3=0,B7,VLOOKUP(A7,Scenarios!$A$4:$D$200,1+$B$4,FALSE)) | D7: USD | E7: Subscription price per active user-week
A8: DISCOUNT_RATE | B8: 0.08 | C8: =IF($B$3=0,B8,VLOOKUP(A8,Scenarios!$A$4:$D$200,1+$B$4,FALSE)) | D8: % | E8: Average discount rate (0-1)
A9: BASE_RETURN_LATENCY_WEEKS | B9: 1.05 | C9: =IF($B$3=0,B9,VLOOKUP(A9,Scenarios!$A$4:$D$200,1+$B$4,FALSE)) | D9: weeks | E9: Outbound-to-inbound latency excluding cleaning
A10: LATE_RETURN_PROB | B10: 0.18 | C10: =IF($B$3=0,B10,VLOOKUP(A10,Scenarios!$A$4:$D$200,1+$B$4,FALSE)) | D10: % | E10: Probability return exceeds target window
A11: LATE_RETURN_EXTRA_WEEKS | B11: 0.55 | C11: =IF($B$3=0,B11,VLOOKUP(A11,Scenarios!$A$4:$D$200,1+$B$4,FALSE)) | D11: weeks | E11: Additional weeks conditional on late return
A12: CLEAN_TAT_WEEKS | B12: 0.35 | C12: =IF($B$3=0,B12,VLOOKUP(A12,Scenarios!$A$4:$D$200,1+$B$4,FALSE)) | D12: weeks | E12: Cleaning + QA turnaround time
A13: SIGMA_RETURN_WEEKS | B13: 0.3 | C13: =IF($B$3=0,B13,VLOOKUP(A13,Scenarios!$A$4:$D$200,1+$B$4,FALSE)) | D13: weeks | E13: Std dev of return latency
A14: SIGMA_CLEAN_WEEKS | B14: 0.1 | C14: =IF($B$3=0,B14,VLOOKUP(A14,Scenarios!$A$4:$D$200,1+$B$4,FALSE)) | D14: weeks | E14: Std dev of cleaning TAT
A15: SERVICE_LEVEL | B15: 0.95 | C15: =IF($B$3=0,B15,VLOOKUP(A15,Scenarios!$A$4:$D$200,1+$B$4,FALSE)) | D15: % | E15: Service level target for safety stock factor
A16: ITEMS_PER_BOX | B16: 4 | C16: =IF($B$3=0,B16,VLOOKUP(A16,Scenarios!$A$4:$D$200,1+$B$4,FALSE)) | E16: Average garments per shipment
A17: GARMENT_ACQ_COST_USD | B17: 25 | C17: =IF($B$3=0,B17,VLOOKUP(A17,Scenarios!$A$4:$D$200,1+$B$4,FALSE)) | D17: USD | E17: Weighted avg acquisition cost per garment
A18: GARMENT_LIFE_CYCLES_WEAR | B18: 28 | C18: =IF($B$3=0,B18,VLOOKUP(A18,Scenarios!$A$4:$D$200,1+$B$4,FALSE)) | D18: cycles | E18: Wear-out cycles excluding loss/damage
A19: LOSS_PROB | B19: 0.009 | C19: =IF($B$3=0,B19,VLOOKUP(A19,Scenarios!$A$4:$D$200,1+$B$4,FALSE)) | D19: % | E19: Permanent loss probability per garment-cycle
A20: DAMAGE_PROB | B20: 0.055 | C20: =IF($B$3=0,B20,VLOOKUP(A20,Scenarios!$A$4:$D$200,1+$B$4,FALSE)) | D20: % | E20: Damage probability per garment-cycle
A21: DAMAGE_RETIRE_PROB | B21: 0.35 | C21: =IF($B$3=0,B21,VLOOKUP(A21,Scenarios!$A$4:$D$200,1+$B$4,FALSE)) | D21: % | E21: Share of damaged garments retired
A22: REPAIR_COST_USD | B22: 6.5 | C22: =IF($B$3=0,B22,VLOOKUP(A22,Scenarios!$A$4:$D$200,1+$B$4,FALSE)) | D22: USD | E22: Repair cost conditional on repairable damage
A23: CLEAN_COST_USD | B23: 2.6 | C23: =IF($B$3=0,B23,VLOOKUP(A23,Scenarios!$A$4:$D$200,1+$B$4,FALSE)) | D23: USD | E23: Cleaning/finishing cost per garment-cycle
A24: QA_COST_USD | B24: 0.75 | C24: =IF($B$3=0,B24,VLOOKUP(A24,Scenarios!$A$4:$D$200,1+$B$4,FALSE)) | D24: USD | E24: QA/rebag cost per garment-cycle
A25: OUTBOUND_SHIP_USD | B25: 8.2 | C25: =IF($B$3=0,B25,VLOOKUP(A25,Scenarios!$A$4:$D$200,1+$B$4,FALSE)) | D25: USD | E25: Outbound shipping cost per box
A26: INBOUND_SHIP_USD | B26: 6.8 | C26: =IF($B$3=0,B26,VLOOKUP(A26,Scenarios!$A$4:$D$200,1+$B$4,FALSE)) | D26: USD | E26: Inbound shipping cost per box
A27: PACKAGING_DEP_USD | B27: 1.1 | C27: =IF($B$3=0,B27,VLOOKUP(A27,Scenarios!$A$4:$D$200,1+$B$4,FALSE)) | D27: USD | E27: Packaging depreciation per cycle
A28: PICKPACK_LABOR_USD | B28: 3.1 | C28: =IF($B$3=0,B28,VLOOKUP(A28,Scenarios!$A$4:$D$200,1+$B$4,FALSE)) | D28: USD | E28: Pick/pack labor per box-cycle
... A57: FAILURE_PROB_KILL | B57: 0.2 | C57: =IF($B$3=0,B57,VLOOKUP(A57,Scenarios!$A$4:$D$200,1+$B$4,FALSE)) | D57: % | E57: Kill threshold: Monte Carlo Pr(CM<0)
A60: Trajectory & Cash Simulation (week-by-week system dynamics)
A62: HORIZON_WEEKS | B62: 104 | C62: =IF($B$3=0,B62,VLOOKUP(A62,Scenarios!$A$4:$D$400,1+$B$4,FALSE))
A63: START_ACTIVE_USERS | B63: 250 | C63: =IF($B$3=0,B63,VLOOKUP(A63,Scenarios!$A$4:$D$400,1+$B$4,FALSE))
A64: WEEKLY_NEW_USERS | B64: 20 | C64: =IF($B$3=0,B64,VLOOKUP(A64,Scenarios!$A$4:$D$400,1+$B$4,FALSE))
A65: CAC_USD | B65: 25 | C65: =IF($B$3=0,B65,VLOOKUP(A65,Scenarios!$A$4:$D$400,1+$B$4,FALSE))
A66: BASE_CHURN_WEEKLY | B66: 0.015 | C66: =IF($B$3=0,B66,VLOOKUP(A66,Scenarios!$A$4:$D$400,1+$B$4,FALSE))
A67: CHURN_SENS_REFUND | B67: 1.2 | C67: =IF($B$3=0,B67,VLOOKUP(A67,Scenarios!$A$4:$D$400,1+$B$4,FALSE))
A68: CHURN_SENS_STOCKOUT | B68: 0.5 | C68: =IF($B$3=0,B68,VLOOKUP(A68,Scenarios!$A$4:$D$400,1+$B$4,FALSE))
A69: CHURN_SENS_LATE | B69: 0.2 | C69: =IF($B$3=0,B69,VLOOKUP(A69,Scenarios!$A$4:$D$400,1+$B$4,FALSE))
A70: STOCKOUT_REFUND_ADD | B70: 0.8 | C70: =IF($B$3=0,B70,VLOOKUP(A70,Scenarios!$A$4:$D$400,1+$B$4,FALSE))
A71: STOCKOUT_PENALTY_USD | B71: 6 | C71: =IF($B$3=0,B71,VLOOKUP(A71,Scenarios!$A$4:$D$400,1+$B$4,FALSE))
A72: START_CASH_USD | B72: 150000 | C72: =IF($B$3=0,B72,VLOOKUP(A72,Scenarios!$A$4:$D$400,1+$B$4,FALSE))
A73: INVENTORY_LEAD_WEEKS | B73: 1 | C73: =IF($B$3=0,B73,VLOOKUP(A73,Scenarios!$A$4:$D$400,1+$B$4,FALSE))
... A76: INITIAL_SITES_ONLINE | B76: 1 | C76: =IF($B$3=0,B76,VLOOKUP(A76,Scenarios!$A$4:$D$400,1+$B$4,FALSE))
A78: Advanced Dynamics Extensions (cohorts, marketing saturation, ramping)
A80: COHORT_MODEL_ON | B80: 1 | C80: =IF($B$3=0,B80,VLOOKUP(A80,Scenarios!$A$4:$D$600,1+$B$4,FALSE))
A81: MAX_COHORT_AGE_WEEKS | B81: 52 | C81: =IF($B$3=0,B81,VLOOKUP(A81,Scenarios!$A$4:$D$600,1+$B$4,FALSE)) | D81: weeks
A82: COHORT_CHURN_BASE_WEEKLY | B82: 0.015 | C82: =IF($B$3=0,B82,VLOOKUP(A82,Scenarios!$A$4:$D$600,1+$B$4,FALSE)) | D82: %
A83: EARLY_CHURN_PREMIUM | B83: 1.5 | C83: =IF($B$3=0,B83,VLOOKUP(A83,Scenarios!$A$4:$D$600,1+$B$4,FALSE)) | D83: mult
A84: CHURN_DECAY_WEEKS | B84: 8 | C84: =IF($B$3=0,B84,VLOOKUP(A84,Scenarios!$A$4:$D$600,1+$B$4,FALSE)) | D84: weeks
A85: MARKETING_MODE | B85: 1 | C85: =IF($B$3=0,B85,VLOOKUP(A85,Scenarios!$A$4:$D$600,1+$B$4,FALSE))
A86: WEEKLY_MKTG_BUDGET_USD | B86: 12000 | C86: =IF($B$3=0,B86,VLOOKUP(A86,Scenarios!$A$4:$D$600,1+$B$4,FALSE)) | D86: USD
A87: MKTG_PCT_REVENUE_CAP | B87: 0.15 | C87: =IF($B$3=0,B87,VLOOKUP(A87,Scenarios!$A$4:$D$600,1+$B$4,FALSE)) | D87: %
A88: TAM_USERS | B88: 2000000 | C88: =IF($B$3=0,B88,VLOOKUP(A88,Scenarios!$A$4:$D$600,1+$B$4,FALSE)) | D88: users
A89: CAC_SATURATION_SENS | B89: 1 | C89: =IF($B$3=0,B89,VLOOKUP(A89,Scenarios!$A$4:$D$600,1+$B$4,FALSE)) | D89: mult
A90: CAC_SATURATION_ELASTICITY | B90: 1.3 | C90: =IF($B$3=0,B90,VLOOKUP(A90,Scenarios!$A$4:$D$600,1+$B$4,FALSE)) | D90: power
A91: MAX_NEW_USERS_PER_WEEK | B91: 800 | C91: =IF($B$3=0,B91,VLOOKUP(A91,Scenarios!$A$4:$D$600,1+$B$4,FALSE)) | D91: users/wk
A92: CAPACITY_UTIL_TARGET | B92: 0.85 | C92: =IF($B$3=0,B92,VLOOKUP(A92,Scenarios!$A$4:$D$600,1+$B$4,FALSE)) | D92: %
A93: RAMP_WEEKS | B93: 6 | C93: =IF($B$3=0,B93,VLOOKUP(A93,Scenarios!$A$4:$D$600,1+$B$4,FALSE)) | D93: weeks
A94: RAMP_EFF_START | B94: 0.6 | C94: =IF($B$3=0,B94,VLOOKUP(A94,Scenarios!$A$4:$D$600,1+$B$4,FALSE)) | D94: %
A95: RAMP_VAR_COST_MULT_MAX | B95: 1.35 | C95: =IF($B$3=0,B95,VLOOKUP(A95,Scenarios!$A$4:$D$600,1+$B$4,FALSE)) | D95: mult

Sheet Lookups
A1: Service_Level | B1: Z_Score
A2: 0.8 | B2: 0.8416
A3: 0.85 | B3: 1.0364
A4: 0.9 | B4: 1.2816
A5: 0.92 | B5: 1.4051
A6: 0.94 | B6: 1.5548
A7: 0.95 | B7: 1.6449
A8: 0.96 | B8: 1.7507
A9: 0.97 | B9: 1.8808
A10: 0.975 | B10: 1.96
A11: 0.98 | B11: 2.0537
A12: 0.985 | B12: 2.1701
A13: 0.99 | B13: 2.3263
A14: 0.995 | B14: 2.5758

Sheet Scenarios
A1: Scenario Library (used when Scenario_Mode = 1)
A3: Parameter | B3: Best | C3: Base | D3: Failure | E3: Notes
A4: PRICE_WEEKLY_USD | B4: 49 | C4: 39 | D4: 29 | E4: Subscription price per active user-week
A5: DISCOUNT_RATE | B5: 0.02 | C5: 0.08 | D5: 0.15 | E5: Average discount rate (0-1)
A6: BASE_RETURN_LATENCY_WEEKS | B6: 0.85 | C6: 1.05 | D6: 1.35 | E6: Outbound-to-inbound latency excluding cleaning
A7: LATE_RETURN_PROB | B7: 0.08 | C7: 0.18 | D7: 0.35 | E7: Probability return exceeds target window
A8: LATE_RETURN_EXTRA_WEEKS | B8: 0.3 | C8: 0.55 | D8: 0.9 | E8: Additional weeks conditional on late return
A9: CLEAN_TAT_WEEKS | B9: 0.25 | C9: 0.35 | D9: 0.55 | E9: Cleaning + QA turnaround time
A10: SIGMA_RETURN_WEEKS | B10: 0.18 | C10: 0.3 | D10: 0.45 | E10: Std dev of return latency
A11: SIGMA_CLEAN_WEEKS | B11: 0.06 | C11: 0.1 | D11: 0.18 | E11: Std dev of cleaning TAT
A12: SERVICE_LEVEL | B12: 0.97 | C12: 0.95 | D12: 0.9 | E12: Service level target for safety stock factor
A13: ITEMS_PER_BOX | B13: 4 | C13: 4 | D13: 4 | E13: Average garments per shipment
A14: GARMENT_ACQ_COST_USD | B14: 22 | C14: 25 | D14: 28 | E14: Weighted avg acquisition cost per garment
A15: GARMENT_LIFE_CYCLES_WEAR | B15: 35 | C15: 28 | D15: 18 | E15: Wear-out cycles excluding loss/damage
... A39: USERS_PER_SITE | B39: 4000 | C39: 3000 | D39: 2200 | E39: User capacity per site per week (step function)
A40: HORIZON_WEEKS | B40: 104 | C40: 104 | D40: 104
A41: START_ACTIVE_USERS | B41: 500 | C41: 250 | D41: 250
A42: WEEKLY_NEW_USERS | B42: 60 | C42: 20 | D42: 10
A43: CAC_USD | B43: 15 | C43: 25 | D43: 35
A44: BASE_CHURN_WEEKLY | B44: 0.008 | C44: 0.015 | D44: 0.035
A45: CHURN_SENS_REFUND | B45: 0.8 | C45: 1.2 | D45: 1.8
A46: CHURN_SENS_STOCKOUT | B46: 0.2 | C46: 0.5 | D46: 1.2
A47: CHURN_SENS_LATE | B47: 0.1 | C47: 0.2 | D47: 0.4
A48: STOCKOUT_REFUND_ADD | B48: 0.5 | C48: 0.8 | D48: 1.2
A49: STOCKOUT_PENALTY_USD | B49: 3 | C49: 6 | D49: 10
A50: START_CASH_USD | B50: 250000 | C50: 150000 | D50: 80000
A51: INVENTORY_LEAD_WEEKS | B51: 0 | C51: 1 | D51: 2
... A70: RAMP_VAR_COST_MULT_MAX | B70: 1.2 | C70: 1.35 | D70: 1.6

Sheet UnitEconomics
A1: Per User-Week Cycle Unit Economics (time-based revenue; per-cycle marginal costs)
A3: Active Users (for scale effects) | B3: =Scale!$B$3 | D3: Key KPIs
D4: CM per cycle | E4: =B33
A5: Scaled Cost Drivers (optional) | D5: Economic CM per cycle | E5: =B35
A6: Clean_Cost_Eff (per garment) | B6: =Inputs!$C$23*IF(Inputs!$C$43=1,POWER(MAX(1,Scale!$B$3)/Inputs!$C$44,Inputs!$C$45),1) | D6: Var cost per cycle | E6: =B32
A7: PickPack_Labor_Eff (per box) | B7: =Inputs!$C$28*IF(Inputs!$C$43=1,POWER(MAX(1,Scale!$B$3)/Inputs!$C$44,Inputs!$C$46),1) | D7: Net revenue per cycle | E7: =B18
A8: Inbound_Labor_Eff (per box) | B8: =Inputs!$C$29*IF(Inputs!$C$43=1,POWER(MAX(1,Scale!$B$3)/Inputs!$C$44,Inputs!$C$46),1) | D8: Var cost as % revenue | E8: =IF(B18=0,0,B32/B18)
A9: Support_Eff (per user-week) | B9: =Inputs!$C$30*IF(Inputs!$C$43=1,POWER(MAX(1,Scale!$B$3)/Inputs!$C$44,Inputs!$C$47),1)
A10: Outbound_Ship_Eff (per box) | B10: =Inputs!$C$25*(1-IF(Inputs!$C$43=1,Inputs!$C$48*(1-EXP(-MAX(1,Scale!$B$3)/Inputs!$C$49)),0))
A11: Inbound_Ship_Eff (per box) | B11: =Inputs!$C$26*(1-IF(Inputs!$C$43=1,Inputs!$C$48*(1-EXP(-MAX(1,Scale!$B$3)/Inputs!$C$49)),0))
A12: MisShip_Prob_Eff | B12: =MAX(Inputs!$C$50, Inputs!$C$33*IF(Inputs!$C$43=1,EXP(-MAX(1,Scale!$B$3)/Inputs!$C$51),1))
A15: Metric | B15: Per Cycle (USD) | C15: Driver | D15: Notes
A16: Collected revenue (pre-refund) | B16: =Inputs!$C$7*(1-Inputs!$C$8) | C16: Price, discount | D16: Subscription yield per active user-week
A17: Refunds / credits | B17: =-Inputs!$C$7*(1-Inputs!$C$8)*(Inputs!$C$36 + B12*Inputs!$C$37 + Inputs!$C$10*Inputs!$C$38) | C17: Refund model | D17: Expected credits from miship & late returns
A18: Revenue net of refunds | B18: =SUM(B16:B17)
A19: Cleaning + QA | B19: =Inputs!$C$16*(B6+Inputs!$C$24) | C19: Service | D19: Per-garment cycle service cost
A20: Outbound shipping | B20: =B10 | C20: Carrier | D20: Per-box outbound transport
A21: Inbound shipping | B21: =B11 | C21: Carrier | D21: Per-box returns transport
A22: Packaging depreciation | B22: =Inputs!$C$27 | C22: Packaging | D22: Reusable box amortized per cycle
A23: Fulfillment labor (pick/pack) | B23: =B7 | C23: Labor | D23: Variable labor per box-cycle
A24: Inbound processing labor | B24: =B8 | C24: Labor | D24: Receiving, sort, rebag staging
A25: Customer support | B25: =B9 | C25: Support | D25: Variable contacts per user-week
A26: Mis-ship expected incremental | B26: =B12*Inputs!$C$34 | C26: Mis-ship | D26: Reship, credits, extra handling
A27: Late return exception handling | B27: =Inputs!$C$10*Inputs!$C$35 | C27: Late return | D27: Manual exceptions, comms
A28: Wear-out retirement replacement | B28: =Inputs!$C$16*(1/Inputs!$C$18)*Inputs!$C$17 | C28: Wear | D28: Wear-based retirement; excludes loss/damage
A29: Loss replacement | B29: =Inputs!$C$16*Inputs!$C$19*Inputs!$C$17 | C29: Loss | D29: Permanent loss per garment-cycle
A30: Damage replacement + repair | B30: =Inputs!$C$16*Inputs!$C$20*(Inputs!$C$22 + Inputs!$C$21*Inputs!$C$17) | C30: Damage | D30: Repair cost plus retire share
A31: Payment processing fees | B31: =Inputs!$C$31*B18 + Inputs!$C$32 | C31: Payments | D31: Applied on net collected revenue
A32: Total variable cost | B32: =SUM(B19:B31)
A33: Contribution margin (CM) | B33: =B18 - B32
A34: Capital charge per cycle (inventory) | B34: =Scale!$B$15 | C34: Capital | D34: Weekly cost of capital allocated per user-week
A35: Economic CM (after capital) | B35: =B33 - B34

Sheet Scale
A1: Scale & Break-even (100 → 100,000 users) with inventory physics and capacity steps
A3: Active_Users | B3: 1000 | F3: Users | G3: Weekly CM Profit | H3: Weekly Economic Profit | I3: CM / Cycle | J3: Fixed OPEX | K3: CapCharge / Cycle
F4: 100 | G4: =F4*I4 - J4 | H4: =F4*(I4-K4) - J4 | I4: =((Inputs!$C$7*(1-Inputs!$C$8) - Inputs!$C$7*(1-Inputs!$C$8)*(Inputs!$C$36 + MAX(Inputs!$C$50, Inputs!$C$33*IF(Inputs!$C$43=1,EXP(-MAX(1,F4)/Inputs!$C$51),1))*Inputs!$C$37 + Inputs!$C$10*Inputs!$C$38))) - (Inputs!$C$16*((Inputs!$C$23*IF(Inputs!$C$43=1,POWER(MAX(1,F4)/Inputs!$C$44,Inputs!$C$45),1))+Inputs!$C$24) + (Inputs!$C$25*(1-IF(Inputs!$C$43=1,Inputs!$C$48*(1-EXP(-MAX(1,F4)/Inputs!$C$49)),0))) + (Inputs!$C$26*(1-IF(Inputs!$C$43=1,Inputs!$C$48*(1-EXP(-MAX(1,F4)/Inputs!$C$49)),0))) + Inputs!$C$27 + (Inputs!$C$28*IF(Inputs!$C$43=1,POWER(MAX(1,F4)/Inputs!$C$44,Inputs!$C$46),1)) + (Inputs!$C$29*IF(Inputs!$C$43=1,POWER(MAX(1,F4)/Inputs!$C$44,Inputs!$C$46),1)) + (Inputs!$C$30*IF(Inputs!$C$43=1,POWER(MAX(1,F4)/Inputs!$C$44,Inputs!$C$47),1)) + (MAX(Inputs!$C$50, Inputs!$C$33*IF(Inputs!$C$43=1,EXP(-MAX(1,F4)/Inputs!$C$51),1))*Inputs!$C$34) + (Inputs!$C$10*Inputs!$C$35) + Inputs!$C$16*(1/Inputs!$C$18)*Inputs!$C$17 + Inputs!$C$16*Inputs!$C$19*Inputs!$C$17 + Inputs!$C$16*Inputs!$C$20*(Inputs!$C$22 + Inputs!$C$21*Inputs!$C$17) + Inputs!$C$31*(Inputs!$C$7*(1-Inputs!$C$8) - Inputs!$C$7*(1-Inputs!$C$8)*(Inputs!$C$36 + MAX(Inputs!$C$50, Inputs!$C$33*IF(Inputs!$C$43=1,EXP(-MAX(1,F4)/Inputs!$C$51),1))*Inputs!$C$37 + Inputs!$C$10*Inputs!$C$38)) + Inputs!$C$32) | J4: =Inputs!$C$40 + CEILING(F4/Inputs!$C$42,1)*Inputs!$C$41 | K4: =Scale!$B$15
A5: Cycle-time physics (drives inventory multiple) | F5: 200 | G5: =F5*I5 - J5 | H5: =F5*(I5-K5) - J5 | I5: =((Inputs!$C$7*(1-Inputs!$C$8) - Inputs!$C$7*(1-Inputs!$C$8)*(Inputs!$C$36 + MAX(Inputs!$C$50, Inputs!$C$33*IF(Inputs!$C$43=1,EXP(-MAX(1,F5)/Inputs!$C$51),1))*Inputs!$C$37 + Inputs!$C$10*Inputs!$C$38))) - (Inputs!$C$16*((Inputs!$C$23*IF(Inputs!$C$43=1,POWER(MAX(1,F5)/Inputs!$C$44,Inputs!$C$45),1))+Inputs!$C$24) + (Inputs!$C$25*(1-IF(Inputs!$C$43=1,Inputs!$C$48*(1-EXP(-MAX(1,F5)/Inputs!$C$49)),0))) + (Inputs!$C$26*(1-IF(Inputs!$C$43=1,Inputs!$C$48*(1-EXP(-MAX(1,F5)/Inputs!$C$49)),0))) + Inputs!$C$27 + (Inputs!$C$28*IF(Inputs!$C$43=1,POWER(MAX(1,F5)/Inputs!$C$44,Inputs!$C$46),1)) + (Inputs!$C$29*IF(Inputs!$C$43=1,POWER(MAX(1,F5)/Inputs!$C$44,Inputs!$C$46),1)) + (Inputs!$C$30*IF(Inputs!$C$43=1,POWER(MAX(1,F5)/Inputs!$C$44,Inputs!$C$47),1)) + (MAX(Inputs!$C$50, Inputs!$C$33*IF(Inputs!$C$43=1,EXP(-MAX(1,F5)/Inputs!$C$51),1))*Inputs!$C$34) + (Inputs!$C$10*Inputs!$C$35) + Inputs!$C$16*(1/Inputs!$C$18)*Inputs!$C$17 + Inputs!$C$16*Inputs!$C$19*Inputs!$C$17 + Inputs!$C$16*Inputs!$C$20*(Inputs!$C$22 + Inputs!$C$21*Inputs!$C$17) + Inputs!$C$31*(Inputs!$C$7*(1-Inputs!$C$8) - Inputs!$C$7*(1-Inputs!$C$8)*(Inputs!$C$36 + MAX(Inputs!$C$50, Inputs!$C$33*IF(Inputs!$C$43=1,EXP(-MAX(1,F5)/Inputs!$C$51),1))*Inputs!$C$37 + Inputs!$C$10*Inputs!$C$38)) + Inputs!$C$32) | J5: =Inputs!$C$40 + CEILING(F5/Inputs!$C$42,1)*Inputs!$C$41 | K5: =Scale!$B$15
A6: Mean return latency (weeks) | B6: =Inputs!$C$9 + Inputs!$C$10*Inputs!$C$11 | F6: 400 | G6: =F6*I6 - J6 | H6: =F6*(I6-K6) - J6 | I6: =((Inputs!$C$7*(1-Inputs!$C$8) - Inputs!$C$7*(1-Inputs!$C$8)*(Inputs!$C$36 + MAX(Inputs!$C$50, Inputs!$C$33*IF(Inputs!$C$43=1,EXP(-MAX(1,F6)/Inputs!$C$51),1))*Inputs!$C$37 + Inputs!$C$10*Inputs!$C$38))) - (Inputs!$C$16*((Inputs!$C$23*IF(Inputs!$C$43=1,POWER(MAX(1,F6)/Inputs!$C$44,Inputs!$C$45),1))+Inputs!$C$24) + (Inputs!$C$25*(1-IF(Inputs!$C$43=1,Inputs!$C$48*(1-EXP(-MAX(1,F6)/Inputs!$C$49)),0))) + (Inputs!$C$26*(1-IF(Inputs!$C$43=1,Inputs!$C$48*(1-EXP(-MAX(1,F6)/Inputs!$C$49)),0))) + Inputs!$C$27 + (Inputs!$C$28*IF(Inputs!$C$43=1,POWER(MAX(1,F6)/Inputs!$C$44,Inputs!$C$46),1)) + (Inputs!$C$29*IF(Inputs!$C$43=1,POWER(MAX(1,F6)/Inputs!$C$44,Inputs!$C$46),1)) + (Inputs!$C$30*IF(Inputs!$C$43=1,POWER(MAX(1,F6)/Inputs!$C$44,Inputs!$C$47),1)) + (MAX(Inputs!$C$50, Inputs!$C$33*IF(Inputs!$C$43=1,EXP(-MAX(1,F6)/Inputs!$C$51),1))*Inputs!$C$34) + (Inputs!$C$10*Inputs!$C$35) + Inputs!$C$16*(1/Inputs!$C$18)*Inputs!$C$17 + Inputs!$C$16*Inputs!$C$19*Inputs!$C$17 + Inputs!$C$16*Inputs!$C$20*(Inputs!$C$22 + Inputs!$C$21*Inputs!$C$17) + Inputs!$C$31*(Inputs!$C$7*(1-Inputs!$C$8) - Inputs!$C$7*(1-Inputs!$C$8)*(Inputs!$C$36 + MAX(Inputs!$C$50, Inputs!$C$33*IF(Inputs!$C$43=1,EXP(-MAX(1,F6)/Inputs!$C$51),1))*Inputs!$C$37 + Inputs!$C$10*Inputs!$C$38)) + Inputs!$C$32) | J6: =Inputs!$C$40 + CEILING(F6/Inputs!$C$42,1)*Inputs!$C$41 | K6: =Scale!$B$15
A7: Mean cleaning TAT (weeks) | B7: =Inputs!$C$12 | F7: 700 | G7: =F7*I7 - J7 | H7: =F7*(I7-K7) - J7 | I7: =((Inputs!$C$7*(1-Inputs!$C$8) - Inputs!$C$7*(1-Inputs!$C$8)*(Inputs!$C$36 + MAX(Inputs!$C$50, Inputs!$C$33*IF(Inputs!$C$43=1,EXP(-MAX(1,F7)/Inputs!$C$51),1))*Inputs!$C$37 + Inputs!$C$10*Inputs!$C$38))) - (Inputs!$C$16*((Inputs!$C$23*IF(Inputs!$C$43=1,POWER(MAX(1,F7)/Inputs!$C$44,Inputs!$C$45),1))+Inputs!$C$24) + (Inputs!$C$25*(1-IF(Inputs!$C$43=1,Inputs!$C$48*(1-EXP(-MAX(1,F7)/Inputs!$C$49)),0))) + (Inputs!$C$26*(1-IF(Inputs!$C$43=1,Inputs!$C$48*(1-EXP(-MAX(1,F7)/Inputs!$C$49)),0))) + Inputs!$C$27 + (Inputs!$C$28*IF(Inputs!$C$43=1,POWER(MAX(1,F7)/Inputs!$C$44,Inputs!$C$46),1)) + (Inputs!$C$29*IF(Inputs!$C$43=1,POWER(MAX(1,F7)/Inputs!$C$44,Inputs!$C$46),1)) + (Inputs!$C$30*IF(Inputs!$C$43=1,POWER(MAX(1,F7)/Inputs!$C$44,Inputs!$C$47),1)) + (MAX(Inputs!$C$50, Inputs!$C$33*IF(Inputs!$C$43=1,EXP(-MAX(1,F7)/Inputs!$C$51),1))*Inputs!$C$34) + (Inputs!$C$10*Inputs!$C$35) + Inputs!$C$16*(1/Inputs!$C$18)*Inputs!$C$17 + Inputs!$C$16*Inputs!$C$19*Inputs!$C$17 + Inputs!$C$16*Inputs!$C$20*(Inputs!$C$22 + Inputs!$C$21*Inputs!$C$17) + Inputs!$C$31*(Inputs!$C$7*(1-Inputs!$C$8) - Inputs!$C$7*(1-Inputs!$C$8)*(Inputs!$C$36 + MAX(Inputs!$C$50, Inputs!$C$33*IF(Inputs!$C$43=1,EXP(-MAX(1,F7)/Inputs!$C$51),1))*Inputs!$C$37 + Inputs!$C$10*Inputs!$C$38)) + Inputs!$C$32) | J7: =Inputs!$C$40 + CEILING(F7/Inputs!$C$42,1)*Inputs!$C$41 | K7: =Scale!$B$15
A8: Mean total cycle time (weeks) | B8: =B6+B7 | F8: 1000 | G8: =F8*I8 - J8 | H8: =F8*(I8-K8) - J8 | I8: =((Inputs!$C$7*(1-Inputs!$C$8) - Inputs!$C$7*(1-Inputs!$C$8)*(Inputs!$C$36 + MAX(Inputs!$C$50, Inputs!$C$33*IF(Inputs!$C$43=1,EXP(-MAX(1,F8)/Inputs!$C$51),1))*Inputs!$C$37 + Inputs!$C$10*Inputs!$C$38))) - (Inputs!$C$16*((Inputs!$C$23*IF(Inputs!$C$43=1,POWER(MAX(1,F8)/Inputs!$C$44,Inputs!$C$45),1))+Inputs!$C$24) + (Inputs!$C$25*(1-IF(Inputs!$C$43=1,Inputs!$C$48*(1-EXP(-MAX(1,F8)/Inputs!$C$49)),0))) + (Inputs!$C$26*(1-IF(Inputs!$C$43=1,Inputs!$C$48*(1-EXP(-MAX(1,F8)/Inputs!$C$49)),0))) + Inputs!$C$27 + (Inputs!$C$28*IF(Inputs!$C$43=1,POWER(MAX(1,F8)/Inputs!$C$44,Inputs!$C$46),1)) + (Inputs!$C$29*IF(Inputs!$C$43=1,POWER(MAX(1,F8)/Inputs!$C$44,Inputs!$C$46),1)) + (Inputs!$C$30*IF(Inputs!$C$43=1,POWER(MAX(1,F8)/Inputs!$C$44,Inputs!$C$47),1)) + (MAX(Inputs!$C$50, Inputs!$C$33*IF(Inputs!$C$43=1,EXP(-MAX(1,F8)/Inputs!$C$51),1))*Inputs!$C$34) + (Inputs!$C$10*Inputs!$C$35) + Inputs!$C$16*(1/Inputs!$C$18)*Inputs!$C$17 + Inputs!$C$16*Inputs!$C$19*Inputs!$C$17 + Inputs!$C$16*Inputs!$C$20*(Inputs!$C$22 + Inputs!$C$21*Inputs!$C$17) + Inputs!$C$31*(Inputs!$C$7*(1-Inputs!$C$8) - Inputs!$C$7*(1-Inputs!$C$8)*(Inputs!$C$36 + MAX(Inputs!$C$50, Inputs!$C$33*IF(Inputs!$C$43=1,EXP(-MAX(1,F8)/Inputs!$C$51),1))*Inputs!$C$37 + Inputs!$C$10*Inputs!$C$38)) + Inputs!$C$32) | J8: =Inputs!$C$40 + CEILING(F8/Inputs!$C$42,1)*Inputs!$C$41 | K8: =Scale!$B$15
A9: Std dev total cycle time (weeks) | B9: =SQRT(Inputs!$C$13^2 + Inputs!$C$14^2) | F9: 1500 | G9: =F9*I9 - J9 | H9: =F9*(I9-K9) - J9 | I9: =((Inputs!$C$7*(1-Inputs!$C$8) - Inputs!$C$7*(1-Inputs!$C$8)*(Inputs!$C$36 + MAX(Inputs!$C$50, Inputs!$C$33*IF(Inputs!$C$43=1,EXP(-MAX(1,F9)/Inputs!$C$51),1))*Inputs!$C$37 + Inputs!$C$10*Inputs!$C$38))) - (Inputs!$C$16*((Inputs!$C$23*IF(Inputs!$C$43=1,POWER(MAX(1,F9)/Inputs!$C$44,Inputs!$C$45),1))+Inputs!$C$24) + (Inputs!$C$25*(1-IF(Inputs!$C$43=1,Inputs!$C$48*(1-EXP(-MAX(1,F9)/Inputs!$C$49)),0))) + (Inputs!$C$26*(1-IF(Inputs!$C$43=1,Inputs!$C$48*(1-EXP(-MAX(1,F9)/Inputs!$C$49)),0))) + Inputs!$C$27 + (Inputs!$C$28*IF(Inputs!$C$43=1,POWER(MAX(1,F9)/Inputs!$C$44,Inputs!$C$46),1)) + (Inputs!$C$29*IF(Inputs!$C$43=1,POWER(MAX(1,F9)/Inputs!$C$44,Inputs!$C$46),1)) + (Inputs!$C$30*IF(Inputs!$C$43=1,POWER(MAX(1,F9)/Inputs!$C$44,Inputs!$C$47),1)) + (MAX(Inputs!$C$50, Inputs!$C$33*IF(Inputs!$C$43=1,EXP(-MAX(1,F9)/Inputs!$C$51),1))*Inputs!$C$34) + (Inputs!$C$10*Inputs!$C$35) + Inputs!$C$16*(1/Inputs!$C$18)*Inputs!$C$17 + Inputs!$C$16*Inputs!$C$19*Inputs!$C$17 + Inputs!$C$16*Inputs!$C$20*(Inputs!$C$22 + Inputs!$C$21*Inputs!$C$17) + Inputs!$C$31*(Inputs!$C$7*(1-Inputs!$C$8) - Inputs!$C$7*(1-Inputs!$C$8)*(Inputs!$C$36 + MAX(Inputs!$C$50, Inputs!$C$33*IF(Inputs!$C$43=1,EXP(-MAX(1,F9)/Inputs!$C$51),1))*Inputs!$C$37 + Inputs!$C$10*Inputs!$C$38)) + Inputs!$C$32) | J9: =Inputs!$C$40 + CEILING(F9/Inputs!$C$42,1)*Inputs!$C$41 | K9: =Scale!$B$15
A10: Z (service level) | B10: =VLOOKUP(Inputs!$C$15,Lookups!$A$2:$B$20,2,TRUE) | F10: 2200 | G10: =F10*I10 - J10 | H10: =F10*(I10-K10) - J10 | I10: =((Inputs!$C$7*(1-Inputs!$C$8) - Inputs!$C$7*(1-Inputs!$C$8)*(Inputs!$C$36 + MAX(Inputs!$C$50, Inputs!$C$33*IF(Inputs!$C$43=1,EXP(-MAX(1,F10)/Inputs!$C$51),1))*Inputs!$C$37 + Inputs!$C$10*Inputs!$C$38))) - (Inputs!$C$16*((Inputs!$C$23*IF(Inputs!$C$43=1,POWER(MAX(1,F10)/Inputs!$C$44,Inputs!$C$45),1))+Inputs!$C$24) + (Inputs!$C$25*(1-IF(Inputs!$C$43=1,Inputs!$C$48*(1-EXP(-MAX(1,F10)/Inputs!$C$49)),0))) + (Inputs!$C$26*(1-IF(Inputs!$C$43=1,Inputs!$C$48*(1-EXP(-MAX(1,F10)/Inputs!$C$49)),0))) + Inputs!$C$27 + (Inputs!$C$28*IF(Inputs!$C$43=1,POWER(MAX(1,F10)/Inputs!$C$44,Inputs!$C$46),1)) + (Inputs!$C$29*IF(Inputs!$C$43=1,POWER(MAX(1,F10)/Inputs!$C$44,Inputs!$C$46),1)) + (Inputs!$C$30*IF(Inputs!$C$43=1,POWER(MAX(1,F10)/Inputs!$C$44,Inputs!$C$47),1)) + (MAX(Inputs!$C$50, Inputs!$C$33*IF(Inputs!$C$43=1,EXP(-MAX(1,F10)/Inputs!$C$51),1))*Inputs!$C$34) + (Inputs!$C$10*Inputs!$C$35) + Inputs!$C$16*(1/Inputs!$C$18)*Inputs!$C$17 + Inputs!$C$16*Inputs!$C$19*Inputs!$C$17 + Inputs!$C$16*Inputs!$C$20*(Inputs!$C$22 + Inputs!$C$21*Inputs!$C$17) + Inputs!$C$31*(Inputs!$C$7*(1-Inputs!$C$8) - Inputs!$C$7*(1-Inputs!$C$8)*(Inputs!$C$36 + MAX(Inputs!$C$50, Inputs!$C$33*IF(Inputs!$C$43=1,EXP(-MAX(1,F10)/Inputs!$C$51),1))*Inputs!$C$37 + Inputs!$C$10*Inputs!$C$38)) + Inputs!$C$32) | J10: =Inputs!$C$40 + CEILING(F10/Inputs!$C$42,1)*Inputs!$C$41 | K10: =Scale!$B$15
A11: Safety stock factor (variance) | B11: =1 + B10*(B9/IF(B8=0,1,B8)) + Inputs!$C$52 | F11: 3200 | G11: =F11*I11 - J11 | H11: =F11*(I11-K11) - J11 | I11: =((Inputs!$C$7*(1-Inputs!$C$8) - Inputs!$C$7*(1-Inputs!$C$8)*(Inputs!$C$36 + MAX(Inputs!$C$50, Inputs!$C$33*IF(Inputs!$C$43=1,EXP(-MAX(1,F11)/Inputs!$C$51),1))*Inputs!$C$37 + Inputs!$C$10*Inputs!$C$38))) - (Inputs!$C$16*((Inputs!$C$23*IF(Inputs!$C$43=1,POWER(MAX(1,F11)/Inputs!$C$44,Inputs!$C$45),1))+Inputs!$C$24) + (Inputs!$C$25*(1-IF(Inputs!$C$43=1,Inputs!$C$48*(1-EXP(-MAX(1,F11)/Inputs!$C$49)),0))) + (Inputs!$C$26*(1-IF(Inputs!$C$43=1,Inputs!$C$48*(1-EXP(-MAX(1,F11)/Inputs!$C$49)),0))) + Inputs!$C$27 + (Inputs!$C$28*IF(Inputs!$C$43=1,POWER(MAX(1,F11)/Inputs!$C$44,Inputs!$C$46),1)) + (Inputs!$C$29*IF(Inputs!$C$43=1,POWER(MAX(1,F11)/Inputs!$C$44,Inputs!$C$46),1)) + (Inputs!$C$30*IF(Inputs!$C$43=1,POWER(MAX(1,F11)/Inputs!$C$44,Inputs!$C$47),1)) + (MAX(Inputs!$C$50, Inputs!$C$33*IF(Inputs!$C$43=1,EXP(-MAX(1,F11)/Inputs!$C$51),1))*Inputs!$C$34) + (Inputs!$C$10*Inputs!$C$35) + Inputs!$C$16*(1/Inputs!$C$18)*Inputs!$C$17 + Inputs!$C$16*Inputs!$C$19*Inputs!$C$17 + Inputs!$C$16*Inputs!$C$20*(Inputs!$C$22 + Inputs!$C$21*Inputs!$C$17) + Inputs!$C$31*(Inputs!$C$7*(1-Inputs!$C$8) - Inputs!$C$7*(1-Inputs!$C$8)*(Inputs!$C$36 + MAX(Inputs!$C$50, Inputs!$C$33*IF(Inputs!$C$43=1,EXP(-MAX(1,F11)/Inputs!$C$51),1))*Inputs!$C$37 + Inputs!$C$10*Inputs!$C$38)) + Inputs!$C$32) | J11: =Inputs!$C$40 + CEILING(F11/Inputs!$C$42,1)*Inputs!$C$41 | K11: =Scale!$B$15
A12: Inventory multiple (garments per active user) | B12: =Inputs!$C$16*B8*B11 | F12: 4500 | G12: =F12*I12 - J12 | H12: =F12*(I12-K12) - J12 | I12: =((Inputs!$C$7*(1-Inputs!$C$8) - Inputs!$C$7*(1-Inputs!$C$8)*(Inputs!$C$36 + MAX(Inputs!$C$50, Inputs!$C$33*IF(Inputs!$C$43=1,EXP(-MAX(1,F12)/Inputs!$C$51),1))*Inputs!$C$37 + Inputs!$C$10*Inputs!$C$38))) - (Inputs!$C$16*((Inputs!$C$23*IF(Inputs!$C$43=1,POWER(MAX(1,F12)/Inputs!$C$44,Inputs!$C$45),1))+Inputs!$C$24) + (Inputs!$C$25*(1-IF(Inputs!$C$43=1,Inputs!$C$48*(1-EXP(-MAX(1,F12)/Inputs!$C$49)),0))) + (Inputs!$C$26*(1-IF(Inputs!$C$43=1,Inputs!$C$48*(1-EXP(-MAX(1,F12)/Inputs!$C$49)),0))) + Inputs!$C$27 + (Inputs!$C$28*IF(Inputs!$C$43=1,POWER(MAX(1,F12)/Inputs!$C$44,Inputs!$C$46),1)) + (Inputs!$C$29*IF(Inputs!$C$43=1,POWER(MAX(1,F12)/Inputs!$C$44,Inputs!$C$46),1)) + (Inputs!$C$30*IF(Inputs!$C$43=1,POWER(MAX(1,F12)/Inputs!$C$44,Inputs!$C$47),1)) + (MAX(Inputs!$C$50, Inputs!$C$33*IF(Inputs!$C$43=1,EXP(-MAX(1,F12)/Inputs!$C$51),1))*Inputs!$C$34) + (Inputs!$C$10*Inputs!$C$35) + Inputs!$C$16*(1/Inputs!$C$18)*Inputs!$C$17 + Inputs!$C$16*Inputs!$C$19*Inputs!$C$17 + Inputs!$C$16*Inputs!$C$20*(Inputs!$C$22 + Inputs!$C$21*Inputs!$C$17) + Inputs!$C$31*(Inputs!$C$7*(1-Inputs!$C$8) - Inputs!$C$7*(1-Inputs!$C$8)*(Inputs!$C$36 + MAX(Inputs!$C$50, Inputs!$C$33*IF(Inputs!$C$43=1,EXP(-MAX(1,F12)/Inputs!$C$51),1))*Inputs!$C$37 + Inputs!$C$10*Inputs!$C$38)) + Inputs!$C$32) | J12: =Inputs!$C$40 + CEILING(F12/Inputs!$C$42,1)*Inputs!$C$41 | K12: =Scale!$B$15
A13: Required garments (total) | B13: =$B$3*B12 | F13: 6500 | G13: =F13*I13 - J13 | H13: =F13*(I13-K13) - J13 | I13: =((Inputs!$C$7*(1-Inputs!$C$8) - Inputs!$C$7*(1-Inputs!$C$8)*(Inputs!$C$36 + MAX(Inputs!$C$50, Inputs!$C$33*IF(Inputs!$C$43=1,EXP(-MAX(1,F13)/Inputs!$C$51),1))*Inputs!$C$37 + Inputs!$C$10*Inputs!$C$38))) - (Inputs!$C$16*((Inputs!$C$23*IF(Inputs!$C$43=1,POWER(MAX(1,F13)/Inputs!$C$44,Inputs!$C$45),1))+Inputs!$C$24) + (Inputs!$C$25*(1-IF(Inputs!$C$43=1,Inputs!$C$48*(1-EXP(-MAX(1,F13)/Inputs!$C$49)),0))) + (Inputs!$C$26*(1-IF(Inputs!$C$43=1,Inputs!$C$48*(1-EXP(-MAX(1,F13)/Inputs!$C$49)),0))) + Inputs!$C$27 + (Inputs!$C$28*IF(Inputs!$C$43=1,POWER(MAX(1,F13)/Inputs!$C$44,Inputs!$C$46),1)) + (Inputs!$C$29*IF(Inputs!$C$43=1,POWER(MAX(1,F13)/Inputs!$C$44,Inputs!$C$46),1)) + (Inputs!$C$30*IF(Inputs!$C$43=1,POWER(MAX(1,F13)/Inputs!$C$44,Inputs!$C$47),1)) + (MAX(Inputs!$C$50, Inputs!$C$33*IF(Inputs!$C$43=1,EXP(-MAX(1,F13)/Inputs!$C$51),1))*Inputs!$C$34) + (Inputs!$C$10*Inputs!$C$35) + Inputs!$C$16*(1/Inputs!$C$18)*Inputs!$C$17 + Inputs!$C$16*Inputs!$C$19*Inputs!$C$17 + Inputs!$C$16*Inputs!$C$20*(Inputs!$C$22 + Inputs!$C$21*Inputs!$C$17) + Inputs!$C$31*(Inputs!$C$7*(1-Inputs!$C$8) - Inputs!$C$7*(1-Inputs!$C$8)*(Inputs!$C$36 + MAX(Inputs!$C$50, Inputs!$C$33*IF(Inputs!$C$43=1,EXP(-MAX(1,F13)/Inputs!$C$51),1))*Inputs!$C$37 + Inputs!$C$10*Inputs!$C$38)) + Inputs!$C$32) | J13: =Inputs!$C$40 + CEILING(F13/Inputs!$C$42,1)*Inputs!$C$41 | K13: =Scale!$B$15
A14: Inventory capital (USD) | B14: =B13*Inputs!$C$17 | F14: 9000 | G14: =F14*I14 - J14 | H14: =F14*(I14-K14) - J14 | I14: =((Inputs!$C$7*(1-Inputs!$C$8) - Inputs!$C$7*(1-Inputs!$C$8)*(Inputs!$C$36 + MAX(Inputs!$C$50, Inputs!$C$33*IF(Inputs!$C$43=1,EXP(-MAX(1,F14)/Inputs!$C$51),1))*Inputs!$C$37 + Inputs!$C$10*Inputs!$C$38))) - (Inputs!$C$16*((Inputs!$C$23*IF(Inputs!$C$43=1,POWER(MAX(1,F14)/Inputs!$C$44,Inputs!$C$45),1))+Inputs!$C$24) + (Inputs!$C$25*(1-IF(Inputs!$C$43=1,Inputs!$C$48*(1-EXP(-MAX(1,F14)/Inputs!$C$49)),0))) + (Inputs!$C$26*(1-IF(Inputs!$C$43=1,Inputs!$C$48*(1-EXP(-MAX(1,F14)/Inputs!$C$49)),0))) + Inputs!$C$27 + (Inputs!$C$28*IF(Inputs!$C$43=1,POWER(MAX(1,F14)/Inputs!$C$44,Inputs!$C$46),1)) + (Inputs!$C$29*IF(Inputs!$C$43=1,POWER(MAX(1,F14)/Inputs!$C$44,Inputs!$C$46),1)) + (Inputs!$C$30*IF(Inputs!$C$43=1,POWER(MAX(1,F14)/Inputs!$C$44,Inputs!$C$47),1)) + (MAX(Inputs!$C$50, Inputs!$C$33*IF(Inputs!$C$43=1,EXP(-MAX(1,F14)/Inputs!$C$51),1))*Inputs!$C$34) + (Inputs!$C$10*Inputs!$C$35) + Inputs!$C$16*(1/Inputs!$C$18)*Inputs!$C$17 + Inputs!$C$16*Inputs!$C$19*Inputs!$C$17 + Inputs!$C$16*Inputs!$C$20*(Inputs!$C$22 + Inputs!$C$21*Inputs!$C$17) + Inputs!$C$31*(Inputs!$C$7*(1-Inputs!$C$8) - Inputs!$C$7*(1-Inputs!$C$8)*(Inputs!$C$36 + MAX(Inputs!$C$50, Inputs!$C$33*IF(Inputs!$C$43=1,EXP(-MAX(1,F14)/Inputs!$C$51),1))*Inputs!$C$37 + Inputs!$C$10*Inputs!$C$38)) + Inputs!$C$32) | J14: =Inputs!$C$40 + CEILING(F14/Inputs!$C$42,1)*Inputs!$C$41 | K14: =Scale!$B$15
A15: Capital charge per cycle (constant) | B15: =Inputs!$C$39*(B12*Inputs!$C$17) | F15: 12500 | G15: =F15*I15 - J15 | H15: =F15*(I15-K15) - J15 | I15: =((Inputs!$C$7*(1-Inputs!$C$8) - Inputs!$C$7*(1-Inputs!$C$8)*(Inputs!$C$36 + MAX(Inputs!$C$50, Inputs!$C$33*IF(Inputs!$C$43=1,EXP(-MAX(1,F15)/Inputs!$C$51),1))*Inputs!$C$37 + Inputs!$C$10*Inputs!$C$38))) - (Inputs!$C$16*((Inputs!$C$23*IF(Inputs!$C$43=1,POWER(MAX(1,F15)/Inputs!$C$44,Inputs!$C$45),1))+Inputs!$C$24) + (Inputs!$C$25*(1-IF(Inputs!$C$43=1,Inputs!$C$48*(1-EXP(-MAX(1,F15)/Inputs!$C$49)),0))) + (Inputs!$C$26*(1-IF(Inputs!$C$43=1,Inputs!$C$48*(1-EXP(-MAX(1,F15)/Inputs!$C$49)),0))) + Inputs!$C$27 + (Inputs!$C$28*IF(Inputs!$C$43=1,POWER(MAX(1,F15)/Inputs!$C$44,Inputs!$C$46),1)) + (Inputs!$C$29*IF(Inputs!$C$43=1,POWER(MAX(1,F15)/Inputs!$C$44,Inputs!$C$46),1)) + (Inputs!$C$30*IF(Inputs!$C$43=1,POWER(MAX(1,F15)/Inputs!$C$44,Inputs!$C$47),1)) + (MAX(Inputs!$C$50, Inputs!$C$33*IF(Inputs!$C$43=1,EXP(-MAX(1,F15)/Inputs!$C$51),1))*Inputs!$C$34) + (Inputs!$C$10*Inputs!$C$35) + Inputs!$C$16*(1/Inputs!$C$18)*Inputs!$C$17 + Inputs!$C$16*Inputs!$C$19*Inputs!$C$17 + Inputs!$C$16*Inputs!$C$20*(Inputs!$C$22 + Inputs!$C$21*Inputs!$C$17) + Inputs!$C$31*(Inputs!$C$7*(1-Inputs!$C$8) - Inputs!$C$7*(1-Inputs!$C$8)*(Inputs!$C$36 + MAX(Inputs!$C$50, Inputs!$C$33*IF(Inputs!$C$43=1,EXP(-MAX(1,F15)/Inputs!$C$51),1))*Inputs!$C$37 + Inputs!$C$10*Inputs!$C$38)) + Inputs!$C$32) | J15: =Inputs!$C$40 + CEILING(F15/Inputs!$C$42,1)*Inputs!$C$41 | K15: =Scale!$B$15
F16: 17500 | G16: =F16*I16 - J16 | H16: =F16*(I16-K16) - J16 | I16: =((Inputs!$C$7*(1-Inputs!$C$8) - Inputs!$C$7*(1-Inputs!$C$8)*(Inputs!$C$36 + MAX(Inputs!$C$50, Inputs!$C$33*IF(Inputs!$C$43=1,EXP(-MAX(1,F16)/Inputs!$C$51),1))*Inputs!$C$37 + Inputs!$C$10*Inputs!$C$38))) - (Inputs!$C$16*((Inputs!$C$23*IF(Inputs!$C$43=1,POWER(MAX(1,F16)/Inputs!$C$44,Inputs!$C$45),1))+Inputs!$C$24) + (Inputs!$C$25*(1-IF(Inputs!$C$43=1,Inputs!$C$48*(1-EXP(-MAX(1,F16)/Inputs!$C$49)),0))) + (Inputs!$C$26*(1-IF(Inputs!$C$43=1,Inputs!$C$48*(1-EXP(-MAX(1,F16)/Inputs!$C$49)),0))) + Inputs!$C$27 + (Inputs!$C$28*IF(Inputs!$C$43=1,POWER(MAX(1,F16)/Inputs!$C$44,Inputs!$C$46),1)) + (Inputs!$C$29*IF(Inputs!$C$43=1,POWER(MAX(1,F16)/Inputs!$C$44,Inputs!$C$46),1)) + (Inputs!$C$30*IF(Inputs!$C$43=1,POWER(MAX(1,F16)/Inputs!$C$44,Inputs!$C$47),1)) + (MAX(Inputs!$C$50, Inputs!$C$33*IF(Inputs!$C$43=1,EXP(-MAX(1,F16)/Inputs!$C$51),1))*Inputs!$C$34) + (Inputs!$C$10*Inputs!$C$35) + Inputs!$C$16*(1/Inputs!$C$18)*Inputs!$C$17 + Inputs!$C$16*Inputs!$C$19*Inputs!$C$17 + Inputs!$C$16*Inputs!$C$20*(Inputs!$C$22 + Inputs!$C$21*Inputs!$C$17) + Inputs!$C$31*(Inputs!$C$7*(1-Inputs!$C$8) - Inputs!$C$7*(1-Inputs!$C$8)*(Inputs!$C$36 + MAX(Inputs!$C$50, Inputs!$C$33*IF(Inputs!$C$43=1,EXP(-MAX(1,F16)/Inputs!$C$51),1))*Inputs!$C$37 + Inputs!$C$10*Inputs!$C$38)) + Inputs!$C$32) | J16: =Inputs!$C$40 + CEILING(F16/Inputs!$C$42,1)*Inputs!$C$41 | K16: =Scale!$B$15
F17: 24000 | G17: =F17*I17 - J17 | H17: =F17*(I17-K17) - J17 | I17: =((Inputs!$C$7*(1-Inputs!$C$8) - Inputs!$C$7*(1-Inputs!$C$8)*(Inputs!$C$36 + MAX(Inputs!$C$50, Inputs!$C$33*IF(Inputs!$C$43=1,EXP(-MAX(1,F17)/Inputs!$C$51),1))*Inputs!$C$37 + Inputs!$C$10*Inputs!$C$38))) - (Inputs!$C$16*((Inputs!$C$23*IF(Inputs!$C$43=1,POWER(MAX(1,F17)/Inputs!$C$44,Inputs!$C$45),1))+Inputs!$C$24) + (Inputs!$C$25*(1-IF(Inputs!$C$43=1,Inputs!$C$48*(1-EXP(-MAX(1,F17)/Inputs!$C$49)),0))) + (Inputs!$C$26*(1-IF(Inputs!$C$43=1,Inputs!$C$48*(1-EXP(-MAX(1,F17)/Inputs!$C$49)),0))) + Inputs!$C$27 + (Inputs!$C$28*IF(Inputs!$C$43=1,POWER(MAX(1,F17)/Inputs!$C$44,Inputs!$C$46),1)) + (Inputs!$C$29*IF(Inputs!$C$43=1,POWER(MAX(1,F17)/Inputs!$C$44,Inputs!$C$46),1)) + (Inputs!$C$30*IF(Inputs!$C$43=1,POWER(MAX(1,F17)/Inputs!$C$44,Inputs!$C$47),1)) + (MAX(Inputs!$C$50, Inputs!$C$33*IF(Inputs!$C$43=1,EXP(-MAX(1,F17)/Inputs!$C$51),1))*Inputs!$C$34) + (Inputs!$C$10*Inputs!$C$35) + Inputs!$C$16*(1/Inputs!$C$18)*Inputs!$C$17 + Inputs!$C$16*Inputs!$C$19*Inputs!$C$17 + Inputs!$C$16*Inputs!$C$20*(Inputs!$C$22 + Inputs!$C$21*Inputs!$C$17) + Inputs!$C$31*(Inputs!$C$7*(1-Inputs!$C$8) - Inputs!$C$7*(1-Inputs!$C$8)*(Inputs!$C$36 + MAX(Inputs!$C$50, Inputs!$C$33*IF(Inputs!$C$43=1,EXP(-MAX(1,F17)/Inputs!$C$51),1))*Inputs!$C$37 + Inputs!$C$10*Inputs!$C$38)) + Inputs!$C$32) | J17: =Inputs!$C$40 + CEILING(F17/Inputs!$C$42,1)*Inputs!$C$41 | K17: =Scale!$B$15
A18: Weekly P&L (steady-state, per week) | F18: 33000 | G18: =F18*I18 - J18 | H18: =F18*(I18-K18) - J18 | I18: =((Inputs!$C$7*(1-Inputs!$C$8) - Inputs!$C$7*(1-Inputs!$C$8)*(Inputs!$C$36 + MAX(Inputs!$C$50, Inputs!$C$33*IF(Inputs!$C$43=1,EXP(-MAX(1,F18)/Inputs!$C$51),1))*Inputs!$C$37 + Inputs!$C$10*Inputs!$C$38))) - (Inputs!$C$16*((Inputs!$C$23*IF(Inputs!$C$43=1,POWER(MAX(1,F18)/Inputs!$C$44,Inputs!$C$45),1))+Inputs!$C$24) + (Inputs!$C$25*(1-IF(Inputs!$C$43=1,Inputs!$C$48*(1-EXP(-MAX(1,F18)/Inputs!$C$49)),0))) + (Inputs!$C$26*(1-IF(Inputs!$C$43=1,Inputs!$C$48*(1-EXP(-MAX(1,F18)/Inputs!$C$49)),0))) + Inputs!$C$27 + (Inputs!$C$28*IF(Inputs!$C$43=1,POWER(MAX(1,F18)/Inputs!$C$44,Inputs!$C$46),1)) + (Inputs!$C$29*IF(Inputs!$C$43=1,POWER(MAX(1,F18)/Inputs!$C$44,Inputs!$C$46),1)) + (Inputs!$C$30*IF(Inputs!$C$43=1,POWER(MAX(1,F18)/Inputs!$C$44,Inputs!$C$47),1)) + (MAX(Inputs!$C$50, Inputs!$C$33*IF(Inputs!$C$43=1,EXP(-MAX(1,F18)/Inputs!$C$51),1))*Inputs!$C$34) + (Inputs!$C$10*Inputs!$C$35) + Inputs!$C$16*(1/Inputs!$C$18)*Inputs!$C$17 + Inputs!$C$16*Inputs!$C$19*Inputs!$C$17 + Inputs!$C$16*Inputs!$C$20*(Inputs!$C$22 + Inputs!$C$21*Inputs!$C$17) + Inputs!$C$31*(Inputs!$C$7*(1-Inputs!$C$8) - Inputs!$C$7*(1-Inputs!$C$8)*(Inputs!$C$36 + MAX(Inputs!$C$50, Inputs!$C$33*IF(Inputs!$C$43=1,EXP(-MAX(1,F18)/Inputs!$C$51),1))*Inputs!$C$37 + Inputs!$C$10*Inputs!$C$38)) + Inputs!$C$32) | J18: =Inputs!$C$40 + CEILING(F18/Inputs!$C$42,1)*Inputs!$C$41 | K18: =Scale!$B$15
A19: User-week cycles fulfilled | B19: =$B$3 | F19: 45000 | G19: =F19*I19 - J19 | H19: =F19*(I19-K19) - J19 | I19: =((Inputs!$C$7*(1-Inputs!$C$8) - Inputs!$C$7*(1-Inputs!$C$8)*(Inputs!$C$36 + MAX(Inputs!$C$50, Inputs!$C$33*IF(Inputs!$C$43=1,EXP(-MAX(1,F19)/Inputs!$C$51),1))*Inputs!$C$37 + Inputs!$C$10*Inputs!$C$38))) - (Inputs!$C$16*((Inputs!$C$23*IF(Inputs!$C$43=1,POWER(MAX(1,F19)/Inputs!$C$44,Inputs!$C$45),1))+Inputs!$C$24) + (Inputs!$C$25*(1-IF(Inputs!$C$43=1,Inputs!$C$48*(1-EXP(-MAX(1,F19)/Inputs!$C$49)),0))) + (Inputs!$C$26*(1-IF(Inputs!$C$43=1,Inputs!$C$48*(1-EXP(-MAX(1,F19)/Inputs!$C$49)),0))) + Inputs!$C$27 + (Inputs!$C$28*IF(Inputs!$C$43=1,POWER(MAX(1,F19)/Inputs!$C$44,Inputs!$C$46),1)) + (Inputs!$C$29*IF(Inputs!$C$43=1,POWER(MAX(1,F19)/Inputs!$C$44,Inputs!$C$46),1)) + (Inputs!$C$30*IF(Inputs!$C$43=1,POWER(MAX(1,F19)/Inputs!$C$44,Inputs!$C$47),1)) + (MAX(Inputs!$C$50, Inputs!$C$33*IF(Inputs!$C$43=1,EXP(-MAX(1,F19)/Inputs!$C$51),1))*Inputs!$C$34) + (Inputs!$C$10*Inputs!$C$35) + Inputs!$C$16*(1/Inputs!$C$18)*Inputs!$C$17 + Inputs!$C$16*Inputs!$C$19*Inputs!$C$17 + Inputs!$C$16*Inputs!$C$20*(Inputs!$C$22 + Inputs!$C$21*Inputs!$C$17) + Inputs!$C$31*(Inputs!$C$7*(1-Inputs!$C$8) - Inputs!$C$7*(1-Inputs!$C$8)*(Inputs!$C$36 + MAX(Inputs!$C$50, Inputs!$C$33*IF(Inputs!$C$43=1,EXP(-MAX(1,F19)/Inputs!$C$51),1))*Inputs!$C$37 + Inputs!$C$10*Inputs!$C$38)) + Inputs!$C$32) | J19: =Inputs!$C$40 + CEILING(F19/Inputs!$C$42,1)*Inputs!$C$41 | K19: =Scale!$B$15
A20: Net revenue per cycle | B20: =UnitEconomics!$B$18 | F20: 60000 | G20: =F20*I20 - J20 | H20: =F20*(I20-K20) - J20 | I20: =((Inputs!$C$7*(1-Inputs!$C$8) - Inputs!$C$7*(1-Inputs!$C$8)*(Inputs!$C$36 + MAX(Inputs!$C$50, Inputs!$C$33*IF(Inputs!$C$43=1,EXP(-MAX(1,F20)/Inputs!$C$51),1))*Inputs!$C$37 + Inputs!$C$10*Inputs!$C$38))) - (Inputs!$C$16*((Inputs!$C$23*IF(Inputs!$C$43=1,POWER(MAX(1,F20)/Inputs!$C$44,Inputs!$C$45),1))+Inputs!$C$24) + (Inputs!$C$25*(1-IF(Inputs!$C$43=1,Inputs!$C$48*(1-EXP(-MAX(1,F20)/Inputs!$C$49)),0))) + (Inputs!$C$26*(1-IF(Inputs!$C$43=1,Inputs!$C$48*(1-EXP(-MAX(1,F20)/Inputs!$C$49)),0))) + Inputs!$C$27 + (Inputs!$C$28*IF(Inputs!$C$43=1,POWER(MAX(1,F20)/Inputs!$C$44,Inputs!$C$46),1)) + (Inputs!$C$29*IF(Inputs!$C$43=1,POWER(MAX(1,F20)/Inputs!$C$44,Inputs!$C$46),1)) + (Inputs!$C$30*IF(Inputs!$C$43=1,POWER(MAX(1,F20)/Inputs!$C$44,Inputs!$C$47),1)) + (MAX(Inputs!$C$50, Inputs!$C$33*IF(Inputs!$C$43=1,EXP(-MAX(1,F20)/Inputs!$C$51),1))*Inputs!$C$34) + (Inputs!$C$10*Inputs!$C$35) + Inputs!$C$16*(1/Inputs!$C$18)*Inputs!$C$17 + Inputs!$C$16*Inputs!$C$19*Inputs!$C$17 + Inputs!$C$16*Inputs!$C$20*(Inputs!$C$22 + Inputs!$C$21*Inputs!$C$17) + Inputs!$C$31*(Inputs!$C$7*(1-Inputs!$C$8) - Inputs!$C$7*(1-Inputs!$C$8)*(Inputs!$C$36 + MAX(Inputs!$C$50, Inputs!$C$33*IF(Inputs!$C$43=1,EXP(-MAX(1,F20)/Inputs!$C$51),1))*Inputs!$C$37 + Inputs!$C$10*Inputs!$C$38)) + Inputs!$C$32) | J20: =Inputs!$C$40 + CEILING(F20/Inputs!$C$42,1)*Inputs!$C$41 | K20: =Scale!$B$15
A21: Variable cost per cycle | B21: =UnitEconomics!$B$32 | F21: 80000 | G21: =F21*I21 - J21 | H21: =F21*(I21-K21) - J21 | I21: =((Inputs!$C$7*(1-Inputs!$C$8) - Inputs!$C$7*(1-Inputs!$C$8)*(Inputs!$C$36 + MAX(Inputs!$C$50, Inputs!$C$33*IF(Inputs!$C$43=1,EXP(-MAX(1,F21)/Inputs!$C$51),1))*Inputs!$C$37 + Inputs!$C$10*Inputs!$C$38))) - (Inputs!$C$16*((Inputs!$C$23*IF(Inputs!$C$43=1,POWER(MAX(1,F21)/Inputs!$C$44,Inputs!$C$45),1))+Inputs!$C$24) + (Inputs!$C$25*(1-IF(Inputs!$C$43=1,Inputs!$C$48*(1-EXP(-MAX(1,F21)/Inputs!$C$49)),0))) + (Inputs!$C$26*(1-IF(Inputs!$C$43=1,Inputs!$C$48*(1-EXP(-MAX(1,F21)/Inputs!$C$49)),0))) + Inputs!$C$27 + (Inputs!$C$28*IF(Inputs!$C$43=1,POWER(MAX(1,F21)/Inputs!$C$44,Inputs!$C$46),1)) + (Inputs!$C$29*IF(Inputs!$C$43=1,POWER(MAX(1,F21)/Inputs!$C$44,Inputs!$C$46),1)) + (Inputs!$C$30*IF(Inputs!$C$43=1,POWER(MAX(1,F21)/Inputs!$C$44,Inputs!$C$47),1)) + (MAX(Inputs!$C$50, Inputs!$C$33*IF(Inputs!$C$43=1,EXP(-MAX(1,F21)/Inputs!$C$51),1))*Inputs!$C$34) + (Inputs!$C$10*Inputs!$C$35) + Inputs!$C$16*(1/Inputs!$C$18)*Inputs!$C$17 + Inputs!$C$16*Inputs!$C$19*Inputs!$C$17 + Inputs!$C$16*Inputs!$C$20*(Inputs!$C$22 + Inputs!$C$21*Inputs!$C$17) + Inputs!$C$31*(Inputs!$C$7*(1-Inputs!$C$8) - Inputs!$C$7*(1-Inputs!$C$8)*(Inputs!$C$36 + MAX(Inputs!$C$50, Inputs!$C$33*IF(Inputs!$C$43=1,EXP(-MAX(1,F21)/Inputs!$C$51),1))*Inputs!$C$37 + Inputs!$C$10*Inputs!$C$38)) + Inputs!$C$32) | J21: =Inputs!$C$40 + CEILING(F21/Inputs!$C$42,1)*Inputs!$C$41 | K21: =Scale!$B$15
A22: Contribution per cycle | B22: =UnitEconomics!$B$33 | F22: 100000 | G22: =F22*I22 - J22 | H22: =F22*(I22-K22) - J22 | I22: =((Inputs!$C$7*(1-Inputs!$C$8) - Inputs!$C$7*(1-Inputs!$C$8)*(Inputs!$C$36 + MAX(Inputs!$C$50, Inputs!$C$33*IF(Inputs!$C$43=1,EXP(-MAX(1,F22)/Inputs!$C$51),1))*Inputs!$C$37 + Inputs!$C$10*Inputs!$C$38))) - (Inputs!$C$16*((Inputs!$C$23*IF(Inputs!$C$43=1,POWER(MAX(1,F22)/Inputs!$C$44,Inputs!$C$45),1))+Inputs!$C$24) + (Inputs!$C$25*(1-IF(Inputs!$C$43=1,Inputs!$C$48*(1-EXP(-MAX(1,F22)/Inputs!$C$49)),0))) + (Inputs!$C$26*(1-IF(Inputs!$C$43=1,Inputs!$C$48*(1-EXP(-MAX(1,F22)/Inputs!$C$49)),0))) + Inputs!$C$27 + (Inputs!$C$28*IF(Inputs!$C$43=1,POWER(MAX(1,F22)/Inputs!$C$44,Inputs!$C$46),1)) + (Inputs!$C$29*IF(Inputs!$C$43=1,POWER(MAX(1,F22)/Inputs!$C$44,Inputs!$C$46),1)) + (Inputs!$C$30*IF(Inputs!$C$43=1,POWER(MAX(1,F22)/Inputs!$C$44,Inputs!$C$47),1)) + (MAX(Inputs!$C$50, Inputs!$C$33*IF(Inputs!$C$43=1,EXP(-MAX(1,F22)/Inputs!$C$51),1))*Inputs!$C$34) + (Inputs!$C$10*Inputs!$C$35) + Inputs!$C$16*(1/Inputs!$C$18)*Inputs!$C$17 + Inputs!$C$16*Inputs!$C$19*Inputs!$C$17 + Inputs!$C$16*Inputs!$C$20*(Inputs!$C$22 + Inputs!$C$21*Inputs!$C$17) + Inputs!$C$31*(Inputs!$C$7*(1-Inputs!$C$8) - Inputs!$C$7*(1-Inputs!$C$8)*(Inputs!$C$36 + MAX(Inputs!$C$50, Inputs!$C$33*IF(Inputs!$C$43=1,EXP(-MAX(1,F22)/Inputs!$C$51),1))*Inputs!$C$37 + Inputs!$C$10*Inputs!$C$38)) + Inputs!$C$32) | J22: =Inputs!$C$40 + CEILING(F22/Inputs!$C$42,1)*Inputs!$C$41 | K22: =Scale!$B$15
A23: Total contribution (weekly) | B23: =B19*B22
A24: Capital charge per cycle | B24: =B15
A25: Economic contribution per cycle | B25: =B22-B24
A26: Economic contribution (weekly) | B26: =B19*B25
A28: Fixed OPEX & capacity steps
A29: Sites required | B29: =CEILING($B$3/Inputs!$C$42,1)
A30: Fixed OPEX (weekly) | B30: =Inputs!$C$40 + B29*Inputs!$C$41
A31: Operating profit (weekly, CM - fixed) | B31: =B23-B30
A32: Economic profit (weekly, after capital) | B32: =B26-B30
A34: Break-even active users (CM basis) | B34: =IF(B22<=0,"",B30/B22)
A35: Break-even active users (economic CM basis) | B35: =IF(B25<=0,"",B30/B25)
A37: Replacement flow (loss + damage retire + wear retire)
A38: Replacement garments per week | B38: =$B$3*Inputs!$C$16*(Inputs!$C$19 + Inputs!$C$20*Inputs!$C$21 + 1/Inputs!$C$18)
A39: Replacement spend per week | B39: =B38*Inputs!$C$17
A40: Replacement spend per cycle | B40: =IF($B$3=0,0,B39/$B$3)

Sheet Cohorts
A1: Cohort Retention Layer (age-based churn with service-failure shock)
A3: Linked inputs
A4: Horizon (weeks) | B4: =Inputs!$C$62
A5: Start active users | B5: =Inputs!$C$63
A6: Base churn (weekly) | B6: =Inputs!$C$82
A7: Early churn premium | B7: =Inputs!$C$83
A8: Churn decay (weeks) | B8: =Inputs!$C$84
A9: Churn curve by age-week (used for baseline churn weighting; shock applied separately)
A10: Age_wk | B10: Churn_rate | C10: Survival
A11: 0 | B11: =MIN(0.8, Inputs!$C$82*(1+Inputs!$C$83*EXP(-A11/MAX(0.0001,Inputs!$C$84)))) | C11: =1-B11
A12: 1 | B12: =MIN(0.8, Inputs!$C$82*(1+Inputs!$C$83*EXP(-A12/MAX(0.0001,Inputs!$C$84)))) | C12: =1-B12
A13: 2 | B13: =MIN(0.8, Inputs!$C$82*(1+Inputs!$C$83*EXP(-A13/MAX(0.0001,Inputs!$C$84)))) | C13: =1-B13
A14: 3 | B14: =MIN(0.8, Inputs!$C$82*(1+Inputs!$C$83*EXP(-A14/MAX(0.0001,Inputs!$C$84)))) | C14: =1-B14
A15: 4 | B15: =MIN(0.8, Inputs!$C$82*(1+Inputs!$C$83*EXP(-A15/MAX(0.0001,Inputs!$C$84)))) | C15: =1-B15
A16: 5 | B16: =MIN(0.8, Inputs!$C$82*(1+Inputs!$C$83*EXP(-A16/MAX(0.0001,Inputs!$C$84)))) | C16: =1-B16
A17: 6 | B17: =MIN(0.8, Inputs!$C$82*(1+Inputs!$C$83*EXP(-A17/MAX(0.0001,Inputs!$C$84)))) | C17: =1-B17
A18: 7 | B18: =MIN(0.8, Inputs!$C$82*(1+Inputs!$C$83*EXP(-A18/MAX(0.0001,Inputs!$C$84)))) | C18: =1-B18
A19: 8 | B19: =MIN(0.8, Inputs!$C$82*(1+Inputs!$C$83*EXP(-A19/MAX(0.0001,Inputs!$C$84)))) | C19: =1-B19
A20: 9 | B20: =MIN(0.8, Inputs!$C$82*(1+Inputs!$C$83*EXP(-A20/MAX(0.0001,Inputs!$C$84)))) | C20: =1-B20
A21: 10 | B21: =MIN(0.8, Inputs!$C$82*(1+Inputs!$C$83*EXP(-A21/MAX(0.0001,Inputs!$C$84)))) | C21: =1-B21
A22: 11 | B22: =MIN(0.8, Inputs!$C$82*(1+Inputs!$C$83*EXP(-A22/MAX(0.0001,Inputs!$C$84)))) | C22: =1-B22
... A63: 52 | B63: =MIN(0.8, Inputs!$C$82*(1+Inputs!$C$83*EXP(-A63/MAX(0.0001,Inputs!$C$84)))) | C63: =1-B63
A66: Week | B66: Carryover_Users | C66: New_Users | D66: Active_Service | E66: Churn_Shock | F66: Baseline_Churn_Rate | G66: Total_Churn_Rate | H66: Churned | I66: Survivors_End | L66: Age0 | M66: Age1 | N66: Age2 | O66: Age3 | P66: Age4 | Q66: Age5 | R66: Age6 | S66: Age7 | T66: Age8 | U66: Age9 | V66: Age10 | W66: Age11 | X66: Age12 | Y66: Age13 | Z66: Age14 | AA66: Age15 | AB66: Age16 | AC66: Age17 | AD66: Age18 | AE66: Age19 | AF66: Age20 | AG66: Age21 | AH66: Age22 | AI66: Age23 | AJ66: Age24 | AK66: Age25 | AL66: Age26 | AM66: Age27 | AN66: Age28 | AO66: Age29 | AP66: Age30 | AQ66: Age31 | AR66: Age32 | AS66: Age33 | AT66: Age34 | AU66: Age35 | AV66: Age36 | AW66: Age37 | AX66: Age38 | AY66: Age39 | AZ66: Age40 | BA66: Age41 | BB66: Age42 | BC66: Age43 | BD66: Age44 | BE66: Age45 | BF66: Age46 | BG66: Age47 | BH66: Age48 | BI66: Age49 | BJ66: Age50 | BK66: Age51 | BL66: Age52+
A67: 1 | B67: =IF(A67>Inputs!$C$62,"",SUM(M67:BK67)) | C67: =IF(A67>Inputs!$C$62,"",INDEX(Trajectory!$C$23:$C$2000,A67)) | D67: =IF(A67>Inputs!$C$62,"",SUM(L67:BK67)) | E67: =IF(A67>Inputs!$C$62,"",INDEX(Trajectory!$AG$23:$AG$2000,A67)) | F67: =IF(D67=0,0,SUMPRODUCT(L67:BK67,$B$11:$B$63)/D67) | G67: =IF(D67=0,0,MIN(0.95,1-(1-F67)*(1-E67))) | H67: =IF(D67=0,0,D67*G67) | I67: =IF(D67=0,0,D67-H67) | L67: =C67 | M67: 0 | N67: 0 | O67: 0 | P67: 0 | Q67: 0 | R67: 0 | S67: 0 | T67: 0 | U67: 0 | V67: 0 | W67: 0 | X67: 0 | Y67: 0 | Z67: 0 | AA67: 0 | AB67: 0 | AC67: 0 | AD67: 0 | AE67: 0 | AF67: 0 | AG67: 0 | AH67: 0 | AI67: 0 | AJ67: 0 | AK67: 0 | AL67: 0 | AM67: 0 | AN67: 0 | AO67: 0 | AP67: 0 | AQ67: 0 | AR67: 0 | AS67: 0 | AT67: 0 | AU67: 0 | AV67: 0 | AW67: 0 | AX67: 0 | AY67: 0 | AZ67: 0 | BA67: 0 | BB67: 0 | BC67: 0 | BD67: 0 | BE67: 0 | BF67: 0 | BG67: 0 | BH67: 0 | BI67: 0 | BJ67: 0 | BK67: 0 | BL67: =Inputs!$C$63
A68: 2 | B68: =IF(A68>Inputs!$C$62,"",SUM(M68:BK68)) | C68: =IF(A68>Inputs!$C$62,"",INDEX(Trajectory!$C$23:$C$2000,A68)) | D68: =IF(A68>Inputs!$C$62,"",SUM(L68:BK68)) | E68: =IF(A68>Inputs!$C$62,"",INDEX(Trajectory!$AG$23:$AG$2000,A68)) | F68: =IF(D68=0,0,SUMPRODUCT(L68:BK68,$B$11:$B$63)/D68) | G68: =IF(D68=0,0,MIN(0.95,1-(1-F68)*(1-E68))) | H68: =IF(D68=0,0,D68*G68) | I68: =IF(D68=0,0,D68-H68) | L68: =C68 | M68: =MAX(0,L67*(1-INDEX($B$11:$B$63,1))*(1-E67)) | N68: =MAX(0,M67*(1-INDEX($B$11:$B$63,2))*(1-E67)) | O68: =MAX(0,N67*(1-INDEX($B$11:$B$63,3))*(1-E67)) | P68: =MAX(0,O67*(1-INDEX($B$11:$B$63,4))*(1-E67)) | Q68: =MAX(0,P67*(1-INDEX($B$11:$B$63,5))*(1-E67)) | R68: =MAX(0,Q67*(1-INDEX($B$11:$B$63,6))*(1-E67)) | S68: =MAX(0,R67*(1-INDEX($B$11:$B$63,7))*(1-E67)) | T68: =MAX(0,S67*(1-INDEX($B$11:$B$63,8))*(1-E67)) | U68: =MAX(0,T67*(1-INDEX($B$11:$B$63,9))*(1-E67)) | V68: =MAX(0,U67*(1-INDEX($B$11:$B$63,10))*(1-E67)) | W68: =MAX(0,V67*(1-INDEX($B$11:$B$63,11))*(1-E67)) | X68: =MAX(0,W67*(1-INDEX($B$11:$B$63,12))*(1-E67)) | Y68: =MAX(0,X67*(1-INDEX($B$11:$B$63,13))*(1-E67)) | Z68: =MAX(0,Y67*(1-INDEX($B$11:$B$63,14))*(1-E67)) | AA68: =MAX(0,Z67*(1-INDEX($B$11:$B$63,15))*(1-E67)) | AB68: =MAX(0,AA67*(1-INDEX($B$11:$B$63,16))*(1-E67)) | AC68: =MAX(0,AB67*(1-INDEX($B$11:$B$63,17))*(1-E67)) | AD68: =MAX(0,AC67*(1-INDEX($B$11:$B$63,18))*(1-E67)) | AE68: =MAX(0,AD67*(1-INDEX($B$11:$B$63,19))*(1-E67)) | AF68: =MAX(0,AE67*(1-INDEX($B$11:$B$63,20))*(1-E67)) | AG68: =MAX(0,AF67*(1-INDEX($B$11:$B$63,21))*(1-E67)) | AH68: =MAX(0,AG67*(1-INDEX($B$11:$B$63,22))*(1-E67)) | AI68: =MAX(0,AH67*(1-INDEX($B$11:$B$63,23))*(1-E67)) | AJ68: =MAX(0,AI67*(1-INDEX($B$11:$B$63,24))*(1-E67)) | AK68: =MAX(0,AJ67*(1-INDEX($B$11:$B$63,25))*(1-E67)) | AL68: =MAX(0,AK67*(1-INDEX($B$11:$B$63,26))*(1-E67)) | AM68: =MAX(0,AL67*(1-INDEX($B$11:$B$63,27))*(1-E67)) | AN68: =MAX(0,AM67*(1-INDEX($B$11:$B$63,28))*(1-E67)) | AO68: =MAX(0,AN67*(1-INDEX($B$11:$B$63,29))*(1-E67)) | AP68: =MAX(0,AO67*(1-INDEX($B$11:$B$63,30))*(1-E67)) | AQ68: =MAX(0,AP67*(1-INDEX($B$11:$B$63,31))*(1-E67)) | AR68: =MAX(0,AQ67*(1-INDEX($B$11:$B$63,32))*(1-E67)) | AS68: =MAX(0,AR67*(1-INDEX($B$11:$B$63,33))*(1-E67)) | AT68: =MAX(0,AS67*(1-INDEX($B$11:$B$63,34))*(1-E67)) | AU68: =MAX(0,AT67*(1-INDEX($B$11:$B$63,35))*(1-E67)) | AV68: =MAX(0,AU67*(1-INDEX($B$11:$B$63,36))*(1-E67)) | AW68: =MAX(0,AV67*(1-INDEX($B$11:$B$63,37))*(1-E67)) | AX68: =MAX(0,AW67*(1-INDEX($B$11:$B$63,38))*(1-E67)) | AY68: =MAX(0,AX67*(1-INDEX($B$11:$B$63,39))*(1-E67)) | AZ68: =MAX(0,AY67*(1-INDEX($B$11:$B$63,40))*(1-E67)) | BA68: =MAX(0,AZ67*(1-INDEX($B$11:$B$63,41))*(1-E67)) | BB68: =MAX(0,BA67*(1-INDEX($B$11:$B$63,42))*(1-E67)) | BC68: =MAX(0,BB67*(1-INDEX($B$11:$B$63,43))*(1-E67)) | BD68: =MAX(0,BC67*(1-INDEX($B$11:$B$63,44))*(1-E67)) | BE68: =MAX(0,BD67*(1-INDEX($B$11:$B$63,45))*(1-E67)) | BF68: =MAX(0,BE67*(1-INDEX($B$11:$B$63,46))*(1-E67)) | BG68: =MAX(0,BF67*(1-INDEX($B$11:$B$63,47))*(1-E67)) | BH68: =MAX(0,BG67*(1-INDEX($B$11:$B$63,48))*(1-E67)) | BI68: =MAX(0,BH67*(1-INDEX($B$11:$B$63,49))*(1-E67)) | BJ68: =MAX(0,BI67*(1-INDEX($B$11:$B$63,50))*(1-E67)) | BK68: =MAX(0,BJ67*(1-INDEX($B$11:$B$63,51))*(1-E67)) | BL68: =MAX(0,(BL67+BK67)*(1-INDEX($B$11:$B$63,53))*(1-E67))
A69: 3 | B69: =IF(A69>Inputs!$C$62,"",SUM(M69:BK69)) | C69: =IF(A69>Inputs!$C$62,"",INDEX(Trajectory!$C$23:$C$2000,A69)) | D69: =IF(A69>Inputs!$C$62,"",SUM(L69:BK69)) | E69: =IF(A69>Inputs!$C$62,"",INDEX(Trajectory!$AG$23:$AG$2000,A69)) | F69: =IF(D69=0,0,SUMPRODUCT(L69:BK69,$B$11:$B$63)/D69) | G69: =IF(D69=0,0,MIN(0.95,1-(1-F69)*(1-E69))) | H69: =IF(D69=0,0,D69*G69) | I69: =IF(D69=0,0,D69-H69) | L69: =C69 | M69: =MAX(0,L68*(1-INDEX($B$11:$B$63,1))*(1-E68)) | N69: =MAX(0,M68*(1-INDEX($B$11:$B$63,2))*(1-E68)) | O69: =MAX(0,N68*(1-INDEX($B$11:$B$63,3))*(1-E68)) | P69: =MAX(0,O68*(1-INDEX($B$11:$B$63,4))*(1-E68)) | Q69: =MAX(0,P68*(1-INDEX($B$11:$B$63,5))*(1-E68)) | R69: =MAX(0,Q68*(1-INDEX($B$11:$B$63,6))*(1-E68)) | S69: =MAX(0,R68*(1-INDEX($B$11:$B$63,7))*(1-E68)) | T69: =MAX(0,S68*(1-INDEX($B$11:$B$63,8))*(1-E68)) | U69: =MAX(0,T68*(1-INDEX($B$11:$B$63,9))*(1-E68)) | V69: =MAX(0,U68*(1-INDEX($B$11:$B$63,10))*(1-E68)) | W69: =MAX(0,V68*(1-INDEX($B$11:$B$63,11))*(1-E68)) | X69: =MAX(0,W68*(1-INDEX($B$11:$B$63,12))*(1-E68)) | Y69: =MAX(0,X68*(1-INDEX($B$11:$B$63,13))*(1-E68)) | Z69: =MAX(0,Y68*(1-INDEX($B$11:$B$63,14))*(1-E68)) | AA69: =MAX(0,Z68*(1-INDEX($B$11:$B$63,15))*(1-E68)) | AB69: =MAX(0,AA68*(1-INDEX($B$11:$B$63,16))*(1-E68)) | AC69: =MAX(0,AB68*(1-INDEX($B$11:$B$63,17))*(1-E68)) | AD69: =MAX(0,AC68*(1-INDEX($B$11:$B$63,18))*(1-E68)) | AE69: =MAX(0,AD68*(1-INDEX($B$11:$B$63,19))*(1-E68)) | AF69: =MAX(0,AE68*(1-INDEX($B$11:$B$63,20))*(1-E68)) | AG69: =MAX(0,AF68*(1-INDEX($B$11:$B$63,21))*(1-E68)) | AH69: =MAX(0,AG68*(1-INDEX($B$11:$B$63,22))*(1-E68)) | AI69: =MAX(0,AH68*(1-INDEX($B$11:$B$63,23))*(1-E68)) | AJ69: =MAX(0,AI68*(1-INDEX($B$11:$B$63,24))*(1-E68)) | AK69: =MAX(0,AJ68*(1-INDEX($B$11:$B$63,25))*(1-E68)) | AL69: =MAX(0,AK68*(1-INDEX($B$11:$B$63,26))*(1-E68)) | AM69: =MAX(0,AL68*(1-INDEX($B$11:$B$63,27))*(1-E68)) | AN69: =MAX(0,AM68*(1-INDEX($B$11:$B$63,28))*(1-E68)) | AO69: =MAX(0,AN68*(1-INDEX($B$11:$B$63,29))*(1-E68)) | AP69: =MAX(0,AO68*(1-INDEX($B$11:$B$63,30))*(1-E68)) | AQ69: =MAX(0,AP68*(1-INDEX($B$11:$B$63,31))*(1-E68)) | AR69: =MAX(0,AQ68*(1-INDEX($B$11:$B$63,32))*(1-E68)) | AS69: =MAX(0,AR68*(1-INDEX($B$11:$B$63,33))*(1-E68)) | AT69: =MAX(0,AS68*(1-INDEX($B$11:$B$63,34))*(1-E68)) | AU69: =MAX(0,AT68*(1-INDEX($B$11:$B$63,35))*(1-E68)) | AV69: =MAX(0,AU68*(1-INDEX($B$11:$B$63,36))*(1-E68)) | AW69: =MAX(0,AV68*(1-INDEX($B$11:$B$63,37))*(1-E68)) | AX69: =MAX(0,AW68*(1-INDEX($B$11:$B$63,38))*(1-E68)) | AY69: =MAX(0,AX68*(1-INDEX($B$11:$B$63,39))*(1-E68)) | AZ69: =MAX(0,AY68*(1-INDEX($B$11:$B$63,40))*(1-E68)) | BA69: =MAX(0,AZ68*(1-INDEX($B$11:$B$63,41))*(1-E68)) | BB69: =MAX(0,BA68*(1-INDEX($B$11:$B$63,42))*(1-E68)) | BC69: =MAX(0,BB68*(1-INDEX($B$11:$B$63,43))*(1-E68)) | BD69: =MAX(0,BC68*(1-INDEX($B$11:$B$63,44))*(1-E68)) | BE69: =MAX(0,BD68*(1-INDEX($B$11:$B$63,45))*(1-E68)) | BF69: =MAX(0,BE68*(1-INDEX($B$11:$B$63,46))*(1-E68)) | BG69: =MAX(0,BF68*(1-INDEX($B$11:$B$63,47))*(1-E68)) | BH69: =MAX(0,BG68*(1-INDEX($B$11:$B$63,48))*(1-E68)) | BI69: =MAX(0,BH68*(1-INDEX($B$11:$B$63,49))*(1-E68)) | BJ69: =MAX(0,BI68*(1-INDEX($B$11:$B$63,50))*(1-E68)) | BK69: =MAX(0,BJ68*(1-INDEX($B$11:$B$63,51))*(1-E68)) | BL69: =MAX(0,(BL68+BK68)*(1-INDEX($B$11:$B$63,53))*(1-E68))
A70: 4 | B70: =IF(A70>Inputs!$C$62,"",SUM(M70:BK70)) | C70: =IF(A70>Inputs!$C$62,"",INDEX(Trajectory!$C$23:$C$2000,A70)) | D70: =IF(A70>Inputs!$C$62,"",SUM(L70:BK70)) | E70: =IF(A70>Inputs!$C$62,"",INDEX(Trajectory!$AG$23:$AG$2000,A70)) | F70: =IF(D70=0,0,SUMPRODUCT(L70:BK70,$B$11:$B$63)/D70) | G70: =IF(D70=0,0,MIN(0.95,1-(1-F70)*(1-E70))) | H70: =IF(D70=0,0,D70*G70) | I70: =IF(D70=0,0,D70-H70) | L70: =C70 | M70: =MAX(0,L69*(1-INDEX($B$11:$B$63,1))*(1-E69)) | N70: =MAX(0,M69*(1-INDEX($B$11:$B$63,2))*(1-E69)) | O70: =MAX(0,N69*(1-INDEX($B$11:$B$63,3))*(1-E69)) | P70: =MAX(0,O69*(1-INDEX($B$11:$B$63,4))*(1-E69)) | Q70: =MAX(0,P69*(1-INDEX($B$11:$B$63,5))*(1-E69)) | R70: =MAX(0,Q69*(1-INDEX($B$11:$B$63,6))*(1-E69)) | S70: =MAX(0,R69*(1-INDEX($B$11:$B$63,7))*(1-E69)) | T70: =MAX(0,S69*(1-INDEX($B$11:$B$63,8))*(1-E69)) | U70: =MAX(0,T69*(1-INDEX($B$11:$B$63,9))*(1-E69)) | V70: =MAX(0,U69*(1-INDEX($B$11:$B$63,10))*(1-E69)) | W70: =MAX(0,V69*(1-INDEX($B$11:$B$63,11))*(1-E69)) | X70: =MAX(0,W69*(1-INDEX($B$11:$B$63,12))*(1-E69)) | Y70: =MAX(0,X69*(1-INDEX($B$11:$B$63,13))*(1-E69)) | Z70: =MAX(0,Y69*(1-INDEX($B$11:$B$63,14))*(1-E69)) | AA70: =MAX(0,Z69*(1-INDEX($B$11:$B$63,15))*(1-E69)) | AB70: =MAX(0,AA69*(1-INDEX($B$11:$B$63,16))*(1-E69)) | AC70: =MAX(0,AB69*(1-INDEX($B$11:$B$63,17))*(1-E69)) | AD70: =MAX(0,AC69*(1-INDEX($B$11:$B$63,18))*(1-E69)) | AE70: =MAX(0,AD69*(1-INDEX($B$11:$B$63,19))*(1-E69)) | AF70: =MAX(0,AE69*(1-INDEX($B$11:$B$63,20))*(1-E69)) | AG70: =MAX(0,AF69*(1-INDEX($B$11:$B$63,21))*(1-E69)) | AH70: =MAX(0,AG69*(1-INDEX($B$11:$B$63,22))*(1-E69)) | AI70: =MAX(0,AH69*(1-INDEX($B$11:$B$63,23))*(1-E69)) | AJ70: =MAX(0,AI69*(1-INDEX($B$11:$B$63,24))*(1-E69)) | AK70: =MAX(0,AJ69*(1-INDEX($B$11:$B$63,25))*(1-E69)) | AL70: =MAX(0,AK69*(1-INDEX($B$11:$B$63,26))*(1-E69)) | AM70: =MAX(0,AL69*(1-INDEX($B$11:$B$63,27))*(1-E69)) | AN70: =MAX(0,AM69*(1-INDEX($B$11:$B$63,28))*(1-E69)) | AO70: =MAX(0,AN69*(1-INDEX($B$11:$B$63,29))*(1-E69)) | AP70: =MAX(0,AO69*(1-INDEX($B$11:$B$63,30))*(1-E69)) | AQ70: =MAX(0,AP69*(1-INDEX($B$11:$B$63,31))*(1-E69)) | AR70: =MAX(0,AQ69*(1-INDEX($B$11:$B$63,32))*(1-E69)) | AS70: =MAX(0,AR69*(1-INDEX($B$11:$B$63,33))*(1-E69)) | AT70: =MAX(0,AS69*(1-INDEX($B$11:$B$63,34))*(1-E69)) | AU70: =MAX(0,AT69*(1-INDEX($B$11:$B$63,35))*(1-E69)) | AV70: =MAX(0,AU69*(1-INDEX($B$11:$B$63,36))*(1-E69)) | AW70: =MAX(0,AV69*(1-INDEX($B$11:$B$63,37))*(1-E69)) | AX70: =MAX(0,AW69*(1-INDEX($B$11:$B$63,38))*(1-E69)) | AY70: =MAX(0,AX69*(1-INDEX($B$11:$B$63,39))*(1-E69)) | AZ70: =MAX(0,AY69*(1-INDEX($B$11:$B$63,40))*(1-E69)) | BA70: =MAX(0,AZ69*(1-INDEX($B$11:$B$63,41))*(1-E69)) | BB70: =MAX(0,BA69*(1-INDEX($B$11:$B$63,42))*(1-E69)) | BC70: =MAX(0,BB69*(1-INDEX($B$11:$B$63,43))*(1-E69)) | BD70: =MAX(0,BC69*(1-INDEX($B$11:$B$63,44))*(1-E69)) | BE70: =MAX(0,BD69*(1-INDEX($B$11:$B$63,45))*(1-E69)) | BF70: =MAX(0,BE69*(1-INDEX($B$11:$B$63,46))*(1-E69)) | BG70: =MAX(0,BF69*(1-INDEX($B$11:$B$63,47))*(1-E69)) | BH70: =MAX(0,BG69*(1-INDEX($B$11:$B$63,48))*(1-E69)) | BI70: =MAX(0,BH69*(1-INDEX($B$11:$B$63,49))*(1-E69)) | BJ70: =MAX(0,BI69*(1-INDEX($B$11:$B$63,50))*(1-E69)) | BK70: =MAX(0,BJ69*(1-INDEX($B$11:$B$63,51))*(1-E69)) | BL70: =MAX(0,(BL69+BK69)*(1-INDEX($B$11:$B$63,53))*(1-E69))
A71: 5 | B71: =IF(A71>Inputs!$C$62,"",SUM(M71:BK71)) | C71: =IF(A71>Inputs!$C$62,"",INDEX(Trajectory!$C$23:$C$2000,A71)) | D71: =IF(A71>Inputs!$C$62,"",SUM(L71:BK71)) | E71: =IF(A71>Inputs!$C$62,"",INDEX(Trajectory!$AG$23:$AG$2000,A71)) | F71: =IF(D71=0,0,SUMPRODUCT(L71:BK71,$B$11:$B$63)/D71) | G71: =IF(D71=0,0,MIN(0.95,1-(1-F71)*(1-E71))) | H71: =IF(D71=0,0,D71*G71) | I71: =IF(D71=0,0,D71-H71) | L71: =C71 | M71: =MAX(0,L70*(1-INDEX($B$11:$B$63,1))*(1-E70)) | N71: =MAX(0,M70*(1-INDEX($B$11:$B$63,2))*(1-E70)) | O71: =MAX(0,N70*(1-INDEX($B$11:$B$63,3))*(1-E70)) | P71: =MAX(0,O70*(1-INDEX($B$11:$B$63,4))*(1-E70)) | Q71: =MAX(0,P70*(1-INDEX($B$11:$B$63,5))*(1-E70)) | R71: =MAX(0,Q70*(1-INDEX($B$11:$B$63,6))*(1-E70)) | S71: =MAX(0,R70*(1-INDEX($B$11:$B$63,7))*(1-E70)) | T71: =MAX(0,S70*(1-INDEX($B$11:$B$63,8))*(1-E70)) | U71: =MAX(0,T70*(1-INDEX($B$11:$B$63,9))*(1-E70)) | V71: =MAX(0,U70*(1-INDEX($B$11:$B$63,10))*(1-E70)) | W71: =MAX(0,V70*(1-INDEX($B$11:$B$63,11))*(1-E70)) | X71: =MAX(0,W70*(1-INDEX($B$11:$B$63,12))*(1-E70)) | Y71: =MAX(0,X70*(1-INDEX($B$11:$B$63,13))*(1-E70)) | Z71: =MAX(0,Y70*(1-INDEX($B$11:$B$63,14))*(1-E70)) | AA71: =MAX(0,Z70*(1-INDEX($B$11:$B$63,15))*(1-E70)) | AB71: =MAX(0,AA70*(1-INDEX($B$11:$B$63,16))*(1-E70)) | AC71: =MAX(0,AB70*(1-INDEX($B$11:$B$63,17))*(1-E70)) | AD71: =MAX(0,AC70*(1-INDEX($B$11:$B$63,18))*(1-E70)) | AE71: =MAX(0,AD70*(1-INDEX($B$11:$B$63,19))*(1-E70)) | AF71: =MAX(0,AE70*(1-INDEX($B$11:$B$63,20))*(1-E70)) | AG71: =MAX(0,AF70*(1-INDEX($B$11:$B$63,21))*(1-E70)) | AH71: =MAX(0,AG70*(1-INDEX($B$11:$B$63,22))*(1-E70)) | AI71: =MAX(0,AH70*(1-INDEX($B$11:$B$63,23))*(1-E70)) | AJ71: =MAX(0,AI70*(1-INDEX($B$11:$B$63,24))*(1-E70)) | AK71: =MAX(0,AJ70*(1-INDEX($B$11:$B$63,25))*(1-E70)) | AL71: =MAX(0,AK70*(1-INDEX($B$11:$B$63,26))*(1-E70)) | AM71: =MAX(0,AL70*(1-INDEX($B$11:$B$63,27))*(1-E70)) | AN71: =MAX(0,AM70*(1-INDEX($B$11:$B$63,28))*(1-E70)) | AO71: =MAX(0,AN70*(1-INDEX($B$11:$B$63,29))*(1-E70)) | AP71: =MAX(0,AO70*(1-INDEX($B$11:$B$63,30))*(1-E70)) | AQ71: =MAX(0,AP70*(1-INDEX($B$11:$B$63,31))*(1-E70)) | AR71: =MAX(0,AQ70*(1-INDEX($B$11:$B$63,32))*(1-E70)) | AS71: =MAX(0,AR70*(1-INDEX($B$11:$B$63,33))*(1-E70)) | AT71: =MAX(0,AS70*(1-INDEX($B$11:$B$63,34))*(1-E70)) | AU71: =MAX(0,AT70*(1-INDEX($B$11:$B$63,35))*(1-E70)) | AV71: =MAX(0,AU70*(1-INDEX($B$11:$B$63,36))*(1-E70)) | AW71: =MAX(0,AV70*(1-INDEX($B$11:$B$63,37))*(1-E70)) | AX71: =MAX(0,AW70*(1-INDEX($B$11:$B$63,38))*(1-E70)) | AY71: =MAX(0,AX70*(1-INDEX($B$11:$B$63,39))*(1-E70)) | AZ71: =MAX(0,AY70*(1-INDEX($B$11:$B$63,40))*(1-E70)) | BA71: =MAX(0,AZ70*(1-INDEX($B$11:$B$63,41))*(1-E70)) | BB71: =MAX(0,BA70*(1-INDEX($B$11:$B$63,42))*(1-E70)) | BC71: =MAX(0,BB70*(1-INDEX($B$11:$B$63,43))*(1-E70)) | BD71: =MAX(0,BC70*(1-INDEX($B$11:$B$63,44))*(1-E70)) | BE71: =MAX(0,BD70*(1-INDEX($B$11:$B$63,45))*(1-E70)) | BF71: =MAX(0,BE70*(1-INDEX($B$11:$B$63,46))*(1-E70)) | BG71: =MAX(0,BF70*(1-INDEX($B$11:$B$63,47))*(1-E70)) | BH71: =MAX(0,BG70*(1-INDEX($B$11:$B$63,48))*(1-E70)) | BI71: =MAX(0,BH70*(1-INDEX($B$11:$B$63,49))*(1-E70)) | BJ71: =MAX(0,BI70*(1-INDEX($B$11:$B$63,50))*(1-E70)) | BK71: =MAX(0,BJ70*(1-INDEX($B$11:$B$63,51))*(1-E70)) | BL71: =MAX(0,(BL70+BK70)*(1-INDEX($B$11:$B$63,53))*(1-E70))
A72: 6 | B72: =IF(A72>Inputs!$C$62,"",SUM(M72:BK72)) | C72: =IF(A72>Inputs!$C$62,"",INDEX(Trajectory!$C$23:$C$2000,A72)) | D72: =IF(A72>Inputs!$C$62,"",SUM(L72:BK72)) | E72: =IF(A72>Inputs!$C$62,"",INDEX(Trajectory!$AG$23:$AG$2000,A72)) | F72: =IF(D72=0,0,SUMPRODUCT(L72:BK72,$B$11:$B$63)/D72) | G72: =IF(D72=0,0,MIN(0.95,1-(1-F72)*(1-E72))) | H72: =IF(D72=0,0,D72*G72) | I72: =IF(D72=0,0,D72-H72) | L72: =C72 | M72: =MAX(0,L71*(1-INDEX($B$11:$B$63,1))*(1-E71)) | N72: =MAX(0,M71*(1-INDEX($B$11:$B$63,2))*(1-E71)) | O72: =MAX(0,N71*(1-INDEX($B$11:$B$63,3))*(1-E71)) | P72: =MAX(0,O71*(1-INDEX($B$11:$B$63,4))*(1-E71)) | Q72: =MAX(0,P71*(1-INDEX($B$11:$B$63,5))*(1-E71)) | R72: =MAX(0,Q71*(1-INDEX($B$11:$B$63,6))*(1-E71)) | S72: =MAX(0,R71*(1-INDEX($B$11:$B$63,7))*(1-E71)) | T72: =MAX(0,S71*(1-INDEX($B$11:$B$63,8))*(1-E71)) | U72: =MAX(0,T71*(1-INDEX($B$11:$B$63,9))*(1-E71)) | V72: =MAX(0,U71*(1-INDEX($B$11:$B$63,10))*(1-E71)) | W72: =MAX(0,V71*(1-INDEX($B$11:$B$63,11))*(1-E71)) | X72: =MAX(0,W71*(1-INDEX($B$11:$B$63,12))*(1-E71)) | Y72: =MAX(0,X71*(1-INDEX($B$11:$B$63,13))*(1-E71)) | Z72: =MAX(0,Y71*(1-INDEX($B$11:$B$63,14))*(1-E71)) | AA72: =MAX(0,Z71*(1-INDEX($B$11:$B$63,15))*(1-E71)) | AB72: =MAX(0,AA71*(1-INDEX($B$11:$B$63,16))*(1-E71)) | AC72: =MAX(0,AB71*(1-INDEX($B$11:$B$63,17))*(1-E71)) | AD72: =MAX(0,AC71*(1-INDEX($B$11:$B$63,18))*(1-E71)) | AE72: =MAX(0,AD71*(1-INDEX($B$11:$B$63,19))*(1-E71)) | AF72: =MAX(0,AE71*(1-INDEX($B$11:$B$63,20))*(1-E71)) | AG72: =MAX(0,AF71*(1-INDEX($B$11:$B$63,21))*(1-E71)) | AH72: =MAX(0,AG71*(1-INDEX($B$11:$B$63,22))*(1-E71)) | AI72: =MAX(0,AH71*(1-INDEX($B$11:$B$63,23))*(1-E71)) | AJ72: =MAX(0,AI71*(1-INDEX($B$11:$B$63,24))*(1-E71)) | AK72: =MAX(0,AJ71*(1-INDEX($B$11:$B$63,25))*(1-E71)) | AL72: =MAX(0,AK71*(1-INDEX($B$11:$B$63,26))*(1-E71)) | AM72: =MAX(0,AL71*(1-INDEX($B$11:$B$63,27))*(1-E71)) | AN72: =MAX(0,AM71*(1-INDEX($B$11:$B$63,28))*(1-E71)) | AO72: =MAX(0,AN71*(1-INDEX($B$11:$B$63,29))*(1-E71)) | AP72: =MAX(0,AO71*(1-INDEX($B$11:$B$63,30))*(1-E71)) | AQ72: =MAX(0,AP71*(1-INDEX($B$11:$B$63,31))*(1-E71)) | AR72: =MAX(0,AQ71*(1-INDEX($B$11:$B$63,32))*(1-E71)) | AS72: =MAX(0,AR71*(1-INDEX($B$11:$B$63,33))*(1-E71)) | AT72: =MAX(0,AS71*(1-INDEX($B$11:$B$63,34))*(1-E71)) | AU72: =MAX(0,AT71*(1-INDEX($B$11:$B$63,35))*(1-E71)) | AV72: =MAX(0,AU71*(1-INDEX($B$11:$B$63,36))*(1-E71)) | AW72: =MAX(0,AV71*(1-INDEX($B$11:$B$63,37))*(1-E71)) | AX72: =MAX(0,AW71*(1-INDEX($B$11:$B$63,38))*(1-E71)) | AY72: =MAX(0,AX71*(1-INDEX($B$11:$B$63,39))*(1-E71)) | AZ72: =MAX(0,AY71*(1-INDEX($B$11:$B$63,40))*(1-E71)) | BA72: =MAX(0,AZ71*(1-INDEX($B$11:$B$63,41))*(1-E71)) | BB72: =MAX(0,BA71*(1-INDEX($B$11:$B$63,42))*(1-E71)) | BC72: =MAX(0,BB71*(1-INDEX($B$11:$B$63,43))*(1-E71)) | BD72: =MAX(0,BC71*(1-INDEX($B$11:$B$63,44))*(1-E71)) | BE72: =MAX(0,BD71*(1-INDEX($B$11:$B$63,45))*(1-E71)) | BF72: =MAX(0,BE71*(1-INDEX($B$11:$B$63,46))*(1-E71)) | BG72: =MAX(0,BF71*(1-INDEX($B$11:$B$63,47))*(1-E71)) | BH72: =MAX(0,BG71*(1-INDEX($B$11:$B$63,48))*(1-E71)) | BI72: =MAX(0,BH71*(1-INDEX($B$11:$B$63,49))*(1-E71)) | BJ72: =MAX(0,BI71*(1-INDEX($B$11:$B$63,50))*(1-E71)) | BK72: =MAX(0,BJ71*(1-INDEX($B$11:$B$63,51))*(1-E71)) | BL72: =MAX(0,(BL71+BK71)*(1-INDEX($B$11:$B$63,53))*(1-E71))
A73: 7 | B73: =IF(A73>Inputs!$C$62,"",SUM(M73:BK73)) | C73: =IF(A73>Inputs!$C$62,"",INDEX(Trajectory!$C$23:$C$2000,A73)) | D73: =IF(A73>Inputs!$C$62,"",SUM(L73:BK73)) | E73: =IF(A73>Inputs!$C$62,"",INDEX(Trajectory!$AG$23:$AG$2000,A73)) | F73: =IF(D73=0,0,SUMPRODUCT(L73:BK73,$B$11:$B$63)/D73) | G73: =IF(D73=0,0,MIN(0.95,1-(1-F73)*(1-E73))) | H73: =IF(D73=0,0,D73*G73) | I73: =IF(D73=0,0,D73-H73) | L73: =C73 | M73: =MAX(0,L72*(1-INDEX($B$11:$B$63,1))*(1-E72)) | N73: =MAX(0,M72*(1-INDEX($B$11:$B$63,2))*(1-E72)) | O73: =MAX(0,N72*(1-INDEX($B$11:$B$63,3))*(1-E72)) | P73: =MAX(0,O72*(1-INDEX($B$11:$B$63,4))*(1-E72)) | Q73: =MAX(0,P72*(1-INDEX($B$11:$B$63,5))*(1-E72)) | R73: =MAX(0,Q72*(1-INDEX($B$11:$B$63,6))*(1-E72)) | S73: =MAX(0,R72*(1-INDEX($B$11:$B$63,7))*(1-E72)) | T73: =MAX(0,S72*(1-INDEX($B$11:$B$63,8))*(1-E72)) | U73: =MAX(0,T72*(1-INDEX($B$11:$B$63,9))*(1-E72)) | V73: =MAX(0,U72*(1-INDEX($B$11:$B$63,10))*(1-E72)) | W73: =MAX(0,V72*(1-INDEX($B$11:$B$63,11))*(1-E72)) | X73: =MAX(0,W72*(1-INDEX($B$11:$B$63,12))*(1-E72)) | Y73: =MAX(0,X72*(1-INDEX($B$11:$B$63,13))*(1-E72)) | Z73: =MAX(0,Y72*(1-INDEX($B$11:$B$63,14))*(1-E72)) | AA73: =MAX(0,Z72*(1-INDEX($B$11:$B$63,15))*(1-E72)) | AB73: =MAX(0,AA72*(1-INDEX($B$11:$B$63,16))*(1-E72)) | AC73: =MAX(0,AB72*(1-INDEX($B$11:$B$63,17))*(1-E72)) | AD73: =MAX(0,AC72*(1-INDEX($B$11:$B$63,18))*(1-E72)) | AE73: =MAX(0,AD72*(1-INDEX($B$11:$B$63,19))*(1-E72)) | AF73: =MAX(0,AE72*(1-INDEX($B$11:$B$63,20))*(1-E72)) | AG73: =MAX(0,AF72*(1-INDEX($B$11:$B$63,21))*(1-E72)) | AH73: =MAX(0,AG72*(1-INDEX($B$11:$B$63,22))*(1-E72)) | AI73: =MAX(0,AH72*(1-INDEX($B$11:$B$63,23))*(1-E72)) | AJ73: =MAX(0,AI72*(1-INDEX($B$11:$B$63,24))*(1-E72)) | AK73: =MAX(0,AJ72*(1-INDEX($B$11:$B$63,25))*(1-E72)) | AL73: =MAX(0,AK72*(1-INDEX($B$11:$B$63,26))*(1-E72)) | AM73: =MAX(0,AL72*(1-INDEX($B$11:$B$63,27))*(1-E72)) | AN73: =MAX(0,AM72*(1-INDEX($B$11:$B$63,28))*(1-E72)) | AO73: =MAX(0,AN72*(1-INDEX($B$11:$B$63,29))*(1-E72)) | AP73: =MAX(0,AO72*(1-INDEX($B$11:$B$63,30))*(1-E72)) | AQ73: =MAX(0,AP72*(1-INDEX($B$11:$B$63,31))*(1-E72)) | AR73: =MAX(0,AQ72*(1-INDEX($B$11:$B$63,32))*(1-E72)) | AS73: =MAX(0,AR72*(1-INDEX($B$11:$B$63,33))*(1-E72)) | AT73: =MAX(0,AS72*(1-INDEX($B$11:$B$63,34))*(1-E72)) | AU73: =MAX(0,AT72*(1-INDEX($B$11:$B$63,35))*(1-E72)) | AV73: =MAX(0,AU72*(1-INDEX($B$11:$B$63,36))*(1-E72)) | AW73: =MAX(0,AV72*(1-INDEX($B$11:$B$63,37))*(1-E72)) | AX73: =MAX(0,AW72*(1-INDEX($B$11:$B$63,38))*(1-E72)) | AY73: =MAX(0,AX72*(1-INDEX($B$11:$B$63,39))*(1-E72)) | AZ73: =MAX(0,AY72*(1-INDEX($B$11:$B$63,40))*(1-E72)) | BA73: =MAX(0,AZ72*(1-INDEX($B$11:$B$63,41))*(1-E72)) | BB73: =MAX(0,BA72*(1-INDEX($B$11:$B$63,42))*(1-E72)) | BC73: =MAX(0,BB72*(1-INDEX($B$11:$B$63,43))*(1-E72)) | BD73: =MAX(0,BC72*(1-INDEX($B$11:$B$63,44))*(1-E72)) | BE73: =MAX(0,BD72*(1-INDEX($B$11:$B$63,45))*(1-E72)) | BF73: =MAX(0,BE72*(1-INDEX($B$11:$B$63,46))*(1-E72)) | BG73: =MAX(0,BF72*(1-INDEX($B$11:$B$63,47))*(1-E72)) | BH73: =MAX(0,BG72*(1-INDEX($B$11:$B$63,48))*(1-E72)) | BI73: =MAX(0,BH72*(1-INDEX($B$11:$B$63,49))*(1-E72)) | BJ73: =MAX(0,BI72*(1-INDEX($B$11:$B$63,50))*(1-E72)) | BK73: =MAX(0,BJ72*(1-INDEX($B$11:$B$63,51))*(1-E72)) | BL73: =MAX(0,(BL72+BK72)*(1-INDEX($B$11:$B$63,53))*(1-E72))
A74: 8 | B74: =IF(A74>Inputs!$C$62,"",SUM(M74:BK74)) | C74: =IF(A74>Inputs!$C$62,"",INDEX(Trajectory!$C$23:$C$2000,A74)) | D74: =IF(A74>Inputs!$C$62,"",SUM(L74:BK74)) | E74: =IF(A74>Inputs!$C$62,"",INDEX(Trajectory!$AG$23:$AG$2000,A74)) | F74: =IF(D74=0,0,SUMPRODUCT(L74:BK74,$B$11:$B$63)/D74) | G74: =IF(D74=0,0,MIN(0.95,1-(1-F74)*(1-E74))) | H74: =IF(D74=0,0,D74*G74) | I74: =IF(D74=0,0,D74-H74) | L74: =C74 | M74: =MAX(0,L73*(1-INDEX($B$11:$B$63,1))*(1-E73)) | N74: =MAX(0,M73*(1-INDEX($B$11:$B$63,2))*(1-E73)) | O74: =MAX(0,N73*(1-INDEX($B$11:$B$63,3))*(1-E73)) | P74: =MAX(0,O73*(1-INDEX($B$11:$B$63,4))*(1-E73)) | Q74: =MAX(0,P73*(1-INDEX($B$11:$B$63,5))*(1-E73)) | R74: =MAX(0,Q73*(1-INDEX($B$11:$B$63,6))*(1-E73)) | S74: =MAX(0,R73*(1-INDEX($B$11:$B$63,7))*(1-E73)) | T74: =MAX(0,S73*(1-INDEX($B$11:$B$63,8))*(1-E73)) | U74: =MAX(0,T73*(1-INDEX($B$11:$B$63,9))*(1-E73)) | V74: =MAX(0,U73*(1-INDEX($B$11:$B$63,10))*(1-E73)) | W74: =MAX(0,V73*(1-INDEX($B$11:$B$63,11))*(1-E73)) | X74: =MAX(0,W73*(1-INDEX($B$11:$B$63,12))*(1-E73)) | Y74: =MAX(0,X73*(1-INDEX($B$11:$B$63,13))*(1-E73)) | Z74: =MAX(0,Y73*(1-INDEX($B$11:$B$63,14))*(1-E73)) | AA74: =MAX(0,Z73*(1-INDEX($B$11:$B$63,15))*(1-E73)) | AB74: =MAX(0,AA73*(1-INDEX($B$11:$B$63,16))*(1-E73)) | AC74: =MAX(0,AB73*(1-INDEX($B$11:$B$63,17))*(1-E73)) | AD74: =MAX(0,AC73*(1-INDEX($B$11:$B$63,18))*(1-E73)) | AE74: =MAX(0,AD73*(1-INDEX($B$11:$B$63,19))*(1-E73)) | AF74: =MAX(0,AE73*(1-INDEX($B$11:$B$63,20))*(1-E73)) | AG74: =MAX(0,AF73*(1-INDEX($B$11:$B$63,21))*(1-E73)) | AH74: =MAX(0,AG73*(1-INDEX($B$11:$B$63,22))*(1-E73)) | AI74: =MAX(0,AH73*(1-INDEX($B$11:$B$63,23))*(1-E73)) | AJ74: =MAX(0,AI73*(1-INDEX($B$11:$B$63,24))*(1-E73)) | AK74: =MAX(0,AJ73*(1-INDEX($B$11:$B$63,25))*(1-E73)) | AL74: =MAX(0,AK73*(1-INDEX($B$11:$B$63,26))*(1-E73)) | AM74: =MAX(0,AL73*(1-INDEX($B$11:$B$63,27))*(1-E73)) | AN74: =MAX(0,AM73*(1-INDEX($B$11:$B$63,28))*(1-E73)) | AO74: =MAX(0,AN73*(1-INDEX($B$11:$B$63,29))*(1-E73)) | AP74: =MAX(0,AO73*(1-INDEX($B$11:$B$63,30))*(1-E73)) | AQ74: =MAX(0,AP73*(1-INDEX($B$11:$B$63,31))*(1-E73)) | AR74: =MAX(0,AQ73*(1-INDEX($B$11:$B$63,32))*(1-E73)) | AS74: =MAX(0,AR73*(1-INDEX($B$11:$B$63,33))*(1-E73)) | AT74: =MAX(0,AS73*(1-INDEX($B$11:$B$63,34))*(1-E73)) | AU74: =MAX(0,AT73*(1-INDEX($B$11:$B$63,35))*(1-E73)) | AV74: =MAX(0,AU73*(1-INDEX($B$11:$B$63,36))*(1-E73)) | AW74: =MAX(0,AV73*(1-INDEX($B$11:$B$63,37))*(1-E73)) | AX74: =MAX(0,AW73*(1-INDEX($B$11:$B$63,38))*(1-E73)) | AY74: =MAX(0,AX73*(1-INDEX($B$11:$B$63,39))*(1-E73)) | AZ74: =MAX(0,AY73*(1-INDEX($B$11:$B$63,40))*(1-E73)) | BA74: =MAX(0,AZ73*(1-INDEX($B$11:$B$63,41))*(1-E73)) | BB74: =MAX(0,BA73*(1-INDEX($B$11:$B$63,42))*(1-E73)) | BC74: =MAX(0,BB73*(1-INDEX($B$11:$B$63,43))*(1-E73)) | BD74: =MAX(0,BC73*(1-INDEX($B$11:$B$63,44))*(1-E73)) | BE74: =MAX(0,BD73*(1-INDEX($B$11:$B$63,45))*(1-E73)) | BF74: =MAX(0,BE73*(1-INDEX($B$11:$B$63,46))*(1-E73)) | BG74: =MAX(0,BF73*(1-INDEX($B$11:$B$63,47))*(1-E73)) | BH74: =MAX(0,BG73*(1-INDEX($B$11:$B$63,48))*(1-E73)) | BI74: =MAX(0,BH73*(1-INDEX($B$11:$B$63,49))*(1-E73)) | BJ74: =MAX(0,BI73*(1-INDEX($B$11:$B$63,50))*(1-E73)) | BK74: =MAX(0,BJ73*(1-INDEX($B$11:$B$63,51))*(1-E73)) | BL74: =MAX(0,(BL73+BK73)*(1-INDEX($B$11:$B$63,53))*(1-E73))
A75: 9 | B75: =IF(A75>Inputs!$C$62,"",SUM(M75:BK75)) | C75: =IF(A75>Inputs!$C$62,"",INDEX(Trajectory!$C$23:$C$2000,A75)) | D75: =IF(A75>Inputs!$C$62,"",SUM(L75:BK75)) | E75: =IF(A75>Inputs!$C$62,"",INDEX(Trajectory!$AG$23:$AG$2000,A75)) | F75: =IF(D75=0,0,SUMPRODUCT(L75:BK75,$B$11:$B$63)/D75) | G75: =IF(D75=0,0,MIN(0.95,1-(1-F75)*(1-E75))) | H75: =IF(D75=0,0,D75*G75) | I75: =IF(D75=0,0,D75-H75) | L75: =C75 | M75: =MAX(0,L74*(1-INDEX($B$11:$B$63,1))*(1-E74)) | N75: =MAX(0,M74*(1-INDEX($B$11:$B$63,2))*(1-E74)) | O75: =MAX(0,N74*(1-INDEX($B$11:$B$63,3))*(1-E74)) | P75: =MAX(0,O74*(1-INDEX($B$11:$B$63,4))*(1-E74)) | Q75: =MAX(0,P74*(1-INDEX($B$11:$B$63,5))*(1-E74)) | R75: =MAX(0,Q74*(1-INDEX($B$11:$B$63,6))*(1-E74)) | S75: =MAX(0,R74*(1-INDEX($B$11:$B$63,7))*(1-E74)) | T75: =MAX(0,S74*(1-INDEX($B$11:$B$63,8))*(1-E74)) | U75: =MAX(0,T74*(1-INDEX($B$11:$B$63,9))*(1-E74)) | V75: =MAX(0,U74*(1-INDEX($B$11:$B$63,10))*(1-E74)) | W75: =MAX(0,V74*(1-INDEX($B$11:$B$63,11))*(1-E74)) | X75: =MAX(0,W74*(1-INDEX($B$11:$B$63,12))*(1-E74)) | Y75: =MAX(0,X74*(1-INDEX($B$11:$B$63,13))*(1-E74)) | Z75: =MAX(0,Y74*(1-INDEX($B$11:$B$63,14))*(1-E74)) | AA75: =MAX(0,Z74*(1-INDEX($B$11:$B$63,15))*(1-E74)) | AB75: =MAX(0,AA74*(1-INDEX($B$11:$B$63,16))*(1-E74)) | AC75: =MAX(0,AB74*(1-INDEX($B$11:$B$63,17))*(1-E74)) | AD75: =MAX(0,AC74*(1-INDEX($B$11:$B$63,18))*(1-E74)) | AE75: =MAX(0,AD74*(1-INDEX($B$11:$B$63,19))*(1-E74)) | AF75: =MAX(0,AE74*(1-INDEX($B$11:$B$63,20))*(1-E74)) | AG75: =MAX(0,AF74*(1-INDEX($B$11:$B$63,21))*(1-E74)) | AH75: =MAX(0,AG74*(1-INDEX($B$11:$B$63,22))*(1-E74)) | AI75: =MAX(0,AH74*(1-INDEX($B$11:$B$63,23))*(1-E74)) | AJ75: =MAX(0,AI74*(1-INDEX($B$11:$B$63,24))*(1-E74)) | AK75: =MAX(0,AJ74*(1-INDEX($B$11:$B$63,25))*(1-E74)) | AL75: =MAX(0,AK74*(1-INDEX($B$11:$B$63,26))*(1-E74)) | AM75: =MAX(0,AL74*(1-INDEX($B$11:$B$63,27))*(1-E74)) | AN75: =MAX(0,AM74*(1-INDEX($B$11:$B$63,28))*(1-E74)) | AO75: =MAX(0,AN74*(1-INDEX($B$11:$B$63,29))*(1-E74)) | AP75: =MAX(0,AO74*(1-INDEX($B$11:$B$63,30))*(1-E74)) | AQ75: =MAX(0,AP74*(1-INDEX($B$11:$B$63,31))*(1-E74)) | AR75: =MAX(0,AQ74*(1-INDEX($B$11:$B$63,32))*(1-E74)) | AS75: =MAX(0,AR74*(1-INDEX($B$11:$B$63,33))*(1-E74)) | AT75: =MAX(0,AS74*(1-INDEX($B$11:$B$63,34))*(1-E74)) | AU75: =MAX(0,AT74*(1-INDEX($B$11:$B$63,35))*(1-E74)) | AV75: =MAX(0,AU74*(1-INDEX($B$11:$B$63,36))*(1-E74)) | AW75: =MAX(0,AV74*(1-INDEX($B$11:$B$63,37))*(1-E74)) | AX75: =MAX(0,AW74*(1-INDEX($B$11:$B$63,38))*(1-E74)) | AY75: =MAX(0,AX74*(1-INDEX($B$11:$B$63,39))*(1-E74)) | AZ75: =MAX(0,AY74*(1-INDEX($B$11:$B$63,40))*(1-E74)) | BA75: =MAX(0,AZ74*(1-INDEX($B$11:$B$63,41))*(1-E74)) | BB75: =MAX(0,BA74*(1-INDEX($B$11:$B$63,42))*(1-E74)) | BC75: =MAX(0,BB74*(1-INDEX($B$11:$B$63,43))*(1-E74)) | BD75: =MAX(0,BC74*(1-INDEX($B$11:$B$63,44))*(1-E74)) | BE75: =MAX(0,BD74*(1-INDEX($B$11:$B$63,45))*(1-E74)) | BF75: =MAX(0,BE74*(1-INDEX($B$11:$B$63,46))*(1-E74)) | BG75: =MAX(0,BF74*(1-INDEX($B$11:$B$63,47))*(1-E74)) | BH75: =MAX(0,BG74*(1-INDEX($B$11:$B$63,48))*(1-E74)) | BI75: =MAX(0,BH74*(1-INDEX($B$11:$B$63,49))*(1-E74)) | BJ75: =MAX(0,BI74*(1-INDEX($B$11:$B$63,50))*(1-E74)) | BK75: =MAX(0,BJ74*(1-INDEX($B$11:$B$63,51))*(1-E74)) | BL75: =MAX(0,(BL74+BK74)*(1-INDEX($B$11:$B$63,53))*(1-E74))
A76: 10 | B76: =IF(A76>Inputs!$C$62,"",SUM(M76:BK76)) | C76: =IF(A76>Inputs!$C$62,"",INDEX(Trajectory!$C$23:$C$2000,A76)) | D76: =IF(A76>Inputs!$C$62,"",SUM(L76:BK76)) | E76: =IF(A76>Inputs!$C$62,"",INDEX(Trajectory!$AG$23:$AG$2000,A76)) | F76: =IF(D76=0,0,SUMPRODUCT(L76:BK76,$B$11:$B$63)/D76) | G76: =IF(D76=0,0,MIN(0.95,1-(1-F76)*(1-E76))) | H76: =IF(D76=0,0,D76*G76) | I76: =IF(D76=0,0,D76-H76) | L76: =C76 | M76: =MAX(0,L75*(1-INDEX($B$11:$B$63,1))*(1-E75)) | N76: =MAX(0,M75*(1-INDEX($B$11:$B$63,2))*(1-E75)) | O76: =MAX(0,N75*(1-INDEX($B$11:$B$63,3))*(1-E75)) | P76: =MAX(0,O75*(1-INDEX($B$11:$B$63,4))*(1-E75)) | Q76: =MAX(0,P75*(1-INDEX($B$11:$B$63,5))*(1-E75)) | R76: =MAX(0,Q75*(1-INDEX($B$11:$B$63,6))*(1-E75)) | S76: =MAX(0,R75*(1-INDEX($B$11:$B$63,7))*(1-E75)) | T76: =MAX(0,S75*(1-INDEX($B$11:$B$63,8))*(1-E75)) | U76: =MAX(0,T75*(1-INDEX($B$11:$B$63,9))*(1-E75)) | V76: =MAX(0,U75*(1-INDEX($B$11:$B$63,10))*(1-E75)) | W76: =MAX(0,V75*(1-INDEX($B$11:$B$63,11))*(1-E75)) | X76: =MAX(0,W75*(1-INDEX($B$11:$B$63,12))*(1-E75)) | Y76: =MAX(0,X75*(1-INDEX($B$11:$B$63,13))*(1-E75)) | Z76: =MAX(0,Y75*(1-INDEX($B$11:$B$63,14))*(1-E75)) | AA76: =MAX(0,Z75*(1-INDEX($B$11:$B$63,15))*(1-E75)) | AB76: =MAX(0,AA75*(1-INDEX($B$11:$B$63,16))*(1-E75)) | AC76: =MAX(0,AB75*(1-INDEX($B$11:$B$63,17))*(1-E75)) | AD76: =MAX(0,AC75*(1-INDEX($B$11:$B$63,18))*(1-E75)) | AE76: =MAX(0,AD75*(1-INDEX($B$11:$B$63,19))*(1-E75)) | AF76: =MAX(0,AE75*(1-INDEX($B$11:$B$63,20))*(1-E75)) | AG76: =MAX(0,AF75*(1-INDEX($B$11:$B$63,21))*(1-E75)) | AH76: =MAX(0,AG75*(1-INDEX($B$11:$B$63,22))*(1-E75)) | AI76: =MAX(0,AH75*(1-INDEX($B$11:$B$63,23))*(1-E75)) | AJ76: =MAX(0,AI75*(1-INDEX($B$11:$B$63,24))*(1-E75)) | AK76: =MAX(0,AJ75*(1-INDEX($B$11:$B$63,25))*(1-E75)) | AL76: =MAX(0,AK75*(1-INDEX($B$11:$B$63,26))*(1-E75)) | AM76: =MAX(0,AL75*(1-INDEX($B$11:$B$63,27))*(1-E75)) | AN76: =MAX(0,AM75*(1-INDEX($B$11:$B$63,28))*(1-E75)) | AO76: =MAX(0,AN75*(1-INDEX($B$11:$B$63,29))*(1-E75)) | AP76: =MAX(0,AO75*(1-INDEX($B$11:$B$63,30))*(1-E75)) | AQ76: =MAX(0,AP75*(1-INDEX($B$11:$B$63,31))*(1-E75)) | AR76: =MAX(0,AQ75*(1-INDEX($B$11:$B$63,32))*(1-E75)) | AS76: =MAX(0,AR75*(1-INDEX($B$11:$B$63,33))*(1-E75)) | AT76: =MAX(0,AS75*(1-INDEX($B$11:$B$63,34))*(1-E75)) | AU76: =MAX(0,AT75*(1-INDEX($B$11:$B$63,35))*(1-E75)) | AV76: =MAX(0,AU75*(1-INDEX($B$11:$B$63,36))*(1-E75)) | AW76: =MAX(0,AV75*(1-INDEX($B$11:$B$63,37))*(1-E75)) | AX76: =MAX(0,AW75*(1-INDEX($B$11:$B$63,38))*(1-E75)) | AY76: =MAX(0,AX75*(1-INDEX($B$11:$B$63,39))*(1-E75)) | AZ76: =MAX(0,AY75*(1-INDEX($B$11:$B$63,40))*(1-E75)) | BA76: =MAX(0,AZ75*(1-INDEX($B$11:$B$63,41))*(1-E75)) | BB76: =MAX(0,BA75*(1-INDEX($B$11:$B$63,42))*(1-E75)) | BC76: =MAX(0,BB75*(1-INDEX($B$11:$B$63,43))*(1-E75)) | BD76: =MAX(0,BC75*(1-INDEX($B$11:$B$63,44))*(1-E75)) | BE76: =MAX(0,BD75*(1-INDEX($B$11:$B$63,45))*(1-E75)) | BF76: =MAX(0,BE75*(1-INDEX($B$11:$B$63,46))*(1-E75)) | BG76: =MAX(0,BF75*(1-INDEX($B$11:$B$63,47))*(1-E75)) | BH76: =MAX(0,BG75*(1-INDEX($B$11:$B$63,48))*(1-E75)) | BI76: =MAX(0,BH75*(1-INDEX($B$11:$B$63,49))*(1-E75)) | BJ76: =MAX(0,BI75*(1-INDEX($B$11:$B$63,50))*(1-E75)) | BK76: =MAX(0,BJ75*(1-INDEX($B$11:$B$63,51))*(1-E75)) | BL76: =MAX(0,(BL75+BK75)*(1-INDEX($B$11:$B$63,53))*(1-E75))
A77: 11 | B77: =IF(A77>Inputs!$C$62,"",SUM(M77:BK77)) | C77: =IF(A77>Inputs!$C$62,"",INDEX(Trajectory!$C$23:$C$2000,A77)) | D77: =IF(A77>Inputs!$C$62,"",SUM(L77:BK77)) | E77: =IF(A77>Inputs!$C$62,"",INDEX(Trajectory!$AG$23:$AG$2000,A77)) | F77: =IF(D77=0,0,SUMPRODUCT(L77:BK77,$B$11:$B$63)/D77) | G77: =IF(D77=0,0,MIN(0.95,1-(1-F77)*(1-E77))) | H77: =IF(D77=0,0,D77*G77) | I77: =IF(D77=0,0,D77-H77) | L77: =C77 | M77: =MAX(0,L76*(1-INDEX($B$11:$B$63,1))*(1-E76)) | N77: =MAX(0,M76*(1-INDEX($B$11:$B$63,2))*(1-E76)) | O77: =MAX(0,N76*(1-INDEX($B$11:$B$63,3))*(1-E76)) | P77: =MAX(0,O76*(1-INDEX($B$11:$B$63,4))*(1-E76)) | Q77: =MAX(0,P76*(1-INDEX($B$11:$B$63,5))*(1-E76)) | R77: =MAX(0,Q76*(1-INDEX($B$11:$B$63,6))*(1-E76)) | S77: =MAX(0,R76*(1-INDEX($B$11:$B$63,7))*(1-E76)) | T77: =MAX(0,S76*(1-INDEX($B$11:$B$63,8))*(1-E76)) | U77: =MAX(0,T76*(1-INDEX($B$11:$B$63,9))*(1-E76)) | V77: =MAX(0,U76*(1-INDEX($B$11:$B$63,10))*(1-E76)) | W77: =MAX(0,V76*(1-INDEX($B$11:$B$63,11))*(1-E76)) | X77: =MAX(0,W76*(1-INDEX($B$11:$B$63,12))*(1-E76)) | Y77: =MAX(0,X76*(1-INDEX($B$11:$B$63,13))*(1-E76)) | Z77: =MAX(0,Y76*(1-INDEX($B$11:$B$63,14))*(1-E76)) | AA77: =MAX(0,Z76*(1-INDEX($B$11:$B$63,15))*(1-E76)) | AB77: =MAX(0,AA76*(1-INDEX($B$11:$B$63,16))*(1-E76)) | AC77: =MAX(0,AB76*(1-INDEX($B$11:$B$63,17))*(1-E76)) | AD77: =MAX(0,AC76*(1-INDEX($B$11:$B$63,18))*(1-E76)) | AE77: =MAX(0,AD76*(1-INDEX($B$11:$B$63,19))*(1-E76)) | AF77: =MAX(0,AE76*(1-INDEX($B$11:$B$63,20))*(1-E76)) | AG77: =MAX(0,AF76*(1-INDEX($B$11:$B$63,21))*(1-E76)) | AH77: =MAX(0,AG76*(1-INDEX($B$11:$B$63,22))*(1-E76)) | AI77: =MAX(0,AH76*(1-INDEX($B$11:$B$63,23))*(1-E76)) | AJ77: =MAX(0,AI76*(1-INDEX($B$11:$B$63,24))*(1-E76)) | AK77: =MAX(0,AJ76*(1-INDEX($B$11:$B$63,25))*(1-E76)) | AL77: =MAX(0,AK76*(1-INDEX($B$11:$B$63,26))*(1-E76)) | AM77: =MAX(0,AL76*(1-INDEX($B$11:$B$63,27))*(1-E76)) | AN77: =MAX(0,AM76*(1-INDEX($B$11:$B$63,28))*(1-E76)) | AO77: =MAX(0,AN76*(1-INDEX($B$11:$B$63,29))*(1-E76)) | AP77: =MAX(0,AO76*(1-INDEX($B$11:$B$63,30))*(1-E76)) | AQ77: =MAX(0,AP76*(1-INDEX($B$11:$B$63,31))*(1-E76)) | AR77: =MAX(0,AQ76*(1-INDEX($B$11:$B$63,32))*(1-E76)) | AS77: =MAX(0,AR76*(1-INDEX($B$11:$B$63,33))*(1-E76)) | AT77: =MAX(0,AS76*(1-INDEX($B$11:$B$63,34))*(1-E76)) | AU77: =MAX(0,AT76*(1-INDEX($B$11:$B$63,35))*(1-E76)) | AV77: =MAX(0,AU76*(1-INDEX($B$11:$B$63,36))*(1-E76)) | AW77: =MAX(0,AV76*(1-INDEX($B$11:$B$63,37))*(1-E76)) | AX77: =MAX(0,AW76*(1-INDEX($B$11:$B$63,38))*(1-E76)) | AY77: =MAX(0,AX76*(1-INDEX($B$11:$B$63,39))*(1-E76)) | AZ77: =MAX(0,AY76*(1-INDEX($B$11:$B$63,40))*(1-E76)) | BA77: =MAX(0,AZ76*(1-INDEX($B$11:$B$63,41))*(1-E76)) | BB77: =MAX(0,BA76*(1-INDEX($B$11:$B$63,42))*(1-E76)) | BC77: =MAX(0,BB76*(1-INDEX($B$11:$B$63,43))*(1-E76)) | BD77: =MAX(0,BC76*(1-INDEX($B$11:$B$63,44))*(1-E76)) | BE77: =MAX(0,BD76*(1-INDEX($B$11:$B$63,45))*(1-E76)) | BF77: =MAX(0,BE76*(1-INDEX($B$11:$B$63,46))*(1-E76)) | BG77: =MAX(0,BF76*(1-INDEX($B$11:$B$63,47))*(1-E76)) | BH77: =MAX(0,BG76*(1-INDEX($B$11:$B$63,48))*(1-E76)) | BI77: =MAX(0,BH76*(1-INDEX($B$11:$B$63,49))*(1-E76)) | BJ77: =MAX(0,BI76*(1-INDEX($B$11:$B$63,50))*(1-E76)) | BK77: =MAX(0,BJ76*(1-INDEX($B$11:$B$63,51))*(1-E76)) | BL77: =MAX(0,(BL76+BK76)*(1-INDEX($B$11:$B$63,53))*(1-E76))
A78: 12 | B78: =IF(A78>Inputs!$C$62,"",SUM(M78:BK78)) | C78: =IF(A78>Inputs!$C$62,"",INDEX(Trajectory!$C$23:$C$2000,A78)) | D78: =IF(A78>Inputs!$C$62,"",SUM(L78:BK78)) | E78: =IF(A78>Inputs!$C$62,"",INDEX(Trajectory!$AG$23:$AG$2000,A78)) | F78: =IF(D78=0,0,SUMPRODUCT(L78:BK78,$B$11:$B$63)/D78) | G78: =IF(D78=0,0,MIN(0.95,1-(1-F78)*(1-E78))) | H78: =IF(D78=0,0,D78*G78) | I78: =IF(D78=0,0,D78-H78) | L78: =C78 | M78: =MAX(0,L77*(1-INDEX($B$11:$B$63,1))*(1-E77)) | N78: =MAX(0,M77*(1-INDEX($B$11:$B$63,2))*(1-E77)) | O78: =MAX(0,N77*(1-INDEX($B$11:$B$63,3))*(1-E77)) | P78: =MAX(0,O77*(1-INDEX($B$11:$B$63,4))*(1-E77)) | Q78: =MAX(0,P77*(1-INDEX($B$11:$B$63,5))*(1-E77)) | R78: =MAX(0,Q77*(1-INDEX($B$11:$B$63,6))*(1-E77)) | S78: =MAX(0,R77*(1-INDEX($B$11:$B$63,7))*(1-E77)) | T78: =MAX(0,S77*(1-INDEX($B$11:$B$63,8))*(1-E77)) | U78: =MAX(0,T77*(1-INDEX($B$11:$B$63,9))*(1-E77)) | V78: =MAX(0,U77*(1-INDEX($B$11:$B$63,10))*(1-E77)) | W78: =MAX(0,V77*(1-INDEX($B$11:$B$63,11))*(1-E77)) | X78: =MAX(0,W77*(1-INDEX($B$11:$B$63,12))*(1-E77)) | Y78: =MAX(0,X77*(1-INDEX($B$11:$B$63,13))*(1-E77)) | Z78: =MAX(0,Y77*(1-INDEX($B$11:$B$63,14))*(1-E77)) | AA78: =MAX(0,Z77*(1-INDEX($B$11:$B$63,15))*(1-E77)) | AB78: =MAX(0,AA77*(1-INDEX($B$11:$B$63,16))*(1-E77)) | AC78: =MAX(0,AB77*(1-INDEX($B$11:$B$63,17))*(1-E77)) | AD78: =MAX(0,AC77*(1-INDEX($B$11:$B$63,18))*(1-E77)) | AE78: =MAX(0,AD77*(1-INDEX($B$11:$B$63,19))*(1-E77)) | AF78: =MAX(0,AE77*(1-INDEX($B$11:$B$63,20))*(1-E77)) | AG78: =MAX(0,AF77*(1-INDEX($B$11:$B$63,21))*(1-E77)) | AH78: =MAX(0,AG77*(1-INDEX($B$11:$B$63,22))*(1-E77)) | AI78: =MAX(0,AH77*(1-INDEX($B$11:$B$63,23))*(1-E77)) | AJ78: =MAX(0,AI77*(1-INDEX($B$11:$B$63,24))*(1-E77)) | AK78: =MAX(0,AJ77*(1-INDEX($B$11:$B$63,25))*(1-E77)) | AL78: =MAX(0,AK77*(1-INDEX($B$11:$B$63,26))*(1-E77)) | AM78: =MAX(0,AL77*(1-INDEX($B$11:$B$63,27))*(1-E77)) | AN78: =MAX(0,AM77*(1-INDEX($B$11:$B$63,28))*(1-E77)) | AO78: =MAX(0,AN77*(1-INDEX($B$11:$B$63,29))*(1-E77)) | AP78: =MAX(0,AO77*(1-INDEX($B$11:$B$63,30))*(1-E77)) | AQ78: =MAX(0,AP77*(1-INDEX($B$11:$B$63,31))*(1-E77)) | AR78: =MAX(0,AQ77*(1-INDEX($B$11:$B$63,32))*(1-E77)) | AS78: =MAX(0,AR77*(1-INDEX($B$11:$B$63,33))*(1-E77)) | AT78: =MAX(0,AS77*(1-INDEX($B$11:$B$63,34))*(1-E77)) | AU78: =MAX(0,AT77*(1-INDEX($B$11:$B$63,35))*(1-E77)) | AV78: =MAX(0,AU77*(1-INDEX($B$11:$B$63,36))*(1-E77)) | AW78: =MAX(0,AV77*(1-INDEX($B$11:$B$63,37))*(1-E77)) | AX78: =MAX(0,AW77*(1-INDEX($B$11:$B$63,38))*(1-E77)) | AY78: =MAX(0,AX77*(1-INDEX($B$11:$B$63,39))*(1-E77)) | AZ78: =MAX(0,AY77*(1-INDEX($B$11:$B$63,40))*(1-E77)) | BA78: =MAX(0,AZ77*(1-INDEX($B$11:$B$63,41))*(1-E77)) | BB78: =MAX(0,BA77*(1-INDEX($B$11:$B$63,42))*(1-E77)) | BC78: =MAX(0,BB77*(1-INDEX($B$11:$B$63,43))*(1-E77)) | BD78: =MAX(0,BC77*(1-INDEX($B$11:$B$63,44))*(1-E77)) | BE78: =MAX(0,BD77*(1-INDEX($B$11:$B$63,45))*(1-E77)) | BF78: =MAX(0,BE77*(1-INDEX($B$11:$B$63,46))*(1-E77)) | BG78: =MAX(0,BF77*(1-INDEX($B$11:$B$63,47))*(1-E77)) | BH78: =MAX(0,BG77*(1-INDEX($B$11:$B$63,48))*(1-E77)) | BI78: =MAX(0,BH77*(1-INDEX($B$11:$B$63,49))*(1-E77)) | BJ78: =MAX(0,BI77*(1-INDEX($B$11:$B$63,50))*(1-E77)) | BK78: =MAX(0,BJ77*(1-INDEX($B$11:$B$63,51))*(1-E77)) | BL78: =MAX(0,(BL77+BK77)*(1-INDEX($B$11:$B$63,53))*(1-E77))
A79: 13 | B79: =IF(A79>Inputs!$C$62,"",SUM(M79:BK79)) | C79: =IF(A79>Inputs!$C$62,"",INDEX(Trajectory!$C$23:$C$2000,A79)) | D79: =IF(A79>Inputs!$C$62,"",SUM(L79:BK79)) | E79: =IF(A79>Inputs!$C$62,"",INDEX(Trajectory!$AG$23:$AG$2000,A79)) | F79: =IF(D79=0,0,SUMPRODUCT(L79:BK79,$B$11:$B$63)/D79) | G79: =IF(D79=0,0,MIN(0.95,1-(1-F79)*(1-E79))) | H79: =IF(D79=0,0,D79*G79) | I79: =IF(D79=0,0,D79-H79) | L79: =C79 | M79: =MAX(0,L78*(1-INDEX($B$11:$B$63,1))*(1-E78)) | N79: =MAX(0,M78*(1-INDEX($B$11:$B$63,2))*(1-E78)) | O79: =MAX(0,N78*(1-INDEX($B$11:$B$63,3))*(1-E78)) | P79: =MAX(0,O78*(1-INDEX($B$11:$B$63,4))*(1-E78)) | Q79: =MAX(0,P78*(1-INDEX($B$11:$B$63,5))*(1-E78)) | R79: =MAX(0,Q78*(1-INDEX($B$11:$B$63,6))*(1-E78)) | S79: =MAX(0,R78*(1-INDEX($B$11:$B$63,7))*(1-E78)) | T79: =MAX(0,S78*(1-INDEX($B$11:$B$63,8))*(1-E78)) | U79: =MAX(0,T78*(1-INDEX($B$11:$B$63,9))*(1-E78)) | V79: =MAX(0,U78*(1-INDEX($B$11:$B$63,10))*(1-E78)) | W79: =MAX(0,V78*(1-INDEX($B$11:$B$63,11))*(1-E78)) | X79: =MAX(0,W78*(1-INDEX($B$11:$B$63,12))*(1-E78)) | Y79: =MAX(0,X78*(1-INDEX($B$11:$B$63,13))*(1-E78)) | Z79: =MAX(0,Y78*(1-INDEX($B$11:$B$63,14))*(1-E78)) | AA79: =MAX(0,Z78*(1-INDEX($B$11:$B$63,15))*(1-E78)) | AB79: =MAX(0,AA78*(1-INDEX($B$11:$B$63,16))*(1-E78)) | AC79: =MAX(0,AB78*(1-INDEX($B$11:$B$63,17))*(1-E78)) | AD79: =MAX(0,AC78*(1-INDEX($B$11:$B$63,18))*(1-E78)) | AE79: =MAX(0,AD78*(1-INDEX($B$11:$B$63,19))*(1-E78)) | AF79: =MAX(0,AE78*(1-INDEX($B$11:$B$63,20))*(1-E78)) | AG79: =MAX(0,AF78*(1-INDEX($B$11:$B$63,21))*(1-E78)) | AH79: =MAX(0,AG78*(1-INDEX($B$11:$B$63,22))*(1-E78)) | AI79: =MAX(0,AH78*(1-INDEX($B$11:$B$63,23))*(1-E78)) | AJ79: =MAX(0,AI78*(1-INDEX($B$11:$B$63,24))*(1-E78)) | AK79: =MAX(0,AJ78*(1-INDEX($B$11:$B$63,25))*(1-E78)) | AL79: =MAX(0,AK78*(1-INDEX($B$11:$B$63,26))*(1-E78)) | AM79: =MAX(0,AL78*(1-INDEX($B$11:$B$63,27))*(1-E78)) | AN79: =MAX(0,AM78*(1-INDEX($B$11:$B$63,28))*(1-E78)) | AO79: =MAX(0,AN78*(1-INDEX($B$11:$B$63,29))*(1-E78)) | AP79: =MAX(0,AO78*(1-INDEX($B$11:$B$63,30))*(1-E78)) | AQ79: =MAX(0,AP78*(1-INDEX($B$11:$B$63,31))*(1-E78)) | AR79: =MAX(0,AQ78*(1-INDEX($B$11:$B$63,32))*(1-E78)) | AS79: =MAX(0,AR78*(1-INDEX($B$11:$B$63,33))*(1-E78)) | AT79: =MAX(0,AS78*(1-INDEX($B$11:$B$63,34))*(1-E78)) | AU79: =MAX(0,AT78*(1-INDEX($B$11:$B$63,35))*(1-E78)) | AV79: =MAX(0,AU78*(1-INDEX($B$11:$B$63,36))*(1-E78)) | AW79: =MAX(0,AV78*(1-INDEX($B$11:$B$63,37))*(1-E78)) | AX79: =MAX(0,AW78*(1-INDEX($B$11:$B$63,38))*(1-E78)) | AY79: =MAX(0,AX78*(1-INDEX($B$11:$B$63,39))*(1-E78)) | AZ79: =MAX(0,AY78*(1-INDEX($B$11:$B$63,40))*(1-E78)) | BA79: =MAX(0,AZ78*(1-INDEX($B$11:$B$63,41))*(1-E78)) | BB79: =MAX(0,BA78*(1-INDEX($B$11:$B$63,42))*(1-E78)) | BC79: =MAX(0,BB78*(1-INDEX($B$11:$B$63,43))*(1-E78)) | BD79: =MAX(0,BC78*(1-INDEX($B$11:$B$63,44))*(1-E78)) | BE79: =MAX(0,BD78*(1-INDEX($B$11:$B$63,45))*(1-E78)) | BF79: =MAX(0,BE78*(1-INDEX($B$11:$B$63,46))*(1-E78)) | BG79: =MAX(0,BF78*(1-INDEX($B$11:$B$63,47))*(1-E78)) | BH79: =MAX(0,BG78*(1-INDEX($B$11:$B$63,48))*(1-E78)) | BI79: =MAX(0,BH78*(1-INDEX($B$11:$B$63,49))*(1-E78)) | BJ79: =MAX(0,BI78*(1-INDEX($B$11:$B$63,50))*(1-E78)) | BK79: =MAX(0,BJ78*(1-INDEX($B$11:$B$63,51))*(1-E78)) | BL79: =MAX(0,(BL78+BK78)*(1-INDEX($B$11:$B$63,53))*(1-E78))
... A326: 260 | B326: =IF(A326>Inputs!$C$62,"",SUM(M326:BK326)) | C326: =IF(A326>Inputs!$C$62,"",INDEX(Trajectory!$C$23:$C$2000,A326)) | D326: =IF(A326>Inputs!$C$62,"",SUM(L326:BK326)) | E326: =IF(A326>Inputs!$C$62,"",INDEX(Trajectory!$AG$23:$AG$2000,A326)) | F326: =IF(D326=0,0,SUMPRODUCT(L326:BK326,$B$11:$B$63)/D326) | G326: =IF(D326=0,0,MIN(0.95,1-(1-F326)*(1-E326))) | H326: =IF(D326=0,0,D326*G326) | I326: =IF(D326=0,0,D326-H326) | L326: =C326 | M326: =MAX(0,L325*(1-INDEX($B$11:$B$63,1))*(1-E325)) | N326: =MAX(0,M325*(1-INDEX($B$11:$B$63,2))*(1-E325)) | O326: =MAX(0,N325*(1-INDEX($B$11:$B$63,3))*(1-E325)) | P326: =MAX(0,O325*(1-INDEX($B$11:$B$63,4))*(1-E325)) | Q326: =MAX(0,P325*(1-INDEX($B$11:$B$63,5))*(1-E325)) | R326: =MAX(0,Q325*(1-INDEX($B$11:$B$63,6))*(1-E325)) | S326: =MAX(0,R325*(1-INDEX($B$11:$B$63,7))*(1-E325)) | T326: =MAX(0,S325*(1-INDEX($B$11:$B$63,8))*(1-E325)) | U326: =MAX(0,T325*(1-INDEX($B$11:$B$63,9))*(1-E325)) | V326: =MAX(0,U325*(1-INDEX($B$11:$B$63,10))*(1-E325)) | W326: =MAX(0,V325*(1-INDEX($B$11:$B$63,11))*(1-E325)) | X326: =MAX(0,W325*(1-INDEX($B$11:$B$63,12))*(1-E325)) | Y326: =MAX(0,X325*(1-INDEX($B$11:$B$63,13))*(1-E325)) | Z326: =MAX(0,Y325*(1-INDEX($B$11:$B$63,14))*(1-E325)) | AA326: =MAX(0,Z325*(1-INDEX($B$11:$B$63,15))*(1-E325)) | AB326: =MAX(0,AA325*(1-INDEX($B$11:$B$63,16))*(1-E325)) | AC326: =MAX(0,AB325*(1-INDEX($B$11:$B$63,17))*(1-E325)) | AD326: =MAX(0,AC325*(1-INDEX($B$11:$B$63,18))*(1-E325)) | AE326: =MAX(0,AD325*(1-INDEX($B$11:$B$63,19))*(1-E325)) | AF326: =MAX(0,AE325*(1-INDEX($B$11:$B$63,20))*(1-E325)) | AG326: =MAX(0,AF325*(1-INDEX($B$11:$B$63,21))*(1-E325)) | AH326: =MAX(0,AG325*(1-INDEX($B$11:$B$63,22))*(1-E325)) | AI326: =MAX(0,AH325*(1-INDEX($B$11:$B$63,23))*(1-E325)) | AJ326: =MAX(0,AI325*(1-INDEX($B$11:$B$63,24))*(1-E325)) | AK326: =MAX(0,AJ325*(1-INDEX($B$11:$B$63,25))*(1-E325)) | AL326: =MAX(0,AK325*(1-INDEX($B$11:$B$63,26))*(1-E325)) | AM326: =MAX(0,AL325*(1-INDEX($B$11:$B$63,27))*(1-E325)) | AN326: =MAX(0,AM325*(1-INDEX($B$11:$B$63,28))*(1-E325)) | AO326: =MAX(0,AN325*(1-INDEX($B$11:$B$63,29))*(1-E325)) | AP326: =MAX(0,AO325*(1-INDEX($B$11:$B$63,30))*(1-E325)) | AQ326: =MAX(0,AP325*(1-INDEX($B$11:$B$63,31))*(1-E325)) | AR326: =MAX(0,AQ325*(1-INDEX($B$11:$B$63,32))*(1-E325)) | AS326: =MAX(0,AR325*(1-INDEX($B$11:$B$63,33))*(1-E325)) | AT326: =MAX(0,AS325*(1-INDEX($B$11:$B$63,34))*(1-E325)) | AU326: =MAX(0,AT325*(1-INDEX($B$11:$B$63,35))*(1-E325)) | AV326: =MAX(0,AU325*(1-INDEX($B$11:$B$63,36))*(1-E325)) | AW326: =MAX(0,AV325*(1-INDEX($B$11:$B$63,37))*(1-E325)) | AX326: =MAX(0,AW325*(1-INDEX($B$11:$B$63,38))*(1-E325)) | AY326: =MAX(0,AX325*(1-INDEX($B$11:$B$63,39))*(1-E325)) | AZ326: =MAX(0,AY325*(1-INDEX($B$11:$B$63,40))*(1-E325)) | BA326: =MAX(0,AZ325*(1-INDEX($B$11:$B$63,41))*(1-E325)) | BB326: =MAX(0,BA325*(1-INDEX($B$11:$B$63,42))*(1-E325)) | BC326: =MAX(0,BB325*(1-INDEX($B$11:$B$63,43))*(1-E325)) | BD326: =MAX(0,BC325*(1-INDEX($B$11:$B$63,44))*(1-E325)) | BE326: =MAX(0,BD325*(1-INDEX($B$11:$B$63,45))*(1-E325)) | BF326: =MAX(0,BE325*(1-INDEX($B$11:$B$63,46))*(1-E325)) | BG326: =MAX(0,BF325*(1-INDEX($B$11:$B$63,47))*(1-E325)) | BH326: =MAX(0,BG325*(1-INDEX($B$11:$B$63,48))*(1-E325)) | BI326: =MAX(0,BH325*(1-INDEX($B$11:$B$63,49))*(1-E325)) | BJ326: =MAX(0,BI325*(1-INDEX($B$11:$B$63,50))*(1-E325)) | BK326: =MAX(0,BJ325*(1-INDEX($B$11:$B$63,51))*(1-E325)) | BL326: =MAX(0,(BL325+BK325)*(1-INDEX($B$11:$B$63,53))*(1-E325))

Sheet CapacityPlan
A1: Capacity Plan (site ramp efficiency and effective throughput)
M3: Ramp curve (age weeks)
M4: Age_wk | N4: Eff
M5: 1 | N5: =IF(M5>Inputs!$C$93,1, Inputs!$C$94 + (1-Inputs!$C$94)*(M5-1)/MAX(1,Inputs!$C$93-1))
A6: Week | B6: Demand_Boxes | C6: Demand_Lagged | D6: Sites_Req | E6: Sites_Online | F6: Sites_Added | G6: Ramp_Eff_Avg | H6: Eff_Sites | I6: Capacity_Boxes | J6: VarCost_Mult | K6: Utilization | L6: Lag1 | M6: Lag2 | N6: Lag3 | O6: Lag4 | P6: Lag5 | Q6: Lag6 | R6: Lag7 | S6: Lag8 | T6: Lag9 | U6: Lag10 | V6: Lag11 | W6: Lag12 | X6: Lag13 | Y6: Lag14 | Z6: Lag15 | AA6: Lag16
A7: 1 | B7: =IF(A7>Inputs!$C$62,"",INDEX(Trajectory!$G$23:$G$2000,A7)) | C7: =IF(B7="","",IF(A7<=Inputs!$C$75,INDEX(Trajectory!$G$23:$G$2000,1),INDEX(Trajectory!$G$23:$G$2000,MAX(1,A7-Inputs!$C$75)))) | D7: =IF(C7="","",MAX(Inputs!$C$76,CEILING(C7/(Inputs!$C$42*Inputs!$C$92),1))) | E7: =D7 | F7: =E7-Inputs!$C$76 | G7: =IF(E7="",1,IF(E7=0,1,(E7-SUM(L7:AA7)+SUMPRODUCT(L7:AA7,$N$5:$N$20))/E7)) | H7: =IF(E7="",0,E7*G7) | I7: =IF(H7="",0,H7*Inputs!$C$42) | J7: =IF(E7="",1,1 + (Inputs!$C$95-1)*IF((1-Inputs!$C$94)=0,0,(1-G7)/(1-Inputs!$C$94))) | K7: =IF(I7=0,"",B7/I7) | L7: =IF(F7="",0,F7) | M7: =IF(A7<=1,0,0) | N7: =IF(A7<=1,0,0) | O7: =IF(A7<=1,0,0) | P7: =IF(A7<=1,0,0) | Q7: =IF(A7<=1,0,0) | R7: =IF(A7<=1,0,0) | S7: =IF(A7<=1,0,0) | T7: =IF(A7<=1,0,0) | U7: =IF(A7<=1,0,0) | V7: =IF(A7<=1,0,0) | W7: =IF(A7<=1,0,0) | X7: =IF(A7<=1,0,0) | Y7: =IF(A7<=1,0,0) | Z7: =IF(A7<=1,0,0) | AA7: =IF(A7<=1,0,0)
A8: 2 | B8: =IF(A8>Inputs!$C$62,"",INDEX(Trajectory!$G$23:$G$2000,A8)) | C8: =IF(B8="","",IF(A8<=Inputs!$C$75,INDEX(Trajectory!$G$23:$G$2000,1),INDEX(Trajectory!$G$23:$G$2000,MAX(1,A8-Inputs!$C$75)))) | D8: =IF(C8="","",MAX(Inputs!$C$76,CEILING(C8/(Inputs!$C$42*Inputs!$C$92),1))) | E8: =IF(D8="","",MAX(E7,D8)) | F8: =E8-E7 | G8: =IF(E8="",1,IF(E8=0,1,(E8-SUM(L8:AA8)+SUMPRODUCT(L8:AA8,$N$5:$N$20))/E8)) | H8: =IF(E8="",0,E8*G8) | I8: =IF(H8="",0,H8*Inputs!$C$42) | J8: =IF(E8="",1,1 + (Inputs!$C$95-1)*IF((1-Inputs!$C$94)=0,0,(1-G8)/(1-Inputs!$C$94))) | K8: =IF(I8=0,"",B8/I8) | L8: =IF(F8="",0,F8) | M8: =IF(A8<=1,0,L7) | N8: =IF(A8<=1,0,M7) | O8: =IF(A8<=1,0,N7) | P8: =IF(A8<=1,0,O7) | Q8: =IF(A8<=1,0,P7) | R8: =IF(A8<=1,0,Q7) | S8: =IF(A8<=1,0,R7) | T8: =IF(A8<=1,0,S7) | U8: =IF(A8<=1,0,T7) | V8: =IF(A8<=1,0,U7) | W8: =IF(A8<=1,0,V7) | X8: =IF(A8<=1,0,W7) | Y8: =IF(A8<=1,0,X7) | Z8: =IF(A8<=1,0,Y7) | AA8: =IF(A8<=1,0,Z7)
A9: 3 | B9: =IF(A9>Inputs!$C$62,"",INDEX(Trajectory!$G$23:$G$2000,A9)) | C9: =IF(B9="","",IF(A9<=Inputs!$C$75,INDEX(Trajectory!$G$23:$G$2000,1),INDEX(Trajectory!$G$23:$G$2000,MAX(1,A9-Inputs!$C$75)))) | D9: =IF(C9="","",MAX(Inputs!$C$76,CEILING(C9/(Inputs!$C$42*Inputs!$C$92),1))) | E9: =IF(D9="","",MAX(E8,D9)) | F9: =E9-E8 | G9: =IF(E9="",1,IF(E9=0,1,(E9-SUM(L9:AA9)+SUMPRODUCT(L9:AA9,$N$5:$N$20))/E9)) | H9: =IF(E9="",0,E9*G9) | I9: =IF(H9="",0,H9*Inputs!$C$42) | J9: =IF(E9="",1,1 + (Inputs!$C$95-1)*IF((1-Inputs!$C$94)=0,0,(1-G9)/(1-Inputs!$C$94))) | K9: =IF(I9=0,"",B9/I9) | L9: =IF(F9="",0,F9) | M9: =IF(A9<=1,0,L8) | N9: =IF(A9<=1,0,M8) | O9: =IF(A9<=1,0,N8) | P9: =IF(A9<=1,0,O8) | Q9: =IF(A9<=1,0,P8) | R9: =IF(A9<=1,0,Q8) | S9: =IF(A9<=1,0,R8) | T9: =IF(A9<=1,0,S8) | U9: =IF(A9<=1,0,T8) | V9: =IF(A9<=1,0,U8) | W9: =IF(A9<=1,0,V8) | X9: =IF(A9<=1,0,W8) | Y9: =IF(A9<=1,0,X8) | Z9: =IF(A9<=1,0,Y8) | AA9: =IF(A9<=1,0,Z8)
A10: 4 | B10: =IF(A10>Inputs!$C$62,"",INDEX(Trajectory!$G$23:$G$2000,A10)) | C10: =IF(B10="","",IF(A10<=Inputs!$C$75,INDEX(Trajectory!$G$23:$G$2000,1),INDEX(Trajectory!$G$23:$G$2000,MAX(1,A10-Inputs!$C$75)))) | D10: =IF(C10="","",MAX(Inputs!$C$76,CEILING(C10/(Inputs!$C$42*Inputs!$C$92),1))) | E10: =IF(D10="","",MAX(E9,D10)) | F10: =E10-E9 | G10: =IF(E10="",1,IF(E10=0,1,(E10-SUM(L10:AA10)+SUMPRODUCT(L10:AA10,$N$5:$N$20))/E10)) | H10: =IF(E10="",0,E10*G10) | I10: =IF(H10="",0,H10*Inputs!$C$42) | J10: =IF(E10="",1,1 + (Inputs!$C$95-1)*IF((1-Inputs!$C$94)=0,0,(1-G10)/(1-Inputs!$C$94))) | K10: =IF(I10=0,"",B10/I10) | L10: =IF(F10="",0,F10) | M10: =IF(A10<=1,0,L9) | N10: =IF(A10<=1,0,M9) | O10: =IF(A10<=1,0,N9) | P10: =IF(A10<=1,0,O9) | Q10: =IF(A10<=1,0,P9) | R10: =IF(A10<=1,0,Q9) | S10: =IF(A10<=1,0,R9) | T10: =IF(A10<=1,0,S9) | U10: =IF(A10<=1,0,T9) | V10: =IF(A10<=1,0,U9) | W10: =IF(A10<=1,0,V9) | X10: =IF(A10<=1,0,W9) | Y10: =IF(A10<=1,0,X9) | Z10: =IF(A10<=1,0,Y9) | AA10: =IF(A10<=1,0,Z9)
A11: 5 | B11: =IF(A11>Inputs!$C$62,"",INDEX(Trajectory!$G$23:$G$2000,A11)) | C11: =IF(B11="","",IF(A11<=Inputs!$C$75,INDEX(Trajectory!$G$23:$G$2000,1),INDEX(Trajectory!$G$23:$G$2000,MAX(1,A11-Inputs!$C$75)))) | D11: =IF(C11="","",MAX(Inputs!$C$76,CEILING(C11/(Inputs!$C$42*Inputs!$C$92),1))) | E11: =IF(D11="","",MAX(E10,D11)) | F11: =E11-E10 | G11: =IF(E11="",1,IF(E11=0,1,(E11-SUM(L11:AA11)+SUMPRODUCT(L11:AA11,$N$5:$N$20))/E11)) | H11: =IF(E11="",0,E11*G11) | I11: =IF(H11="",0,H11*Inputs!$C$42) | J11: =IF(E11="",1,1 + (Inputs!$C$95-1)*IF((1-Inputs!$C$94)=0,0,(1-G11)/(1-Inputs!$C$94))) | K11: =IF(I11=0,"",B11/I11) | L11: =IF(F11="",0,F11) | M11: =IF(A11<=1,0,L10) | N11: =IF(A11<=1,0,M10) | O11: =IF(A11<=1,0,N10) | P11: =IF(A11<=1,0,O10) | Q11: =IF(A11<=1,0,P10) | R11: =IF(A11<=1,0,Q10) | S11: =IF(A11<=1,0,R10) | T11: =IF(A11<=1,0,S10) | U11: =IF(A11<=1,0,T10) | V11: =IF(A11<=1,0,U10) | W11: =IF(A11<=1,0,V10) | X11: =IF(A11<=1,0,W10) | Y11: =IF(A11<=1,0,X10) | Z11: =IF(A11<=1,0,Y10) | AA11: =IF(A11<=1,0,Z10)
A12: 6 | B12: =IF(A12>Inputs!$C$62,"",INDEX(Trajectory!$G$23:$G$2000,A12)) | C12: =IF(B12="","",IF(A12<=Inputs!$C$75,INDEX(Trajectory!$G$23:$G$2000,1),INDEX(Trajectory!$G$23:$G$2000,MAX(1,A12-Inputs!$C$75)))) | D12: =IF(C12="","",MAX(Inputs!$C$76,CEILING(C12/(Inputs!$C$42*Inputs!$C$92),1))) | E12: =IF(D12="","",MAX(E11,D12)) | F12: =E12-E11 | G12: =IF(E12="",1,IF(E12=0,1,(E12-SUM(L12:AA12)+SUMPRODUCT(L12:AA12,$N$5:$N$20))/E12)) | H12: =IF(E12="",0,E12*G12) | I12: =IF(H12="",0,H12*Inputs!$C$42) | J12: =IF(E12="",1,1 + (Inputs!$C$95-1)*IF((1-Inputs!$C$94)=0,0,(1-G12)/(1-Inputs!$C$94))) | K12: =IF(I12=0,"",B12/I12) | L12: =IF(F12="",0,F12) | M12: =IF(A12<=1,0,L11) | N12: =IF(A12<=1,0,M11) | O12: =IF(A12<=1,0,N11) | P12: =IF(A12<=1,0,O11) | Q12: =IF(A12<=1,0,P11) | R12: =IF(A12<=1,0,Q11) | S12: =IF(A12<=1,0,R11) | T12: =IF(A12<=1,0,S11) | U12: =IF(A12<=1,0,T11) | V12: =IF(A12<=1,0,U11) | W12: =IF(A12<=1,0,V11) | X12: =IF(A12<=1,0,W11) | Y12: =IF(A12<=1,0,X11) | Z12: =IF(A12<=1,0,Y11) | AA12: =IF(A12<=1,0,Z11)
A13: 7 | B13: =IF(A13>Inputs!$C$62,"",INDEX(Trajectory!$G$23:$G$2000,A13)) | C13: =IF(B13="","",IF(A13<=Inputs!$C$75,INDEX(Trajectory!$G$23:$G$2000,1),INDEX(Trajectory!$G$23:$G$2000,MAX(1,A13-Inputs!$C$75)))) | D13: =IF(C13="","",MAX(Inputs!$C$76,CEILING(C13/(Inputs!$C$42*Inputs!$C$92),1))) | E13: =IF(D13="","",MAX(E12,D13)) | F13: =E13-E12 | G13: =IF(E13="",1,IF(E13=0,1,(E13-SUM(L13:AA13)+SUMPRODUCT(L13:AA13,$N$5:$N$20))/E13)) | H13: =IF(E13="",0,E13*G13) | I13: =IF(H13="",0,H13*Inputs!$C$42) | J13: =IF(E13="",1,1 + (Inputs!$C$95-1)*IF((1-Inputs!$C$94)=0,0,(1-G13)/(1-Inputs!$C$94))) | K13: =IF(I13=0,"",B13/I13) | L13: =IF(F13="",0,F13) | M13: =IF(A13<=1,0,L12) | N13: =IF(A13<=1,0,M12) | O13: =IF(A13<=1,0,N12) | P13: =IF(A13<=1,0,O12) | Q13: =IF(A13<=1,0,P12) | R13: =IF(A13<=1,0,Q12) | S13: =IF(A13<=1,0,R12) | T13: =IF(A13<=1,0,S12) | U13: =IF(A13<=1,0,T12) | V13: =IF(A13<=1,0,U12) | W13: =IF(A13<=1,0,V12) | X13: =IF(A13<=1,0,W12) | Y13: =IF(A13<=1,0,X12) | Z13: =IF(A13<=1,0,Y12) | AA13: =IF(A13<=1,0,Z12)
A14: 8 | B14: =IF(A14>Inputs!$C$62,"",INDEX(Trajectory!$G$23:$G$2000,A14)) | C14: =IF(B14="","",IF(A14<=Inputs!$C$75,INDEX(Trajectory!$G$23:$G$2000,1),INDEX(Trajectory!$G$23:$G$2000,MAX(1,A14-Inputs!$C$75)))) | D14: =IF(C14="","",MAX(Inputs!$C$76,CEILING(C14/(Inputs!$C$42*Inputs!$C$92),1))) | E14: =IF(D14="","",MAX(E13,D14)) | F14: =E14-E13 | G14: =IF(E14="",1,IF(E14=0,1,(E14-SUM(L14:AA14)+SUMPRODUCT(L14:AA14,$N$5:$N$20))/E14)) | H14: =IF(E14="",0,E14*G14) | I14: =IF(H14="",0,H14*Inputs!$C$42) | J14: =IF(E14="",1,1 + (Inputs!$C$95-1)*IF((1-Inputs!$C$94)=0,0,(1-G14)/(1-Inputs!$C$94))) | K14: =IF(I14=0,"",B14/I14) | L14: =IF(F14="",0,F14) | M14: =IF(A14<=1,0,L13) | N14: =IF(A14<=1,0,M13) | O14: =IF(A14<=1,0,N13) | P14: =IF(A14<=1,0,O13) | Q14: =IF(A14<=1,0,P13) | R14: =IF(A14<=1,0,Q13) | S14: =IF(A14<=1,0,R13) | T14: =IF(A14<=1,0,S13) | U14: =IF(A14<=1,0,T13) | V14: =IF(A14<=1,0,U13) | W14: =IF(A14<=1,0,V13) | X14: =IF(A14<=1,0,W13) | Y14: =IF(A14<=1,0,X13) | Z14: =IF(A14<=1,0,Y13) | AA14: =IF(A14<=1,0,Z13)
A15: 9 | B15: =IF(A15>Inputs!$C$62,"",INDEX(Trajectory!$G$23:$G$2000,A15)) | C15: =IF(B15="","",IF(A15<=Inputs!$C$75,INDEX(Trajectory!$G$23:$G$2000,1),INDEX(Trajectory!$G$23:$G$2000,MAX(1,A15-Inputs!$C$75)))) | D15: =IF(C15="","",MAX(Inputs!$C$76,CEILING(C15/(Inputs!$C$42*Inputs!$C$92),1))) | E15: =IF(D15="","",MAX(E14,D15)) | F15: =E15-E14 | G15: =IF(E15="",1,IF(E15=0,1,(E15-SUM(L15:AA15)+SUMPRODUCT(L15:AA15,$N$5:$N$20))/E15)) | H15: =IF(E15="",0,E15*G15) | I15: =IF(H15="",0,H15*Inputs!$C$42) | J15: =IF(E15="",1,1 + (Inputs!$C$95-1)*IF((1-Inputs!$C$94)=0,0,(1-G15)/(1-Inputs!$C$94))) | K15: =IF(I15=0,"",B15/I15) | L15: =IF(F15="",0,F15) | M15: =IF(A15<=1,0,L14) | N15: =IF(A15<=1,0,M14) | O15: =IF(A15<=1,0,N14) | P15: =IF(A15<=1,0,O14) | Q15: =IF(A15<=1,0,P14) | R15: =IF(A15<=1,0,Q14) | S15: =IF(A15<=1,0,R14) | T15: =IF(A15<=1,0,S14) | U15: =IF(A15<=1,0,T14) | V15: =IF(A15<=1,0,U14) | W15: =IF(A15<=1,0,V14) | X15: =IF(A15<=1,0,W14) | Y15: =IF(A15<=1,0,X14) | Z15: =IF(A15<=1,0,Y14) | AA15: =IF(A15<=1,0,Z14)
A16: 10 | B16: =IF(A16>Inputs!$C$62,"",INDEX(Trajectory!$G$23:$G$2000,A16)) | C16: =IF(B16="","",IF(A16<=Inputs!$C$75,INDEX(Trajectory!$G$23:$G$2000,1),INDEX(Trajectory!$G$23:$G$2000,MAX(1,A16-Inputs!$C$75)))) | D16: =IF(C16="","",MAX(Inputs!$C$76,CEILING(C16/(Inputs!$C$42*Inputs!$C$92),1))) | E16: =IF(D16="","",MAX(E15,D16)) | F16: =E16-E15 | G16: =IF(E16="",1,IF(E16=0,1,(E16-SUM(L16:AA16)+SUMPRODUCT(L16:AA16,$N$5:$N$20))/E16)) | H16: =IF(E16="",0,E16*G16) | I16: =IF(H16="",0,H16*Inputs!$C$42) | J16: =IF(E16="",1,1 + (Inputs!$C$95-1)*IF((1-Inputs!$C$94)=0,0,(1-G16)/(1-Inputs!$C$94))) | K16: =IF(I16=0,"",B16/I16) | L16: =IF(F16="",0,F16) | M16: =IF(A16<=1,0,L15) | N16: =IF(A16<=1,0,M15) | O16: =IF(A16<=1,0,N15) | P16: =IF(A16<=1,0,O15) | Q16: =IF(A16<=1,0,P15) | R16: =IF(A16<=1,0,Q15) | S16: =IF(A16<=1,0,R15) | T16: =IF(A16<=1,0,S15) | U16: =IF(A16<=1,0,T15) | V16: =IF(A16<=1,0,U15) | W16: =IF(A16<=1,0,V15) | X16: =IF(A16<=1,0,W15) | Y16: =IF(A16<=1,0,X15) | Z16: =IF(A16<=1,0,Y15) | AA16: =IF(A16<=1,0,Z15)
A17: 11 | B17: =IF(A17>Inputs!$C$62,"",INDEX(Trajectory!$G$23:$G$2000,A17)) | C17: =IF(B17="","",IF(A17<=Inputs!$C$75,INDEX(Trajectory!$G$23:$G$2000,1),INDEX(Trajectory!$G$23:$G$2000,MAX(1,A17-Inputs!$C$75)))) | D17: =IF(C17="","",MAX(Inputs!$C$76,CEILING(C17/(Inputs!$C$42*Inputs!$C$92),1))) | E17: =IF(D17="","",MAX(E16,D17)) | F17: =E17-E16 | G17: =IF(E17="",1,IF(E17=0,1,(E17-SUM(L17:AA17)+SUMPRODUCT(L17:AA17,$N$5:$N$20))/E17)) | H17: =IF(E17="",0,E17*G17) | I17: =IF(H17="",0,H17*Inputs!$C$42) | J17: =IF(E17="",1,1 + (Inputs!$C$95-1)*IF((1-Inputs!$C$94)=0,0,(1-G17)/(1-Inputs!$C$94))) | K17: =IF(I17=0,"",B17/I17) | L17: =IF(F17="",0,F17) | M17: =IF(A17<=1,0,L16) | N17: =IF(A17<=1,0,M16) | O17: =IF(A17<=1,0,N16) | P17: =IF(A17<=1,0,O16) | Q17: =IF(A17<=1,0,P16) | R17: =IF(A17<=1,0,Q16) | S17: =IF(A17<=1,0,R16) | T17: =IF(A17<=1,0,S16) | U17: =IF(A17<=1,0,T16) | V17: =IF(A17<=1,0,U16) | W17: =IF(A17<=1,0,V16) | X17: =IF(A17<=1,0,W16) | Y17: =IF(A17<=1,0,X16) | Z17: =IF(A17<=1,0,Y16) | AA17: =IF(A17<=1,0,Z16)
A18: 12 | B18: =IF(A18>Inputs!$C$62,"",INDEX(Trajectory!$G$23:$G$2000,A18)) | C18: =IF(B18="","",IF(A18<=Inputs!$C$75,INDEX(Trajectory!$G$23:$G$2000,1),INDEX(Trajectory!$G$23:$G$2000,MAX(1,A18-Inputs!$C$75)))) | D18: =IF(C18="","",MAX(Inputs!$C$76,CEILING(C18/(Inputs!$C$42*Inputs!$C$92),1))) | E18: =IF(D18="","",MAX(E17,D18)) | F18: =E18-E17 | G18: =IF(E18="",1,IF(E18=0,1,(E18-SUM(L18:AA18)+SUMPRODUCT(L18:AA18,$N$5:$N$20))/E18)) | H18: =IF(E18="",0,E18*G18) | I18: =IF(H18="",0,H18*Inputs!$C$42) | J18: =IF(E18="",1,1 + (Inputs!$C$95-1)*IF((1-Inputs!$C$94)=0,0,(1-G18)/(1-Inputs!$C$94))) | K18: =IF(I18=0,"",B18/I18) | L18: =IF(F18="",0,F18) | M18: =IF(A18<=1,0,L17) | N18: =IF(A18<=1,0,M17) | O18: =IF(A18<=1,0,N17) | P18: =IF(A18<=1,0,O17) | Q18: =IF(A18<=1,0,P17) | R18: =IF(A18<=1,0,Q17) | S18: =IF(A18<=1,0,R17) | T18: =IF(A18<=1,0,S17) | U18: =IF(A18<=1,0,T17) | V18: =IF(A18<=1,0,U17) | W18: =IF(A18<=1,0,V17) | X18: =IF(A18<=1,0,W17) | Y18: =IF(A18<=1,0,X17) | Z18: =IF(A18<=1,0,Y17) | AA18: =IF(A18<=1,0,Z17)
A19: 13 | B19: =IF(A19>Inputs!$C$62,"",INDEX(Trajectory!$G$23:$G$2000,A19)) | C19: =IF(B19="","",IF(A19<=Inputs!$C$75,INDEX(Trajectory!$G$23:$G$2000,1),INDEX(Trajectory!$G$23:$G$2000,MAX(1,A19-Inputs!$C$75)))) | D19: =IF(C19="","",MAX(Inputs!$C$76,CEILING(C19/(Inputs!$C$42*Inputs!$C$92),1))) | E19: =IF(D19="","",MAX(E18,D19)) | F19: =E19-E18 | G19: =IF(E19="",1,IF(E19=0,1,(E19-SUM(L19:AA19)+SUMPRODUCT(L19:AA19,$N$5:$N$20))/E19)) | H19: =IF(E19="",0,E19*G19) | I19: =IF(H19="",0,H19*Inputs!$C$42) | J19: =IF(E19="",1,1 + (Inputs!$C$95-1)*IF((1-Inputs!$C$94)=0,0,(1-G19)/(1-Inputs!$C$94))) | K19: =IF(I19=0,"",B19/I19) | L19: =IF(F19="",0,F19) | M19: =IF(A19<=1,0,L18) | N19: =IF(A19<=1,0,M18) | O19: =IF(A19<=1,0,N18) | P19: =IF(A19<=1,0,O18) | Q19: =IF(A19<=1,0,P18) | R19: =IF(A19<=1,0,Q18) | S19: =IF(A19<=1,0,R18) | T19: =IF(A19<=1,0,S18) | U19: =IF(A19<=1,0,T18) | V19: =IF(A19<=1,0,U18) | W19: =IF(A19<=1,0,V18) | X19: =IF(A19<=1,0,W18) | Y19: =IF(A19<=1,0,X18) | Z19: =IF(A19<=1,0,Y18) | AA19: =IF(A19<=1,0,Z18)
... A266: 260 | B266: =IF(A266>Inputs!$C$62,"",INDEX(Trajectory!$G$23:$G$2000,A266)) | C266: =IF(B266="","",IF(A266<=Inputs!$C$75,INDEX(Trajectory!$G$23:$G$2000,1),INDEX(Trajectory!$G$23:$G$2000,MAX(1,A266-Inputs!$C$75)))) | D266: =IF(C266="","",MAX(Inputs!$C$76,CEILING(C266/(Inputs!$C$42*Inputs!$C$92),1))) | E266: =IF(D266="","",MAX(E265,D266)) | F266: =E266-E265 | G266: =IF(E266="",1,IF(E266=0,1,(E266-SUM(L266:AA266)+SUMPRODUCT(L266:AA266,$N$5:$N$20))/E266)) | H266: =IF(E266="",0,E266*G266) | I266: =IF(H266="",0,H266*Inputs!$C$42) | J266: =IF(E266="",1,1 + (Inputs!$C$95-1)*IF((1-Inputs!$C$94)=0,0,(1-G266)/(1-Inputs!$C$94))) | K266: =IF(I266=0,"",B266/I266) | L266: =IF(F266="",0,F266) | M266: =IF(A266<=1,0,L265) | N266: =IF(A266<=1,0,M265) | O266: =IF(A266<=1,0,N265) | P266: =IF(A266<=1,0,O265) | Q266: =IF(A266<=1,0,P265) | R266: =IF(A266<=1,0,Q265) | S266: =IF(A266<=1,0,R265) | T266: =IF(A266<=1,0,S265) | U266: =IF(A266<=1,0,T265) | V266: =IF(A266<=1,0,U265) | W266: =IF(A266<=1,0,V265) | X266: =IF(A266<=1,0,W265) | Y266: =IF(A266<=1,0,X265) | Z266: =IF(A266<=1,0,Y265) | AA266: =IF(A266<=1,0,Z265)

Sheet Trajectory
A1: Trajectory Simulation (weekly cadence, capacity steps, inventory, cash)
A3: Inputs (linked) | D3: Key Outputs (derived)
A4: Horizon (weeks) | B4: =Inputs!C62 | D4: Min cash balance | E4: =MIN(AA23:INDEX(AA:AA,22+Inputs!$C$62))
A5: Start active users | B5: =Inputs!C63 | D5: Weeks to cash-out | E5: =IF(E4>=0,"",MATCH(1,AB23:INDEX(AB:AB,22+Inputs!$C$62),0))
A6: Weekly new users | B6: =Inputs!C64 | D6: Min fulfill rate | E6: =MIN(K23:INDEX(K:K,22+Inputs!$C$62))
A7: Base churn (weekly) | B7: =Inputs!C66 | D7: Max required garments | E7: =MAX(R23:INDEX(R:R,22+Inputs!$C$62))
A8: Start cash | B8: =Inputs!C72 | D8: Max inventory multiple | E8: =MAX(AC23:INDEX(AC:AC,22+Inputs!$C$62))
A9: CAC per new user | B9: =Inputs!C65
A10: Site add lead (wks) | B10: =Inputs!C75
A11: Inventory lead (wks) | B11: =Inputs!C73
A22: Week | B22: Active_Begin | C22: New_Users | D22: Churn_Rate | E22: Churned | F22: Active_End | G22: Demand_Boxes | H22: Sites_Online | I22: Capacity_Boxes | J22: Fulfilled | K22: Fulfill_Rate | L22: Refund_Rate | M22: Net_Revenue | N22: Var_Cost | O22: CM | P22: Fixed_OPEX | Q22: Op_Profit | R22: Req_Garments | S22: Inv_OnHand_Begin | T22: Replace_Garments | U22: Order_Garments | V22: Arrivals | W22: Inv_OnHand_End | X22: Inv_Spend | Y22: CAC_Spend | Z22: Cash_Begin | AA22: Cash_End | AB22: Cash_Neg_Flag | AC22: Inv_Multiple | AD22: Active_Service | AE22: CAC_t | AF22: Mktg_Budget | AG22: Churn_Shock | AH22: Ramp_Eff | AI22: VarCost_Mult | AJ22: Utilization
A23: 1 | B23: =IF(A23>Inputs!$C$62,"",IF(Inputs!$C$80=1,INDEX(Cohorts!$B$67:$B$326,A23),IF(A23=1,Inputs!$C$63,F22))) | C23: =IF(A23>Inputs!$C$62,"",IF(Inputs!$C$85=0,Inputs!$C$64,MIN(Inputs!$C$91,IF(AE23=0,0,AF23/AE23)))) | D23: =IF(A23>Inputs!$C$62,"",IF(Inputs!$C$80=1,INDEX(Cohorts!$G$67:$G$326,A23),MAX(0, Inputs!$C$66 + Inputs!$C$67*L23 + Inputs!$C$68*(1-K23) + Inputs!$C$69*Inputs!$C$10))) | E23: =IF(A23>Inputs!$C$62,"",IF(Inputs!$C$80=1,INDEX(Cohorts!$H$67:$H$326,A23),D23*AD23)) | F23: =IF(A23>Inputs!$C$62,"",IF(Inputs!$C$80=1,INDEX(Cohorts!$I$67:$I$326,A23),AD23-E23)) | G23: =IF(A23>Inputs!$C$62,"",AD23) | H23: =IF(A23>Inputs!$C$62,"",INDEX(CapacityPlan!$E$7:$E$266,A23)) | I23: =IF(A23>Inputs!$C$62,"",INDEX(CapacityPlan!$I$7:$I$266,A23)) | J23: =IF(A23>Inputs!$C$62,"",IF(G23>I23,I23,G23)) | K23: =IF(A23>Inputs!$C$62,"",IF(G23=0,1,J23/G23)) | L23: =IF((Inputs!$C$36 + UnitEconomics!$B$12*Inputs!$C$37 + Inputs!$C$10*Inputs!$C$38 + Inputs!$C$70*(1-K23))>1,1,(Inputs!$C$36 + UnitEconomics!$B$12*Inputs!$C$37 + Inputs!$C$10*Inputs!$C$38 + Inputs!$C$70*(1-K23))) | M23: =IF(A23>Inputs!$C$62,"",J23*Inputs!$C$7*(1-Inputs!$C$8)*(1-L23)) | N23: =IF(A23>Inputs!$C$62,"",J23*UnitEconomics!$B$32*AI23 + (G23-J23)*Inputs!$C$71) | O23: =M23-N23 | P23: =IF(A23>Inputs!$C$62,"",Inputs!$C$40 + H23*Inputs!$C$41) | Q23: =O23-P23 | R23: =IF(A23>Inputs!$C$62,"",AD23*Inputs!$C$16*(Inputs!$C$9 + Inputs!$C$10*Inputs!$C$11 + Inputs!$C$12)*(1 + VLOOKUP(Inputs!$C$15,Lookups!$A$2:$B$20,2,TRUE)*(Scale!$B$9/IF(Scale!$B$8=0,1,Scale!$B$8)) + Inputs!$C$52)) | S23: =IF(A23=1,Scale!$B$13, W22) | T23: =J23*Inputs!$C$16*(Inputs!$C$19 + Inputs!$C$20*Inputs!$C$21 + 1/Inputs!$C$18) | U23: =MAX(0, (R23*(1+Inputs!$C$74)) - (S23 - T23)) | V23: =IF(A23<=Inputs!$C$73,0,INDEX(U:U,ROW()-Inputs!$C$73)) | W23: =S23 - T23 + V23 | X23: =V23*Inputs!$C$17 | Y23: =IF(A23>Inputs!$C$62,"",C23*AE23) | Z23: =IF(A23=1,Inputs!$C$72,AA22) | AA23: =Z23 + M23 - N23 - P23 - X23 - Y23 | AB23: =IF(AA23<0,1,0) | AC23: =IF(AD23=0,0,R23/(AD23*Inputs!$C$16)) | AD23: =IF(A23>Inputs!$C$62,"",B23+C23) | AE23: =IF(A23>Inputs!$C$62,"", Inputs!$C$65*(1+Inputs!$C$89*POWER(MIN(1,IF(Inputs!$C$88=0,0,B23/Inputs!$C$88)),Inputs!$C$90))) | AF23: =IF(A23>Inputs!$C$62,"",IF(A23=1,Inputs!$C$86,MIN(Inputs!$C$86,Inputs!$C$87*M22))) | AG23: =IF(A23>Inputs!$C$62,"",MIN(0.5,MAX(0, Inputs!$C$67*L23 + Inputs!$C$68*(1-K23) + Inputs!$C$69*Inputs!$C$10))) | AH23: =IF(A23>Inputs!$C$62,"",INDEX(CapacityPlan!$G$7:$G$266,A23)) | AI23: =IF(A23>Inputs!$C$62,"",INDEX(CapacityPlan!$J$7:$J$266,A23)) | AJ23: =IF(A23>Inputs!$C$62,"",IF(I23=0,"",G23/I23))
A24: 2 | B24: =IF(A24>Inputs!$C$62,"",IF(Inputs!$C$80=1,INDEX(Cohorts!$B$67:$B$326,A24),IF(A24=1,Inputs!$C$63,F23))) | C24: =IF(A24>Inputs!$C$62,"",IF(Inputs!$C$85=0,Inputs!$C$64,MIN(Inputs!$C$91,IF(AE24=0,0,AF24/AE24)))) | D24: =IF(A24>Inputs!$C$62,"",IF(Inputs!$C$80=1,INDEX(Cohorts!$G$67:$G$326,A24),MAX(0, Inputs!$C$66 + Inputs!$C$67*L24 + Inputs!$C$68*(1-K24) + Inputs!$C$69*Inputs!$C$10))) | E24: =IF(A24>Inputs!$C$62,"",IF(Inputs!$C$80=1,INDEX(Cohorts!$H$67:$H$326,A24),D24*AD24)) | F24: =IF(A24>Inputs!$C$62,"",IF(Inputs!$C$80=1,INDEX(Cohorts!$I$67:$I$326,A24),AD24-E24)) | G24: =IF(A24>Inputs!$C$62,"",AD24) | H24: =IF(A24>Inputs!$C$62,"",INDEX(CapacityPlan!$E$7:$E$266,A24)) | I24: =IF(A24>Inputs!$C$62,"",INDEX(CapacityPlan!$I$7:$I$266,A24)) | J24: =IF(A24>Inputs!$C$62,"",IF(G24>I24,I24,G24)) | K24: =IF(A24>Inputs!$C$62,"",IF(G24=0,1,J24/G24)) | L24: =IF((Inputs!$C$36 + UnitEconomics!$B$12*Inputs!$C$37 + Inputs!$C$10*Inputs!$C$38 + Inputs!$C$70*(1-K24))>1,1,(Inputs!$C$36 + UnitEconomics!$B$12*Inputs!$C$37 + Inputs!$C$10*Inputs!$C$38 + Inputs!$C$70*(1-K24))) | M24: =IF(A24>Inputs!$C$62,"",J24*Inputs!$C$7*(1-Inputs!$C$8)*(1-L24)) | N24: =IF(A24>Inputs!$C$62,"",J24*UnitEconomics!$B$32*AI24 + (G24-J24)*Inputs!$C$71) | O24: =M24-N24 | P24: =IF(A24>Inputs!$C$62,"",Inputs!$C$40 + H24*Inputs!$C$41) | Q24: =O24-P24 | R24: =IF(A24>Inputs!$C$62,"",AD24*Inputs!$C$16*(Inputs!$C$9 + Inputs!$C$10*Inputs!$C$11 + Inputs!$C$12)*(1 + VLOOKUP(Inputs!$C$15,Lookups!$A$2:$B$20,2,TRUE)*(Scale!$B$9/IF(Scale!$B$8=0,1,Scale!$B$8)) + Inputs!$C$52)) | S24: =IF(A24=1,Scale!$B$13, W23) | T24: =J24*Inputs!$C$16*(Inputs!$C$19 + Inputs!$C$20*Inputs!$C$21 + 1/Inputs!$C$18) | U24: =MAX(0, (R24*(1+Inputs!$C$74)) - (S24 - T24)) | V24: =IF(A24<=Inputs!$C$73,0,INDEX(U:U,ROW()-Inputs!$C$73)) | W24: =S24 - T24 + V24 | X24: =V24*Inputs!$C$17 | Y24: =IF(A24>Inputs!$C$62,"",C24*AE24) | Z24: =IF(A24=1,Inputs!$C$72,AA23) | AA24: =Z24 + M24 - N24 - P24 - X24 - Y24 | AB24: =IF(AA24<0,1,0) | AC24: =IF(AD24=0,0,R24/(AD24*Inputs!$C$16)) | AD24: =IF(A24>Inputs!$C$62,"",B24+C24) | AE24: =IF(A24>Inputs!$C$62,"", Inputs!$C$65*(1+Inputs!$C$89*POWER(MIN(1,IF(Inputs!$C$88=0,0,B24/Inputs!$C$88)),Inputs!$C$90))) | AF24: =IF(A24>Inputs!$C$62,"",IF(A24=1,Inputs!$C$86,MIN(Inputs!$C$86,Inputs!$C$87*M23))) | AG24: =IF(A24>Inputs!$C$62,"",MIN(0.5,MAX(0, Inputs!$C$67*L24 + Inputs!$C$68*(1-K24) + Inputs!$C$69*Inputs!$C$10))) | AH24: =IF(A24>Inputs!$C$62,"",INDEX(CapacityPlan!$G$7:$G$266,A24)) | AI24: =IF(A24>Inputs!$C$62,"",INDEX(CapacityPlan!$J$7:$J$266,A24)) | AJ24: =IF(A24>Inputs!$C$62,"",IF(I24=0,"",G24/I24))
A25: 3 | B25: =IF(A25>Inputs!$C$62,"",IF(Inputs!$C$80=1,INDEX(Cohorts!$B$67:$B$326,A25),IF(A25=1,Inputs!$C$63,F24))) | C25: =IF(A25>Inputs!$C$62,"",IF(Inputs!$C$85=0,Inputs!$C$64,MIN(Inputs!$C$91,IF(AE25=0,0,AF25/AE25)))) | D25: =IF(A25>Inputs!$C$62,"",IF(Inputs!$C$80=1,INDEX(Cohorts!$G$67:$G$326,A25),MAX(0, Inputs!$C$66 + Inputs!$C$67*L25 + Inputs!$C$68*(1-K25) + Inputs!$C$69*Inputs!$C$10))) | E25: =IF(A25>Inputs!$C$62,"",IF(Inputs!$C$80=1,INDEX(Cohorts!$H$67:$H$326,A25),D25*AD25)) | F25: =IF(A25>Inputs!$C$62,"",IF(Inputs!$C$80=1,INDEX(Cohorts!$I$67:$I$326,A25),AD25-E25)) | G25: =IF(A25>Inputs!$C$62,"",AD25) | H25: =IF(A25>Inputs!$C$62,"",INDEX(CapacityPlan!$E$7:$E$266,A25)) | I25: =IF(A25>Inputs!$C$62,"",INDEX(CapacityPlan!$I$7:$I$266,A25)) | J25: =IF(A25>Inputs!$C$62,"",IF(G25>I25,I25,G25)) | K25: =IF(A25>Inputs!$C$62,"",IF(G25=0,1,J25/G25)) | L25: =IF((Inputs!$C$36 + UnitEconomics!$B$12*Inputs!$C$37 + Inputs!$C$10*Inputs!$C$38 + Inputs!$C$70*(1-K25))>1,1,(Inputs!$C$36 + UnitEconomics!$B$12*Inputs!$C$37 + Inputs!$C$10*Inputs!$C$38 + Inputs!$C$70*(1-K25))) | M25: =IF(A25>Inputs!$C$62,"",J25*Inputs!$C$7*(1-Inputs!$C$8)*(1-L25)) | N25: =IF(A25>Inputs!$C$62,"",J25*UnitEconomics!$B$32*AI25 + (G25-J25)*Inputs!$C$71) | O25: =M25-N25 | P25: =IF(A25>Inputs!$C$62,"",Inputs!$C$40 + H25*Inputs!$C$41) | Q25: =O25-P25 | R25: =IF(A25>Inputs!$C$62,"",AD25*Inputs!$C$16*(Inputs!$C$9 + Inputs!$C$10*Inputs!$C$11 + Inputs!$C$12)*(1 + VLOOKUP(Inputs!$C$15,Lookups!$A$2:$B$20,2,TRUE)*(Scale!$B$9/IF(Scale!$B$8=0,1,Scale!$B$8)) + Inputs!$C$52)) | S25: =IF(A25=1,Scale!$B$13, W24) | T25: =J25*Inputs!$C$16*(Inputs!$C$19 + Inputs!$C$20*Inputs!$C$21 + 1/Inputs!$C$18) | U25: =MAX(0, (R25*(1+Inputs!$C$74)) - (S25 - T25)) | V25: =IF(A25<=Inputs!$C$73,0,INDEX(U:U,ROW()-Inputs!$C$73)) | W25: =S25 - T25 + V25 | X25: =V25*Inputs!$C$17 | Y25: =IF(A25>Inputs!$C$62,"",C25*AE25) | Z25: =IF(A25=1,Inputs!$C$72,AA24) | AA25: =Z25 + M25 - N25 - P25 - X25 - Y25 | AB25: =IF(AA25<0,1,0) | AC25: =IF(AD25=0,0,R25/(AD25*Inputs!$C$16)) | AD25: =IF(A25>Inputs!$C$62,"",B25+C25) | AE25: =IF(A25>Inputs!$C$62,"", Inputs!$C$65*(1+Inputs!$C$89*POWER(MIN(1,IF(Inputs!$C$88=0,0,B25/Inputs!$C$88)),Inputs!$C$90))) | AF25: =IF(A25>Inputs!$C$62,"",IF(A25=1,Inputs!$C$86,MIN(Inputs!$C$86,Inputs!$C$87*M24))) | AG25: =IF(A25>Inputs!$C$62,"",MIN(0.5,MAX(0, Inputs!$C$67*L25 + Inputs!$C$68*(1-K25) + Inputs!$C$69*Inputs!$C$10))) | AH25: =IF(A25>Inputs!$C$62,"",INDEX(CapacityPlan!$G$7:$G$266,A25)) | AI25: =IF(A25>Inputs!$C$62,"",INDEX(CapacityPlan!$J$7:$J$266,A25)) | AJ25: =IF(A25>Inputs!$C$62,"",IF(I25=0,"",G25/I25))
A26: 4 | B26: =IF(A26>Inputs!$C$62,"",IF(Inputs!$C$80=1,INDEX(Cohorts!$B$67:$B$326,A26),IF(A26=1,Inputs!$C$63,F25))) | C26: =IF(A26>Inputs!$C$62,"",IF(Inputs!$C$85=0,Inputs!$C$64,MIN(Inputs!$C$91,IF(AE26=0,0,AF26/AE26)))) | D26: =IF(A26>Inputs!$C$62,"",IF(Inputs!$C$80=1,INDEX(Cohorts!$G$67:$G$326,A26),MAX(0, Inputs!$C$66 + Inputs!$C$67*L26 + Inputs!$C$68*(1-K26) + Inputs!$C$69*Inputs!$C$10))) | E26: =IF(A26>Inputs!$C$62,"",IF(Inputs!$C$80=1,INDEX(Cohorts!$H$67:$H$326,A26),D26*AD26)) | F26: =IF(A26>Inputs!$C$62,"",IF(Inputs!$C$80=1,INDEX(Cohorts!$I$67:$I$326,A26),AD26-E26)) | G26: =IF(A26>Inputs!$C$62,"",AD26) | H26: =IF(A26>Inputs!$C$62,"",INDEX(CapacityPlan!$E$7:$E$266,A26)) | I26: =IF(A26>Inputs!$C$62,"",INDEX(CapacityPlan!$I$7:$I$266,A26)) | J26: =IF(A26>Inputs!$C$62,"",IF(G26>I26,I26,G26)) | K26: =IF(A26>Inputs!$C$62,"",IF(G26=0,1,J26/G26)) | L26: =IF((Inputs!$C$36 + UnitEconomics!$B$12*Inputs!$C$37 + Inputs!$C$10*Inputs!$C$38 + Inputs!$C$70*(1-K26))>1,1,(Inputs!$C$36 + UnitEconomics!$B$12*Inputs!$C$37 + Inputs!$C$10*Inputs!$C$38 + Inputs!$C$70*(1-K26))) | M26: =IF(A26>Inputs!$C$62,"",J26*Inputs!$C$7*(1-Inputs!$C$8)*(1-L26)) | N26: =IF(A26>Inputs!$C$62,"",J26*UnitEconomics!$B$32*AI26 + (G26-J26)*Inputs!$C$71) | O26: =M26-N26 | P26: =IF(A26>Inputs!$C$62,"",Inputs!$C$40 + H26*Inputs!$C$41) | Q26: =O26-P26 | R26: =IF(A26>Inputs!$C$62,"",AD26*Inputs!$C$16*(Inputs!$C$9 + Inputs!$C$10*Inputs!$C$11 + Inputs!$C$12)*(1 + VLOOKUP(Inputs!$C$15,Lookups!$A$2:$B$20,2,TRUE)*(Scale!$B$9/IF(Scale!$B$8=0,1,Scale!$B$8)) + Inputs!$C$52)) | S26: =IF(A26=1,Scale!$B$13, W25) | T26: =J26*Inputs!$C$16*(Inputs!$C$19 + Inputs!$C$20*Inputs!$C$21 + 1/Inputs!$C$18) | U26: =MAX(0, (R26*(1+Inputs!$C$74)) - (S26 - T26)) | V26: =IF(A26<=Inputs!$C$73,0,INDEX(U:U,ROW()-Inputs!$C$73)) | W26: =S26 - T26 + V26 | X26: =V26*Inputs!$C$17 | Y26: =IF(A26>Inputs!$C$62,"",C26*AE26) | Z26: =IF(A26=1,Inputs!$C$72,AA25) | AA26: =Z26 + M26 - N26 - P26 - X26 - Y26 | AB26: =IF(AA26<0,1,0) | AC26: =IF(AD26=0,0,R26/(AD26*Inputs!$C$16)) | AD26: =IF(A26>Inputs!$C$62,"",B26+C26) | AE26: =IF(A26>Inputs!$C$62,"", Inputs!$C$65*(1+Inputs!$C$89*POWER(MIN(1,IF(Inputs!$C$88=0,0,B26/Inputs!$C$88)),Inputs!$C$90))) | AF26: =IF(A26>Inputs!$C$62,"",IF(A26=1,Inputs!$C$86,MIN(Inputs!$C$86,Inputs!$C$87*M25))) | AG26: =IF(A26>Inputs!$C$62,"",MIN(0.5,MAX(0, Inputs!$C$67*L26 + Inputs!$C$68*(1-K26) + Inputs!$C$69*Inputs!$C$10))) | AH26: =IF(A26>Inputs!$C$62,"",INDEX(CapacityPlan!$G$7:$G$266,A26)) | AI26: =IF(A26>Inputs!$C$62,"",INDEX(CapacityPlan!$J$7:$J$266,A26)) | AJ26: =IF(A26>Inputs!$C$62,"",IF(I26=0,"",G26/I26))
A27: 5 | B27: =IF(A27>Inputs!$C$62,"",IF(Inputs!$C$80=1,INDEX(Cohorts!$B$67:$B$326,A27),IF(A27=1,Inputs!$C$63,F26))) | C27: =IF(A27>Inputs!$C$62,"",IF(Inputs!$C$85=0,Inputs!$C$64,MIN(Inputs!$C$91,IF(AE27=0,0,AF27/AE27)))) | D27: =IF(A27>Inputs!$C$62,"",IF(Inputs!$C$80=1,INDEX(Cohorts!$G$67:$G$326,A27),MAX(0, Inputs!$C$66 + Inputs!$C$67*L27 + Inputs!$C$68*(1-K27) + Inputs!$C$69*Inputs!$C$10))) | E27: =IF(A27>Inputs!$C$62,"",IF(Inputs!$C$80=1,INDEX(Cohorts!$H$67:$H$326,A27),D27*AD27)) | F27: =IF(A27>Inputs!$C$62,"",IF(Inputs!$C$80=1,INDEX(Cohorts!$I$67:$I$326,A27),AD27-E27)) | G27: =IF(A27>Inputs!$C$62,"",AD27) | H27: =IF(A27>Inputs!$C$62,"",INDEX(CapacityPlan!$E$7:$E$266,A27)) | I27: =IF(A27>Inputs!$C$62,"",INDEX(CapacityPlan!$I$7:$I$266,A27)) | J27: =IF(A27>Inputs!$C$62,"",IF(G27>I27,I27,G27)) | K27: =IF(A27>Inputs!$C$62,"",IF(G27=0,1,J27/G27)) | L27: =IF((Inputs!$C$36 + UnitEconomics!$B$12*Inputs!$C$37 + Inputs!$C$10*Inputs!$C$38 + Inputs!$C$70*(1-K27))>1,1,(Inputs!$C$36 + UnitEconomics!$B$12*Inputs!$C$37 + Inputs!$C$10*Inputs!$C$38 + Inputs!$C$70*(1-K27))) | M27: =IF(A27>Inputs!$C$62,"",J27*Inputs!$C$7*(1-Inputs!$C$8)*(1-L27)) | N27: =IF(A27>Inputs!$C$62,"",J27*UnitEconomics!$B$32*AI27 + (G27-J27)*Inputs!$C$71) | O27: =M27-N27 | P27: =IF(A27>Inputs!$C$62,"",Inputs!$C$40 + H27*Inputs!$C$41) | Q27: =O27-P27 | R27: =IF(A27>Inputs!$C$62,"",AD27*Inputs!$C$16*(Inputs!$C$9 + Inputs!$C$10*Inputs!$C$11 + Inputs!$C$12)*(1 + VLOOKUP(Inputs!$C$15,Lookups!$A$2:$B$20,2,TRUE)*(Scale!$B$9/IF(Scale!$B$8=0,1,Scale!$B$8)) + Inputs!$C$52)) | S27: =IF(A27=1,Scale!$B$13, W26) | T27: =J27*Inputs!$C$16*(Inputs!$C$19 + Inputs!$C$20*Inputs!$C$21 + 1/Inputs!$C$18) | U27: =MAX(0, (R27*(1+Inputs!$C$74)) - (S27 - T27)) | V27: =IF(A27<=Inputs!$C$73,0,INDEX(U:U,ROW()-Inputs!$C$73)) | W27: =S27 - T27 + V27 | X27: =V27*Inputs!$C$17 | Y27: =IF(A27>Inputs!$C$62,"",C27*AE27) | Z27: =IF(A27=1,Inputs!$C$72,AA26) | AA27: =Z27 + M27 - N27 - P27 - X27 - Y27 | AB27: =IF(AA27<0,1,0) | AC27: =IF(AD27=0,0,R27/(AD27*Inputs!$C$16)) | AD27: =IF(A27>Inputs!$C$62,"",B27+C27) | AE27: =IF(A27>Inputs!$C$62,"", Inputs!$C$65*(1+Inputs!$C$89*POWER(MIN(1,IF(Inputs!$C$88=0,0,B27/Inputs!$C$88)),Inputs!$C$90))) | AF27: =IF(A27>Inputs!$C$62,"",IF(A27=1,Inputs!$C$86,MIN(Inputs!$C$86,Inputs!$C$87*M26))) | AG27: =IF(A27>Inputs!$C$62,"",MIN(0.5,MAX(0, Inputs!$C$67*L27 + Inputs!$C$68*(1-K27) + Inputs!$C$69*Inputs!$C$10))) | AH27: =IF(A27>Inputs!$C$62,"",INDEX(CapacityPlan!$G$7:$G$266,A27)) | AI27: =IF(A27>Inputs!$C$62,"",INDEX(CapacityPlan!$J$7:$J$266,A27)) | AJ27: =IF(A27>Inputs!$C$62,"",IF(I27=0,"",G27/I27))
A28: 6 | B28: =IF(A28>Inputs!$C$62,"",IF(Inputs!$C$80=1,INDEX(Cohorts!$B$67:$B$326,A28),IF(A28=1,Inputs!$C$63,F27))) | C28: =IF(A28>Inputs!$C$62,"",IF(Inputs!$C$85=0,Inputs!$C$64,MIN(Inputs!$C$91,IF(AE28=0,0,AF28/AE28)))) | D28: =IF(A28>Inputs!$C$62,"",IF(Inputs!$C$80=1,INDEX(Cohorts!$G$67:$G$326,A28),MAX(0, Inputs!$C$66 + Inputs!$C$67*L28 + Inputs!$C$68*(1-K28) + Inputs!$C$69*Inputs!$C$10))) | E28: =IF(A28>Inputs!$C$62,"",IF(Inputs!$C$80=1,INDEX(Cohorts!$H$67:$H$326,A28),D28*AD28)) | F28: =IF(A28>Inputs!$C$62,"",IF(Inputs!$C$80=1,INDEX(Cohorts!$I$67:$I$326,A28),AD28-E28)) | G28: =IF(A28>Inputs!$C$62,"",AD28) | H28: =IF(A28>Inputs!$C$62,"",INDEX(CapacityPlan!$E$7:$E$266,A28)) | I28: =IF(A28>Inputs!$C$62,"",INDEX(CapacityPlan!$I$7:$I$266,A28)) | J28: =IF(A28>Inputs!$C$62,"",IF(G28>I28,I28,G28)) | K28: =IF(A28>Inputs!$C$62,"",IF(G28=0,1,J28/G28)) | L28: =IF((Inputs!$C$36 + UnitEconomics!$B$12*Inputs!$C$37 + Inputs!$C$10*Inputs!$C$38 + Inputs!$C$70*(1-K28))>1,1,(Inputs!$C$36 + UnitEconomics!$B$12*Inputs!$C$37 + Inputs!$C$10*Inputs!$C$38 + Inputs!$C$70*(1-K28))) | M28: =IF(A28>Inputs!$C$62,"",J28*Inputs!$C$7*(1-Inputs!$C$8)*(1-L28)) | N28: =IF(A28>Inputs!$C$62,"",J28*UnitEconomics!$B$32*AI28 + (G28-J28)*Inputs!$C$71) | O28: =M28-N28 | P28: =IF(A28>Inputs!$C$62,"",Inputs!$C$40 + H28*Inputs!$C$41) | Q28: =O28-P28 | R28: =IF(A28>Inputs!$C$62,"",AD28*Inputs!$C$16*(Inputs!$C$9 + Inputs!$C$10*Inputs!$C$11 + Inputs!$C$12)*(1 + VLOOKUP(Inputs!$C$15,Lookups!$A$2:$B$20,2,TRUE)*(Scale!$B$9/IF(Scale!$B$8=0,1,Scale!$B$8)) + Inputs!$C$52)) | S28: =IF(A28=1,Scale!$B$13, W27) | T28: =J28*Inputs!$C$16*(Inputs!$C$19 + Inputs!$C$20*Inputs!$C$21 + 1/Inputs!$C$18) | U28: =MAX(0, (R28*(1+Inputs!$C$74)) - (S28 - T28)) | V28: =IF(A28<=Inputs!$C$73,0,INDEX(U:U,ROW()-Inputs!$C$73)) | W28: =S28 - T28 + V28 | X28: =V28*Inputs!$C$17 | Y28: =IF(A28>Inputs!$C$62,"",C28*AE28) | Z28: =IF(A28=1,Inputs!$C$72,AA27) | AA28: =Z28 + M28 - N28 - P28 - X28 - Y28 | AB28: =IF(AA28<0,1,0) | AC28: =IF(AD28=0,0,R28/(AD28*Inputs!$C$16)) | AD28: =IF(A28>Inputs!$C$62,"",B28+C28) | AE28: =IF(A28>Inputs!$C$62,"", Inputs!$C$65*(1+Inputs!$C$89*POWER(MIN(1,IF(Inputs!$C$88=0,0,B28/Inputs!$C$88)),Inputs!$C$90))) | AF28: =IF(A28>Inputs!$C$62,"",IF(A28=1,Inputs!$C$86,MIN(Inputs!$C$86,Inputs!$C$87*M27))) | AG28: =IF(A28>Inputs!$C$62,"",MIN(0.5,MAX(0, Inputs!$C$67*L28 + Inputs!$C$68*(1-K28) + Inputs!$C$69*Inputs!$C$10))) | AH28: =IF(A28>Inputs!$C$62,"",INDEX(CapacityPlan!$G$7:$G$266,A28)) | AI28: =IF(A28>Inputs!$C$62,"",INDEX(CapacityPlan!$J$7:$J$266,A28)) | AJ28: =IF(A28>Inputs!$C$62,"",IF(I28=0,"",G28/I28))
A29: 7 | B29: =IF(A29>Inputs!$C$62,"",IF(Inputs!$C$80=1,INDEX(Cohorts!$B$67:$B$326,A29),IF(A29=1,Inputs!$C$63,F28))) | C29: =IF(A29>Inputs!$C$62,"",IF(Inputs!$C$85=0,Inputs!$C$64,MIN(Inputs!$C$91,IF(AE29=0,0,AF29/AE29)))) | D29: =IF(A29>Inputs!$C$62,"",IF(Inputs!$C$80=1,INDEX(Cohorts!$G$67:$G$326,A29),MAX(0, Inputs!$C$66 + Inputs!$C$67*L29 + Inputs!$C$68*(1-K29) + Inputs!$C$69*Inputs!$C$10))) | E29: =IF(A29>Inputs!$C$62,"",IF(Inputs!$C$80=1,INDEX(Cohorts!$H$67:$H$326,A29),D29*AD29)) | F29: =IF(A29>Inputs!$C$62,"",IF(Inputs!$C$80=1,INDEX(Cohorts!$I$67:$I$326,A29),AD29-E29)) | G29: =IF(A29>Inputs!$C$62,"",AD29) | H29: =IF(A29>Inputs!$C$62,"",INDEX(CapacityPlan!$E$7:$E$266,A29)) | I29: =IF(A29>Inputs!$C$62,"",INDEX(CapacityPlan!$I$7:$I$266,A29)) | J29: =IF(A29>Inputs!$C$62,"",IF(G29>I29,I29,G29)) | K29: =IF(A29>Inputs!$C$62,"",IF(G29=0,1,J29/G29)) | L29: =IF((Inputs!$C$36 + UnitEconomics!$B$12*Inputs!$C$37 + Inputs!$C$10*Inputs!$C$38 + Inputs!$C$70*(1-K29))>1,1,(Inputs!$C$36 + UnitEconomics!$B$12*Inputs!$C$37 + Inputs!$C$10*Inputs!$C$38 + Inputs!$C$70*(1-K29))) | M29: =IF(A29>Inputs!$C$62,"",J29*Inputs!$C$7*(1-Inputs!$C$8)*(1-L29)) | N29: =IF(A29>Inputs!$C$62,"",J29*UnitEconomics!$B$32*AI29 + (G29-J29)*Inputs!$C$71) | O29: =M29-N29 | P29: =IF(A29>Inputs!$C$62,"",Inputs!$C$40 + H29*Inputs!$C$41) | Q29: =O29-P29 | R29: =IF(A29>Inputs!$C$62,"",AD29*Inputs!$C$16*(Inputs!$C$9 + Inputs!$C$10*Inputs!$C$11 + Inputs!$C$12)*(1 + VLOOKUP(Inputs!$C$15,Lookups!$A$2:$B$20,2,TRUE)*(Scale!$B$9/IF(Scale!$B$8=0,1,Scale!$B$8)) + Inputs!$C$52)) | S29: =IF(A29=1,Scale!$B$13, W28) | T29: =J29*Inputs!$C$16*(Inputs!$C$19 + Inputs!$C$20*Inputs!$C$21 + 1/Inputs!$C$18) | U29: =MAX(0, (R29*(1+Inputs!$C$74)) - (S29 - T29)) | V29: =IF(A29<=Inputs!$C$73,0,INDEX(U:U,ROW()-Inputs!$C$73)) | W29: =S29 - T29 + V29 | X29: =V29*Inputs!$C$17 | Y29: =IF(A29>Inputs!$C$62,"",C29*AE29) | Z29: =IF(A29=1,Inputs!$C$72,AA28) | AA29: =Z29 + M29 - N29 - P29 - X29 - Y29 | AB29: =IF(AA29<0,1,0) | AC29: =IF(AD29=0,0,R29/(AD29*Inputs!$C$16)) | AD29: =IF(A29>Inputs!$C$62,"",B29+C29) | AE29: =IF(A29>Inputs!$C$62,"", Inputs!$C$65*(1+Inputs!$C$89*POWER(MIN(1,IF(Inputs!$C$88=0,0,B29/Inputs!$C$88)),Inputs!$C$90))) | AF29: =IF(A29>Inputs!$C$62,"",IF(A29=1,Inputs!$C$86,MIN(Inputs!$C$86,Inputs!$C$87*M28))) | AG29: =IF(A29>Inputs!$C$62,"",MIN(0.5,MAX(0, Inputs!$C$67*L29 + Inputs!$C$68*(1-K29) + Inputs!$C$69*Inputs!$C$10))) | AH29: =IF(A29>Inputs!$C$62,"",INDEX(CapacityPlan!$G$7:$G$266,A29)) | AI29: =IF(A29>Inputs!$C$62,"",INDEX(CapacityPlan!$J$7:$J$266,A29)) | AJ29: =IF(A29>Inputs!$C$62,"",IF(I29=0,"",G29/I29))
A30: 8 | B30: =IF(A30>Inputs!$C$62,"",IF(Inputs!$C$80=1,INDEX(Cohorts!$B$67:$B$326,A30),IF(A30=1,Inputs!$C$63,F29))) | C30: =IF(A30>Inputs!$C$62,"",IF(Inputs!$C$85=0,Inputs!$C$64,MIN(Inputs!$C$91,IF(AE30=0,0,AF30/AE30)))) | D30: =IF(A30>Inputs!$C$62,"",IF(Inputs!$C$80=1,INDEX(Cohorts!$G$67:$G$326,A30),MAX(0, Inputs!$C$66 + Inputs!$C$67*L30 + Inputs!$C$68*(1-K30) + Inputs!$C$69*Inputs!$C$10))) | E30: =IF(A30>Inputs!$C$62,"",IF(Inputs!$C$80=1,INDEX(Cohorts!$H$67:$H$326,A30),D30*AD30)) | F30: =IF(A30>Inputs!$C$62,"",IF(Inputs!$C$80=1,INDEX(Cohorts!$I$67:$I$326,A30),AD30-E30)) | G30: =IF(A30>Inputs!$C$62,"",AD30) | H30: =IF(A30>Inputs!$C$62,"",INDEX(CapacityPlan!$E$7:$E$266,A30)) | I30: =IF(A30>Inputs!$C$62,"",INDEX(CapacityPlan!$I$7:$I$266,A30)) | J30: =IF(A30>Inputs!$C$62,"",IF(G30>I30,I30,G30)) | K30: =IF(A30>Inputs!$C$62,"",IF(G30=0,1,J30/G30)) | L30: =IF((Inputs!$C$36 + UnitEconomics!$B$12*Inputs!$C$37 + Inputs!$C$10*Inputs!$C$38 + Inputs!$C$70*(1-K30))>1,1,(Inputs!$C$36 + UnitEconomics!$B$12*Inputs!$C$37 + Inputs!$C$10*Inputs!$C$38 + Inputs!$C$70*(1-K30))) | M30: =IF(A30>Inputs!$C$62,"",J30*Inputs!$C$7*(1-Inputs!$C$8)*(1-L30)) | N30: =IF(A30>Inputs!$C$62,"",J30*UnitEconomics!$B$32*AI30 + (G30-J30)*Inputs!$C$71) | O30: =M30-N30 | P30: =IF(A30>Inputs!$C$62,"",Inputs!$C$40 + H30*Inputs!$C$41) | Q30: =O30-P30 | R30: =IF(A30>Inputs!$C$62,"",AD30*Inputs!$C$16*(Inputs!$C$9 + Inputs!$C$10*Inputs!$C$11 + Inputs!$C$12)*(1 + VLOOKUP(Inputs!$C$15,Lookups!$A$2:$B$20,2,TRUE)*(Scale!$B$9/IF(Scale!$B$8=0,1,Scale!$B$8)) + Inputs!$C$52)) | S30: =IF(A30=1,Scale!$B$13, W29) | T30: =J30*Inputs!$C$16*(Inputs!$C$19 + Inputs!$C$20*Inputs!$C$21 + 1/Inputs!$C$18) | U30: =MAX(0, (R30*(1+Inputs!$C$74)) - (S30 - T30)) | V30: =IF(A30<=Inputs!$C$73,0,INDEX(U:U,ROW()-Inputs!$C$73)) | W30: =S30 - T30 + V30 | X30: =V30*Inputs!$C$17 | Y30: =IF(A30>Inputs!$C$62,"",C30*AE30) | Z30: =IF(A30=1,Inputs!$C$72,AA29) | AA30: =Z30 + M30 - N30 - P30 - X30 - Y30 | AB30: =IF(AA30<0,1,0) | AC30: =IF(AD30=0,0,R30/(AD30*Inputs!$C$16)) | AD30: =IF(A30>Inputs!$C$62,"",B30+C30) | AE30: =IF(A30>Inputs!$C$62,"", Inputs!$C$65*(1+Inputs!$C$89*POWER(MIN(1,IF(Inputs!$C$88=0,0,B30/Inputs!$C$88)),Inputs!$C$90))) | AF30: =IF(A30>Inputs!$C$62,"",IF(A30=1,Inputs!$C$86,MIN(Inputs!$C$86,Inputs!$C$87*M29))) | AG30: =IF(A30>Inputs!$C$62,"",MIN(0.5,MAX(0, Inputs!$C$67*L30 + Inputs!$C$68*(1-K30) + Inputs!$C$69*Inputs!$C$10))) | AH30: =IF(A30>Inputs!$C$62,"",INDEX(CapacityPlan!$G$7:$G$266,A30)) | AI30: =IF(A30>Inputs!$C$62,"",INDEX(CapacityPlan!$J$7:$J$266,A30)) | AJ30: =IF(A30>Inputs!$C$62,"",IF(I30=0,"",G30/I30))
A31: 9 | B31: =IF(A31>Inputs!$C$62,"",IF(Inputs!$C$80=1,INDEX(Cohorts!$B$67:$B$326,A31),IF(A31=1,Inputs!$C$63,F30))) | C31: =IF(A31>Inputs!$C$62,"",IF(Inputs!$C$85=0,Inputs!$C$64,MIN(Inputs!$C$91,IF(AE31=0,0,AF31/AE31)))) | D31: =IF(A31>Inputs!$C$62,"",IF(Inputs!$C$80=1,INDEX(Cohorts!$G$67:$G$326,A31),MAX(0, Inputs!$C$66 + Inputs!$C$67*L31 + Inputs!$C$68*(1-K31) + Inputs!$C$69*Inputs!$C$10))) | E31: =IF(A31>Inputs!$C$62,"",IF(Inputs!$C$80=1,INDEX(Cohorts!$H$67:$H$326,A31),D31*AD31)) | F31: =IF(A31>Inputs!$C$62,"",IF(Inputs!$C$80=1,INDEX(Cohorts!$I$67:$I$326,A31),AD31-E31)) | G31: =IF(A31>Inputs!$C$62,"",AD31) | H31: =IF(A31>Inputs!$C$62,"",INDEX(CapacityPlan!$E$7:$E$266,A31)) | I31: =IF(A31>Inputs!$C$62,"",INDEX(CapacityPlan!$I$7:$I$266,A31)) | J31: =IF(A31>Inputs!$C$62,"",IF(G31>I31,I31,G31)) | K31: =IF(A31>Inputs!$C$62,"",IF(G31=0,1,J31/G31)) | L31: =IF((Inputs!$C$36 + UnitEconomics!$B$12*Inputs!$C$37 + Inputs!$C$10*Inputs!$C$38 + Inputs!$C$70*(1-K31))>1,1,(Inputs!$C$36 + UnitEconomics!$B$12*Inputs!$C$37 + Inputs!$C$10*Inputs!$C$38 + Inputs!$C$70*(1-K31))) | M31: =IF(A31>Inputs!$C$62,"",J31*Inputs!$C$7*(1-Inputs!$C$8)*(1-L31)) | N31: =IF(A31>Inputs!$C$62,"",J31*UnitEconomics!$B$32*AI31 + (G31-J31)*Inputs!$C$71) | O31: =M31-N31 | P31: =IF(A31>Inputs!$C$62,"",Inputs!$C$40 + H31*Inputs!$C$41) | Q31: =O31-P31 | R31: =IF(A31>Inputs!$C$62,"",AD31*Inputs!$C$16*(Inputs!$C$9 + Inputs!$C$10*Inputs!$C$11 + Inputs!$C$12)*(1 + VLOOKUP(Inputs!$C$15,Lookups!$A$2:$B$20,2,TRUE)*(Scale!$B$9/IF(Scale!$B$8=0,1,Scale!$B$8)) + Inputs!$C$52)) | S31: =IF(A31=1,Scale!$B$13, W30) | T31: =J31*Inputs!$C$16*(Inputs!$C$19 + Inputs!$C$20*Inputs!$C$21 + 1/Inputs!$C$18) | U31: =MAX(0, (R31*(1+Inputs!$C$74)) - (S31 - T31)) | V31: =IF(A31<=Inputs!$C$73,0,INDEX(U:U,ROW()-Inputs!$C$73)) | W31: =S31 - T31 + V31 | X31: =V31*Inputs!$C$17 | Y31: =IF(A31>Inputs!$C$62,"",C31*AE31) | Z31: =IF(A31=1,Inputs!$C$72,AA30) | AA31: =Z31 + M31 - N31 - P31 - X31 - Y31 | AB31: =IF(AA31<0,1,0) | AC31: =IF(AD31=0,0,R31/(AD31*Inputs!$C$16)) | AD31: =IF(A31>Inputs!$C$62,"",B31+C31) | AE31: =IF(A31>Inputs!$C$62,"", Inputs!$C$65*(1+Inputs!$C$89*POWER(MIN(1,IF(Inputs!$C$88=0,0,B31/Inputs!$C$88)),Inputs!$C$90))) | AF31: =IF(A31>Inputs!$C$62,"",IF(A31=1,Inputs!$C$86,MIN(Inputs!$C$86,Inputs!$C$87*M30))) | AG31: =IF(A31>Inputs!$C$62,"",MIN(0.5,MAX(0, Inputs!$C$67*L31 + Inputs!$C$68*(1-K31) + Inputs!$C$69*Inputs!$C$10))) | AH31: =IF(A31>Inputs!$C$62,"",INDEX(CapacityPlan!$G$7:$G$266,A31)) | AI31: =IF(A31>Inputs!$C$62,"",INDEX(CapacityPlan!$J$7:$J$266,A31)) | AJ31: =IF(A31>Inputs!$C$62,"",IF(I31=0,"",G31/I31))
A32: 10 | B32: =IF(A32>Inputs!$C$62,"",IF(Inputs!$C$80=1,INDEX(Cohorts!$B$67:$B$326,A32),IF(A32=1,Inputs!$C$63,F31))) | C32: =IF(A32>Inputs!$C$62,"",IF(Inputs!$C$85=0,Inputs!$C$64,MIN(Inputs!$C$91,IF(AE32=0,0,AF32/AE32)))) | D32: =IF(A32>Inputs!$C$62,"",IF(Inputs!$C$80=1,INDEX(Cohorts!$G$67:$G$326,A32),MAX(0, Inputs!$C$66 + Inputs!$C$67*L32 + Inputs!$C$68*(1-K32) + Inputs!$C$69*Inputs!$C$10))) | E32: =IF(A32>Inputs!$C$62,"",IF(Inputs!$C$80=1,INDEX(Cohorts!$H$67:$H$326,A32),D32*AD32)) | F32: =IF(A32>Inputs!$C$62,"",IF(Inputs!$C$80=1,INDEX(Cohorts!$I$67:$I$326,A32),AD32-E32)) | G32: =IF(A32>Inputs!$C$62,"",AD32) | H32: =IF(A32>Inputs!$C$62,"",INDEX(CapacityPlan!$E$7:$E$266,A32)) | I32: =IF(A32>Inputs!$C$62,"",INDEX(CapacityPlan!$I$7:$I$266,A32)) | J32: =IF(A32>Inputs!$C$62,"",IF(G32>I32,I32,G32)) | K32: =IF(A32>Inputs!$C$62,"",IF(G32=0,1,J32/G32)) | L32: =IF((Inputs!$C$36 + UnitEconomics!$B$12*Inputs!$C$37 + Inputs!$C$10*Inputs!$C$38 + Inputs!$C$70*(1-K32))>1,1,(Inputs!$C$36 + UnitEconomics!$B$12*Inputs!$C$37 + Inputs!$C$10*Inputs!$C$38 + Inputs!$C$70*(1-K32))) | M32: =IF(A32>Inputs!$C$62,"",J32*Inputs!$C$7*(1-Inputs!$C$8)*(1-L32)) | N32: =IF(A32>Inputs!$C$62,"",J32*UnitEconomics!$B$32*AI32 + (G32-J32)*Inputs!$C$71) | O32: =M32-N32 | P32: =IF(A32>Inputs!$C$62,"",Inputs!$C$40 + H32*Inputs!$C$41) | Q32: =O32-P32 | R32: =IF(A32>Inputs!$C$62,"",AD32*Inputs!$C$16*(Inputs!$C$9 + Inputs!$C$10*Inputs!$C$11 + Inputs!$C$12)*(1 + VLOOKUP(Inputs!$C$15,Lookups!$A$2:$B$20,2,TRUE)*(Scale!$B$9/IF(Scale!$B$8=0,1,Scale!$B$8)) + Inputs!$C$52)) | S32: =IF(A32=1,Scale!$B$13, W31) | T32: =J32*Inputs!$C$16*(Inputs!$C$19 + Inputs!$C$20*Inputs!$C$21 + 1/Inputs!$C$18) | U32: =MAX(0, (R32*(1+Inputs!$C$74)) - (S32 - T32)) | V32: =IF(A32<=Inputs!$C$73,0,INDEX(U:U,ROW()-Inputs!$C$73)) | W32: =S32 - T32 + V32 | X32: =V32*Inputs!$C$17 | Y32: =IF(A32>Inputs!$C$62,"",C32*AE32) | Z32: =IF(A32=1,Inputs!$C$72,AA31) | AA32: =Z32 + M32 - N32 - P32 - X32 - Y32 | AB32: =IF(AA32<0,1,0) | AC32: =IF(AD32=0,0,R32/(AD32*Inputs!$C$16)) | AD32: =IF(A32>Inputs!$C$62,"",B32+C32) | AE32: =IF(A32>Inputs!$C$62,"", Inputs!$C$65*(1+Inputs!$C$89*POWER(MIN(1,IF(Inputs!$C$88=0,0,B32/Inputs!$C$88)),Inputs!$C$90))) | AF32: =IF(A32>Inputs!$C$62,"",IF(A32=1,Inputs!$C$86,MIN(Inputs!$C$86,Inputs!$C$87*M31))) | AG32: =IF(A32>Inputs!$C$62,"",MIN(0.5,MAX(0, Inputs!$C$67*L32 + Inputs!$C$68*(1-K32) + Inputs!$C$69*Inputs!$C$10))) | AH32: =IF(A32>Inputs!$C$62,"",INDEX(CapacityPlan!$G$7:$G$266,A32)) | AI32: =IF(A32>Inputs!$C$62,"",INDEX(CapacityPlan!$J$7:$J$266,A32)) | AJ32: =IF(A32>Inputs!$C$62,"",IF(I32=0,"",G32/I32))
A33: 11 | B33: =IF(A33>Inputs!$C$62,"",IF(Inputs!$C$80=1,INDEX(Cohorts!$B$67:$B$326,A33),IF(A33=1,Inputs!$C$63,F32))) | C33: =IF(A33>Inputs!$C$62,"",IF(Inputs!$C$85=0,Inputs!$C$64,MIN(Inputs!$C$91,IF(AE33=0,0,AF33/AE33)))) | D33: =IF(A33>Inputs!$C$62,"",IF(Inputs!$C$80=1,INDEX(Cohorts!$G$67:$G$326,A33),MAX(0, Inputs!$C$66 + Inputs!$C$67*L33 + Inputs!$C$68*(1-K33) + Inputs!$C$69*Inputs!$C$10))) | E33: =IF(A33>Inputs!$C$62,"",IF(Inputs!$C$80=1,INDEX(Cohorts!$H$67:$H$326,A33),D33*AD33)) | F33: =IF(A33>Inputs!$C$62,"",IF(Inputs!$C$80=1,INDEX(Cohorts!$I$67:$I$326,A33),AD33-E33)) | G33: =IF(A33>Inputs!$C$62,"",AD33) | H33: =IF(A33>Inputs!$C$62,"",INDEX(CapacityPlan!$E$7:$E$266,A33)) | I33: =IF(A33>Inputs!$C$62,"",INDEX(CapacityPlan!$I$7:$I$266,A33)) | J33: =IF(A33>Inputs!$C$62,"",IF(G33>I33,I33,G33)) | K33: =IF(A33>Inputs!$C$62,"",IF(G33=0,1,J33/G33)) | L33: =IF((Inputs!$C$36 + UnitEconomics!$B$12*Inputs!$C$37 + Inputs!$C$10*Inputs!$C$38 + Inputs!$C$70*(1-K33))>1,1,(Inputs!$C$36 + UnitEconomics!$B$12*Inputs!$C$37 + Inputs!$C$10*Inputs!$C$38 + Inputs!$C$70*(1-K33))) | M33: =IF(A33>Inputs!$C$62,"",J33*Inputs!$C$7*(1-Inputs!$C$8)*(1-L33)) | N33: =IF(A33>Inputs!$C$62,"",J33*UnitEconomics!$B$32*AI33 + (G33-J33)*Inputs!$C$71) | O33: =M33-N33 | P33: =IF(A33>Inputs!$C$62,"",Inputs!$C$40 + H33*Inputs!$C$41) | Q33: =O33-P33 | R33: =IF(A33>Inputs!$C$62,"",AD33*Inputs!$C$16*(Inputs!$C$9 + Inputs!$C$10*Inputs!$C$11 + Inputs!$C$12)*(1 + VLOOKUP(Inputs!$C$15,Lookups!$A$2:$B$20,2,TRUE)*(Scale!$B$9/IF(Scale!$B$8=0,1,Scale!$B$8)) + Inputs!$C$52)) | S33: =IF(A33=1,Scale!$B$13, W32) | T33: =J33*Inputs!$C$16*(Inputs!$C$19 + Inputs!$C$20*Inputs!$C$21 + 1/Inputs!$C$18) | U33: =MAX(0, (R33*(1+Inputs!$C$74)) - (S33 - T33)) | V33: =IF(A33<=Inputs!$C$73,0,INDEX(U:U,ROW()-Inputs!$C$73)) | W33: =S33 - T33 + V33 | X33: =V33*Inputs!$C$17 | Y33: =IF(A33>Inputs!$C$62,"",C33*AE33) | Z33: =IF(A33=1,Inputs!$C$72,AA32) | AA33: =Z33 + M33 - N33 - P33 - X33 - Y33 | AB33: =IF(AA33<0,1,0) | AC33: =IF(AD33=0,0,R33/(AD33*Inputs!$C$16)) | AD33: =IF(A33>Inputs!$C$62,"",B33+C33) | AE33: =IF(A33>Inputs!$C$62,"", Inputs!$C$65*(1+Inputs!$C$89*POWER(MIN(1,IF(Inputs!$C$88=0,0,B33/Inputs!$C$88)),Inputs!$C$90))) | AF33: =IF(A33>Inputs!$C$62,"",IF(A33=1,Inputs!$C$86,MIN(Inputs!$C$86,Inputs!$C$87*M32))) | AG33: =IF(A33>Inputs!$C$62,"",MIN(0.5,MAX(0, Inputs!$C$67*L33 + Inputs!$C$68*(1-K33) + Inputs!$C$69*Inputs!$C$10))) | AH33: =IF(A33>Inputs!$C$62,"",INDEX(CapacityPlan!$G$7:$G$266,A33)) | AI33: =IF(A33>Inputs!$C$62,"",INDEX(CapacityPlan!$J$7:$J$266,A33)) | AJ33: =IF(A33>Inputs!$C$62,"",IF(I33=0,"",G33/I33))
A34: 12 | B34: =IF(A34>Inputs!$C$62,"",IF(Inputs!$C$80=1,INDEX(Cohorts!$B$67:$B$326,A34),IF(A34=1,Inputs!$C$63,F33))) | C34: =IF(A34>Inputs!$C$62,"",IF(Inputs!$C$85=0,Inputs!$C$64,MIN(Inputs!$C$91,IF(AE34=0,0,AF34/AE34)))) | D34: =IF(A34>Inputs!$C$62,"",IF(Inputs!$C$80=1,INDEX(Cohorts!$G$67:$G$326,A34),MAX(0, Inputs!$C$66 + Inputs!$C$67*L34 + Inputs!$C$68*(1-K34) + Inputs!$C$69*Inputs!$C$10))) | E34: =IF(A34>Inputs!$C$62,"",IF(Inputs!$C$80=1,INDEX(Cohorts!$H$67:$H$326,A34),D34*AD34)) | F34: =IF(A34>Inputs!$C$62,"",IF(Inputs!$C$80=1,INDEX(Cohorts!$I$67:$I$326,A34),AD34-E34)) | G34: =IF(A34>Inputs!$C$62,"",AD34) | H34: =IF(A34>Inputs!$C$62,"",INDEX(CapacityPlan!$E$7:$E$266,A34)) | I34: =IF(A34>Inputs!$C$62,"",INDEX(CapacityPlan!$I$7:$I$266,A34)) | J34: =IF(A34>Inputs!$C$62,"",IF(G34>I34,I34,G34)) | K34: =IF(A34>Inputs!$C$62,"",IF(G34=0,1,J34/G34)) | L34: =IF((Inputs!$C$36 + UnitEconomics!$B$12*Inputs!$C$37 + Inputs!$C$10*Inputs!$C$38 + Inputs!$C$70*(1-K34))>1,1,(Inputs!$C$36 + UnitEconomics!$B$12*Inputs!$C$37 + Inputs!$C$10*Inputs!$C$38 + Inputs!$C$70*(1-K34))) | M34: =IF(A34>Inputs!$C$62,"",J34*Inputs!$C$7*(1-Inputs!$C$8)*(1-L34)) | N34: =IF(A34>Inputs!$C$62,"",J34*UnitEconomics!$B$32*AI34 + (G34-J34)*Inputs!$C$71) | O34: =M34-N34 | P34: =IF(A34>Inputs!$C$62,"",Inputs!$C$40 + H34*Inputs!$C$41) | Q34: =O34-P34 | R34: =IF(A34>Inputs!$C$62,"",AD34*Inputs!$C$16*(Inputs!$C$9 + Inputs!$C$10*Inputs!$C$11 + Inputs!$C$12)*(1 + VLOOKUP(Inputs!$C$15,Lookups!$A$2:$B$20,2,TRUE)*(Scale!$B$9/IF(Scale!$B$8=0,1,Scale!$B$8)) + Inputs!$C$52)) | S34: =IF(A34=1,Scale!$B$13, W33) | T34: =J34*Inputs!$C$16*(Inputs!$C$19 + Inputs!$C$20*Inputs!$C$21 + 1/Inputs!$C$18) | U34: =MAX(0, (R34*(1+Inputs!$C$74)) - (S34 - T34)) | V34: =IF(A34<=Inputs!$C$73,0,INDEX(U:U,ROW()-Inputs!$C$73)) | W34: =S34 - T34 + V34 | X34: =V34*Inputs!$C$17 | Y34: =IF(A34>Inputs!$C$62,"",C34*AE34) | Z34: =IF(A34=1,Inputs!$C$72,AA33) | AA34: =Z34 + M34 - N34 - P34 - X34 - Y34 | AB34: =IF(AA34<0,1,0) | AC34: =IF(AD34=0,0,R34/(AD34*Inputs!$C$16)) | AD34: =IF(A34>Inputs!$C$62,"",B34+C34) | AE34: =IF(A34>Inputs!$C$62,"", Inputs!$C$65*(1+Inputs!$C$89*POWER(MIN(1,IF(Inputs!$C$88=0,0,B34/Inputs!$C$88)),Inputs!$C$90))) | AF34: =IF(A34>Inputs!$C$62,"",IF(A34=1,Inputs!$C$86,MIN(Inputs!$C$86,Inputs!$C$87*M33))) | AG34: =IF(A34>Inputs!$C$62,"",MIN(0.5,MAX(0, Inputs!$C$67*L34 + Inputs!$C$68*(1-K34) + Inputs!$C$69*Inputs!$C$10))) | AH34: =IF(A34>Inputs!$C$62,"",INDEX(CapacityPlan!$G$7:$G$266,A34)) | AI34: =IF(A34>Inputs!$C$62,"",INDEX(CapacityPlan!$J$7:$J$266,A34)) | AJ34: =IF(A34>Inputs!$C$62,"",IF(I34=0,"",G34/I34))
... A222: 200 | B222: =IF(A222>Inputs!$C$62,"",IF(Inputs!$C$80=1,INDEX(Cohorts!$B$67:$B$326,A222),IF(A222=1,Inputs!$C$63,F221))) | C222: =IF(A222>Inputs!$C$62,"",IF(Inputs!$C$85=0,Inputs!$C$64,MIN(Inputs!$C$91,IF(AE222=0,0,AF222/AE222)))) | D222: =IF(A222>Inputs!$C$62,"",IF(Inputs!$C$80=1,INDEX(Cohorts!$G$67:$G$326,A222),MAX(0, Inputs!$C$66 + Inputs!$C$67*L222 + Inputs!$C$68*(1-K222) + Inputs!$C$69*Inputs!$C$10))) | E222: =IF(A222>Inputs!$C$62,"",IF(Inputs!$C$80=1,INDEX(Cohorts!$H$67:$H$326,A222),D222*AD222)) | F222: =IF(A222>Inputs!$C$62,"",IF(Inputs!$C$80=1,INDEX(Cohorts!$I$67:$I$326,A222),AD222-E222)) | G222: =IF(A222>Inputs!$C$62,"",AD222) | H222: =IF(A222>Inputs!$C$62,"",INDEX(CapacityPlan!$E$7:$E$266,A222)) | I222: =IF(A222>Inputs!$C$62,"",INDEX(CapacityPlan!$I$7:$I$266,A222)) | J222: =IF(A222>Inputs!$C$62,"",IF(G222>I222,I222,G222)) | K222: =IF(A222>Inputs!$C$62,"",IF(G222=0,1,J222/G222)) | L222: =IF((Inputs!$C$36 + UnitEconomics!$B$12*Inputs!$C$37 + Inputs!$C$10*Inputs!$C$38 + Inputs!$C$70*(1-K222))>1,1,(Inputs!$C$36 + UnitEconomics!$B$12*Inputs!$C$37 + Inputs!$C$10*Inputs!$C$38 + Inputs!$C$70*(1-K222))) | M222: =IF(A222>Inputs!$C$62,"",J222*Inputs!$C$7*(1-Inputs!$C$8)*(1-L222)) | N222: =IF(A222>Inputs!$C$62,"",J222*UnitEconomics!$B$32*AI222 + (G222-J222)*Inputs!$C$71) | O222: =M222-N222 | P222: =IF(A222>Inputs!$C$62,"",Inputs!$C$40 + H222*Inputs!$C$41) | Q222: =O222-P222 | R222: =IF(A222>Inputs!$C$62,"",AD222*Inputs!$C$16*(Inputs!$C$9 + Inputs!$C$10*Inputs!$C$11 + Inputs!$C$12)*(1 + VLOOKUP(Inputs!$C$15,Lookups!$A$2:$B$20,2,TRUE)*(Scale!$B$9/IF(Scale!$B$8=0,1,Scale!$B$8)) + Inputs!$C$52)) | S222: =IF(A222=1,Scale!$B$13, W221) | T222: =J222*Inputs!$C$16*(Inputs!$C$19 + Inputs!$C$20*Inputs!$C$21 + 1/Inputs!$C$18) | U222: =MAX(0, (R222*(1+Inputs!$C$74)) - (S222 - T222)) | V222: =IF(A222<=Inputs!$C$73,0,INDEX(U:U,ROW()-Inputs!$C$73)) | W222: =S222 - T222 + V222 | X222: =V222*Inputs!$C$17 | Y222: =IF(A222>Inputs!$C$62,"",C222*AE222) | Z222: =IF(A222=1,Inputs!$C$72,AA221) | AA222: =Z222 + M222 - N222 - P222 - X222 - Y222 | AB222: =IF(AA222<0,1,0) | AC222: =IF(AD222=0,0,R222/(AD222*Inputs!$C$16)) | AD222: =IF(A222>Inputs!$C$62,"",B222+C222) | AE222: =IF(A222>Inputs!$C$62,"", Inputs!$C$65*(1+Inputs!$C$89*POWER(MIN(1,IF(Inputs!$C$88=0,0,B222/Inputs!$C$88)),Inputs!$C$90))) | AF222: =IF(A222>Inputs!$C$62,"",IF(A222=1,Inputs!$C$86,MIN(Inputs!$C$86,Inputs!$C$87*M221))) | AG222: =IF(A222>Inputs!$C$62,"",MIN(0.5,MAX(0, Inputs!$C$67*L222 + Inputs!$C$68*(1-K222) + Inputs!$C$69*Inputs!$C$10))) | AH222: =IF(A222>Inputs!$C$62,"",INDEX(CapacityPlan!$G$7:$G$266,A222)) | AI222: =IF(A222>Inputs!$C$62,"",INDEX(CapacityPlan!$J$7:$J$266,A222)) | AJ222: =IF(A222>Inputs!$C$62,"",IF(I222=0,"",G222/I222))
A223: 201 | B223: =IF(A223>Inputs!$C$62,"",IF(Inputs!$C$80=1,INDEX(Cohorts!$B$67:$B$326,A223),IF(A223=1,Inputs!$C$63,F222))) | C223: =IF(A223>Inputs!$C$62,"",IF(Inputs!$C$85=0,Inputs!$C$64,MIN(Inputs!$C$91,IF(AE223=0,0,AF223/AE223)))) | D223: =IF(A223>Inputs!$C$62,"",IF(Inputs!$C$80=1,INDEX(Cohorts!$G$67:$G$326,A223),MAX(0, Inputs!$C$66 + Inputs!$C$67*L223 + Inputs!$C$68*(1-K223) + Inputs!$C$69*Inputs!$C$10))) | E223: =IF(A223>Inputs!$C$62,"",IF(Inputs!$C$80=1,INDEX(Cohorts!$H$67:$H$326,A223),D223*AD223)) | F223: =IF(A223>Inputs!$C$62,"",IF(Inputs!$C$80=1,INDEX(Cohorts!$I$67:$I$326,A223),AD223-E223)) | G223: =IF(A223>Inputs!$C$62,"",AD223) | H223: =IF(A223>Inputs!$C$62,"",INDEX(CapacityPlan!$E$7:$E$266,A223)) | I223: =IF(A223>Inputs!$C$62,"",INDEX(CapacityPlan!$I$7:$I$266,A223)) | J223: =IF(A223>Inputs!$C$62,"",IF(G223>I223,I223,G223)) | K223: =IF(A223>Inputs!$C$62,"",IF(G223=0,1,J223/G223)) | M223: =IF(A223>Inputs!$C$62,"",J223*Inputs!$C$7*(1-Inputs!$C$8)*(1-L223)) | N223: =IF(A223>Inputs!$C$62,"",J223*UnitEconomics!$B$32*AI223 + (G223-J223)*Inputs!$C$71) | P223: =IF(A223>Inputs!$C$62,"",Inputs!$C$40 + H223*Inputs!$C$41) | R223: =IF(A223>Inputs!$C$62,"",AD223*Inputs!$C$16*(Inputs!$C$9 + Inputs!$C$10*Inputs!$C$11 + Inputs!$C$12)*(1 + VLOOKUP(Inputs!$C$15,Lookups!$A$2:$B$20,2,TRUE)*(Scale!$B$9/IF(Scale!$B$8=0,1,Scale!$B$8)) + Inputs!$C$52)) | Y223: =IF(A223>Inputs!$C$62,"",C223*AE223) | AC223: =IF(AD223=0,0,R223/(AD223*Inputs!$C$16)) | AD223: =IF(A223>Inputs!$C$62,"",B223+C223) | AE223: =IF(A223>Inputs!$C$62,"", Inputs!$C$65*(1+Inputs!$C$89*POWER(MIN(1,IF(Inputs!$C$88=0,0,B223/Inputs!$C$88)),Inputs!$C$90))) | AF223: =IF(A223>Inputs!$C$62,"",IF(A223=1,Inputs!$C$86,MIN(Inputs!$C$86,Inputs!$C$87*M222))) | AG223: =IF(A223>Inputs!$C$62,"",MIN(0.5,MAX(0, Inputs!$C$67*L223 + Inputs!$C$68*(1-K223) + Inputs!$C$69*Inputs!$C$10))) | AH223: =IF(A223>Inputs!$C$62,"",INDEX(CapacityPlan!$G$7:$G$266,A223)) | AI223: =IF(A223>Inputs!$C$62,"",INDEX(CapacityPlan!$J$7:$J$266,A223)) | AJ223: =IF(A223>Inputs!$C$62,"",IF(I223=0,"",G223/I223))
A224: 202 | B224: =IF(A224>Inputs!$C$62,"",IF(Inputs!$C$80=1,INDEX(Cohorts!$B$67:$B$326,A224),IF(A224=1,Inputs!$C$63,F223))) | C224: =IF(A224>Inputs!$C$62,"",IF(Inputs!$C$85=0,Inputs!$C$64,MIN(Inputs!$C$91,IF(AE224=0,0,AF224/AE224)))) | D224: =IF(A224>Inputs!$C$62,"",IF(Inputs!$C$80=1,INDEX(Cohorts!$G$67:$G$326,A224),MAX(0, Inputs!$C$66 + Inputs!$C$67*L224 + Inputs!$C$68*(1-K224) + Inputs!$C$69*Inputs!$C$10))) | E224: =IF(A224>Inputs!$C$62,"",IF(Inputs!$C$80=1,INDEX(Cohorts!$H$67:$H$326,A224),D224*AD224)) | F224: =IF(A224>Inputs!$C$62,"",IF(Inputs!$C$80=1,INDEX(Cohorts!$I$67:$I$326,A224),AD224-E224)) | G224: =IF(A224>Inputs!$C$62,"",AD224) | H224: =IF(A224>Inputs!$C$62,"",INDEX(CapacityPlan!$E$7:$E$266,A224)) | I224: =IF(A224>Inputs!$C$62,"",INDEX(CapacityPlan!$I$7:$I$266,A224)) | J224: =IF(A224>Inputs!$C$62,"",IF(G224>I224,I224,G224)) | K224: =IF(A224>Inputs!$C$62,"",IF(G224=0,1,J224/G224)) | M224: =IF(A224>Inputs!$C$62,"",J224*Inputs!$C$7*(1-Inputs!$C$8)*(1-L224)) | N224: =IF(A224>Inputs!$C$62,"",J224*UnitEconomics!$B$32*AI224 + (G224-J224)*Inputs!$C$71) | P224: =IF(A224>Inputs!$C$62,"",Inputs!$C$40 + H224*Inputs!$C$41) | R224: =IF(A224>Inputs!$C$62,"",AD224*Inputs!$C$16*(Inputs!$C$9 + Inputs!$C$10*Inputs!$C$11 + Inputs!$C$12)*(1 + VLOOKUP(Inputs!$C$15,Lookups!$A$2:$B$20,2,TRUE)*(Scale!$B$9/IF(Scale!$B$8=0,1,Scale!$B$8)) + Inputs!$C$52)) | Y224: =IF(A224>Inputs!$C$62,"",C224*AE224) | AC224: =IF(AD224=0,0,R224/(AD224*Inputs!$C$16)) | AD224: =IF(A224>Inputs!$C$62,"",B224+C224) | AE224: =IF(A224>Inputs!$C$62,"", Inputs!$C$65*(1+Inputs!$C$89*POWER(MIN(1,IF(Inputs!$C$88=0,0,B224/Inputs!$C$88)),Inputs!$C$90))) | AF224: =IF(A224>Inputs!$C$62,"",IF(A224=1,Inputs!$C$86,MIN(Inputs!$C$86,Inputs!$C$87*M223))) | AG224: =IF(A224>Inputs!$C$62,"",MIN(0.5,MAX(0, Inputs!$C$67*L224 + Inputs!$C$68*(1-K224) + Inputs!$C$69*Inputs!$C$10))) | AH224: =IF(A224>Inputs!$C$62,"",INDEX(CapacityPlan!$G$7:$G$266,A224)) | AI224: =IF(A224>Inputs!$C$62,"",INDEX(CapacityPlan!$J$7:$J$266,A224)) | AJ224: =IF(A224>Inputs!$C$62,"",IF(I224=0,"",G224/I224))
A225: 203 | B225: =IF(A225>Inputs!$C$62,"",IF(Inputs!$C$80=1,INDEX(Cohorts!$B$67:$B$326,A225),IF(A225=1,Inputs!$C$63,F224))) | C225: =IF(A225>Inputs!$C$62,"",IF(Inputs!$C$85=0,Inputs!$C$64,MIN(Inputs!$C$91,IF(AE225=0,0,AF225/AE225)))) | D225: =IF(A225>Inputs!$C$62,"",IF(Inputs!$C$80=1,INDEX(Cohorts!$G$67:$G$326,A225),MAX(0, Inputs!$C$66 + Inputs!$C$67*L225 + Inputs!$C$68*(1-K225) + Inputs!$C$69*Inputs!$C$10))) | E225: =IF(A225>Inputs!$C$62,"",IF(Inputs!$C$80=1,INDEX(Cohorts!$H$67:$H$326,A225),D225*AD225)) | F225: =IF(A225>Inputs!$C$62,"",IF(Inputs!$C$80=1,INDEX(Cohorts!$I$67:$I$326,A225),AD225-E225)) | G225: =IF(A225>Inputs!$C$62,"",AD225) | H225: =IF(A225>Inputs!$C$62,"",INDEX(CapacityPlan!$E$7:$E$266,A225)) | I225: =IF(A225>Inputs!$C$62,"",INDEX(CapacityPlan!$I$7:$I$266,A225)) | J225: =IF(A225>Inputs!$C$62,"",IF(G225>I225,I225,G225)) | K225: =IF(A225>Inputs!$C$62,"",IF(G225=0,1,J225/G225)) | M225: =IF(A225>Inputs!$C$62,"",J225*Inputs!$C$7*(1-Inputs!$C$8)*(1-L225)) | N225: =IF(A225>Inputs!$C$62,"",J225*UnitEconomics!$B$32*AI225 + (G225-J225)*Inputs!$C$71) | P225: =IF(A225>Inputs!$C$62,"",Inputs!$C$40 + H225*Inputs!$C$41) | R225: =IF(A225>Inputs!$C$62,"",AD225*Inputs!$C$16*(Inputs!$C$9 + Inputs!$C$10*Inputs!$C$11 + Inputs!$C$12)*(1 + VLOOKUP(Inputs!$C$15,Lookups!$A$2:$B$20,2,TRUE)*(Scale!$B$9/IF(Scale!$B$8=0,1,Scale!$B$8)) + Inputs!$C$52)) | Y225: =IF(A225>Inputs!$C$62,"",C225*AE225) | AC225: =IF(AD225=0,0,R225/(AD225*Inputs!$C$16)) | AD225: =IF(A225>Inputs!$C$62,"",B225+C225) | AE225: =IF(A225>Inputs!$C$62,"", Inputs!$C$65*(1+Inputs!$C$89*POWER(MIN(1,IF(Inputs!$C$88=0,0,B225/Inputs!$C$88)),Inputs!$C$90))) | AF225: =IF(A225>Inputs!$C$62,"",IF(A225=1,Inputs!$C$86,MIN(Inputs!$C$86,Inputs!$C$87*M224))) | AG225: =IF(A225>Inputs!$C$62,"",MIN(0.5,MAX(0, Inputs!$C$67*L225 + Inputs!$C$68*(1-K225) + Inputs!$C$69*Inputs!$C$10))) | AH225: =IF(A225>Inputs!$C$62,"",INDEX(CapacityPlan!$G$7:$G$266,A225)) | AI225: =IF(A225>Inputs!$C$62,"",INDEX(CapacityPlan!$J$7:$J$266,A225)) | AJ225: =IF(A225>Inputs!$C$62,"",IF(I225=0,"",G225/I225))
A226: 204 | B226: =IF(A226>Inputs!$C$62,"",IF(Inputs!$C$80=1,INDEX(Cohorts!$B$67:$B$326,A226),IF(A226=1,Inputs!$C$63,F225))) | C226: =IF(A226>Inputs!$C$62,"",IF(Inputs!$C$85=0,Inputs!$C$64,MIN(Inputs!$C$91,IF(AE226=0,0,AF226/AE226)))) | D226: =IF(A226>Inputs!$C$62,"",IF(Inputs!$C$80=1,INDEX(Cohorts!$G$67:$G$326,A226),MAX(0, Inputs!$C$66 + Inputs!$C$67*L226 + Inputs!$C$68*(1-K226) + Inputs!$C$69*Inputs!$C$10))) | E226: =IF(A226>Inputs!$C$62,"",IF(Inputs!$C$80=1,INDEX(Cohorts!$H$67:$H$326,A226),D226*AD226)) | F226: =IF(A226>Inputs!$C$62,"",IF(Inputs!$C$80=1,INDEX(Cohorts!$I$67:$I$326,A226),AD226-E226)) | G226: =IF(A226>Inputs!$C$62,"",AD226) | H226: =IF(A226>Inputs!$C$62,"",INDEX(CapacityPlan!$E$7:$E$266,A226)) | I226: =IF(A226>Inputs!$C$62,"",INDEX(CapacityPlan!$I$7:$I$266,A226)) | J226: =IF(A226>Inputs!$C$62,"",IF(G226>I226,I226,G226)) | K226: =IF(A226>Inputs!$C$62,"",IF(G226=0,1,J226/G226)) | M226: =IF(A226>Inputs!$C$62,"",J226*Inputs!$C$7*(1-Inputs!$C$8)*(1-L226)) | N226: =IF(A226>Inputs!$C$62,"",J226*UnitEconomics!$B$32*AI226 + (G226-J226)*Inputs!$C$71) | P226: =IF(A226>Inputs!$C$62,"",Inputs!$C$40 + H226*Inputs!$C$41) | R226: =IF(A226>Inputs!$C$62,"",AD226*Inputs!$C$16*(Inputs!$C$9 + Inputs!$C$10*Inputs!$C$11 + Inputs!$C$12)*(1 + VLOOKUP(Inputs!$C$15,Lookups!$A$2:$B$20,2,TRUE)*(Scale!$B$9/IF(Scale!$B$8=0,1,Scale!$B$8)) + Inputs!$C$52)) | Y226: =IF(A226>Inputs!$C$62,"",C226*AE226) | AC226: =IF(AD226=0,0,R226/(AD226*Inputs!$C$16)) | AD226: =IF(A226>Inputs!$C$62,"",B226+C226) | AE226: =IF(A226>Inputs!$C$62,"", Inputs!$C$65*(1+Inputs!$C$89*POWER(MIN(1,IF(Inputs!$C$88=0,0,B226/Inputs!$C$88)),Inputs!$C$90))) | AF226: =IF(A226>Inputs!$C$62,"",IF(A226=1,Inputs!$C$86,MIN(Inputs!$C$86,Inputs!$C$87*M225))) | AG226: =IF(A226>Inputs!$C$62,"",MIN(0.5,MAX(0, Inputs!$C$67*L226 + Inputs!$C$68*(1-K226) + Inputs!$C$69*Inputs!$C$10))) | AH226: =IF(A226>Inputs!$C$62,"",INDEX(CapacityPlan!$G$7:$G$266,A226)) | AI226: =IF(A226>Inputs!$C$62,"",INDEX(CapacityPlan!$J$7:$J$266,A226)) | AJ226: =IF(A226>Inputs!$C$62,"",IF(I226=0,"",G226/I226))
A227: 205 | B227: =IF(A227>Inputs!$C$62,"",IF(Inputs!$C$80=1,INDEX(Cohorts!$B$67:$B$326,A227),IF(A227=1,Inputs!$C$63,F226))) | C227: =IF(A227>Inputs!$C$62,"",IF(Inputs!$C$85=0,Inputs!$C$64,MIN(Inputs!$C$91,IF(AE227=0,0,AF227/AE227)))) | D227: =IF(A227>Inputs!$C$62,"",IF(Inputs!$C$80=1,INDEX(Cohorts!$G$67:$G$326,A227),MAX(0, Inputs!$C$66 + Inputs!$C$67*L227 + Inputs!$C$68*(1-K227) + Inputs!$C$69*Inputs!$C$10))) | E227: =IF(A227>Inputs!$C$62,"",IF(Inputs!$C$80=1,INDEX(Cohorts!$H$67:$H$326,A227),D227*AD227)) | F227: =IF(A227>Inputs!$C$62,"",IF(Inputs!$C$80=1,INDEX(Cohorts!$I$67:$I$326,A227),AD227-E227)) | G227: =IF(A227>Inputs!$C$62,"",AD227) | H227: =IF(A227>Inputs!$C$62,"",INDEX(CapacityPlan!$E$7:$E$266,A227)) | I227: =IF(A227>Inputs!$C$62,"",INDEX(CapacityPlan!$I$7:$I$266,A227)) | J227: =IF(A227>Inputs!$C$62,"",IF(G227>I227,I227,G227)) | K227: =IF(A227>Inputs!$C$62,"",IF(G227=0,1,J227/G227)) | M227: =IF(A227>Inputs!$C$62,"",J227*Inputs!$C$7*(1-Inputs!$C$8)*(1-L227)) | N227: =IF(A227>Inputs!$C$62,"",J227*UnitEconomics!$B$32*AI227 + (G227-J227)*Inputs!$C$71) | P227: =IF(A227>Inputs!$C$62,"",Inputs!$C$40 + H227*Inputs!$C$41) | R227: =IF(A227>Inputs!$C$62,"",AD227*Inputs!$C$16*(Inputs!$C$9 + Inputs!$C$10*Inputs!$C$11 + Inputs!$C$12)*(1 + VLOOKUP(Inputs!$C$15,Lookups!$A$2:$B$20,2,TRUE)*(Scale!$B$9/IF(Scale!$B$8=0,1,Scale!$B$8)) + Inputs!$C$52)) | Y227: =IF(A227>Inputs!$C$62,"",C227*AE227) | AC227: =IF(AD227=0,0,R227/(AD227*Inputs!$C$16)) | AD227: =IF(A227>Inputs!$C$62,"",B227+C227) | AE227: =IF(A227>Inputs!$C$62,"", Inputs!$C$65*(1+Inputs!$C$89*POWER(MIN(1,IF(Inputs!$C$88=0,0,B227/Inputs!$C$88)),Inputs!$C$90))) | AF227: =IF(A227>Inputs!$C$62,"",IF(A227=1,Inputs!$C$86,MIN(Inputs!$C$86,Inputs!$C$87*M226))) | AG227: =IF(A227>Inputs!$C$62,"",MIN(0.5,MAX(0, Inputs!$C$67*L227 + Inputs!$C$68*(1-K227) + Inputs!$C$69*Inputs!$C$10))) | AH227: =IF(A227>Inputs!$C$62,"",INDEX(CapacityPlan!$G$7:$G$266,A227)) | AI227: =IF(A227>Inputs!$C$62,"",INDEX(CapacityPlan!$J$7:$J$266,A227)) | AJ227: =IF(A227>Inputs!$C$62,"",IF(I227=0,"",G227/I227))
A228: 206 | B228: =IF(A228>Inputs!$C$62,"",IF(Inputs!$C$80=1,INDEX(Cohorts!$B$67:$B$326,A228),IF(A228=1,Inputs!$C$63,F227))) | C228: =IF(A228>Inputs!$C$62,"",IF(Inputs!$C$85=0,Inputs!$C$64,MIN(Inputs!$C$91,IF(AE228=0,0,AF228/AE228)))) | D228: =IF(A228>Inputs!$C$62,"",IF(Inputs!$C$80=1,INDEX(Cohorts!$G$67:$G$326,A228),MAX(0, Inputs!$C$66 + Inputs!$C$67*L228 + Inputs!$C$68*(1-K228) + Inputs!$C$69*Inputs!$C$10))) | E228: =IF(A228>Inputs!$C$62,"",IF(Inputs!$C$80=1,INDEX(Cohorts!$H$67:$H$326,A228),D228*AD228)) | F228: =IF(A228>Inputs!$C$62,"",IF(Inputs!$C$80=1,INDEX(Cohorts!$I$67:$I$326,A228),AD228-E228)) | G228: =IF(A228>Inputs!$C$62,"",AD228) | H228: =IF(A228>Inputs!$C$62,"",INDEX(CapacityPlan!$E$7:$E$266,A228)) | I228: =IF(A228>Inputs!$C$62,"",INDEX(CapacityPlan!$I$7:$I$266,A228)) | J228: =IF(A228>Inputs!$C$62,"",IF(G228>I228,I228,G228)) | K228: =IF(A228>Inputs!$C$62,"",IF(G228=0,1,J228/G228)) | M228: =IF(A228>Inputs!$C$62,"",J228*Inputs!$C$7*(1-Inputs!$C$8)*(1-L228)) | N228: =IF(A228>Inputs!$C$62,"",J228*UnitEconomics!$B$32*AI228 + (G228-J228)*Inputs!$C$71) | P228: =IF(A228>Inputs!$C$62,"",Inputs!$C$40 + H228*Inputs!$C$41) | R228: =IF(A228>Inputs!$C$62,"",AD228*Inputs!$C$16*(Inputs!$C$9 + Inputs!$C$10*Inputs!$C$11 + Inputs!$C$12)*(1 + VLOOKUP(Inputs!$C$15,Lookups!$A$2:$B$20,2,TRUE)*(Scale!$B$9/IF(Scale!$B$8=0,1,Scale!$B$8)) + Inputs!$C$52)) | Y228: =IF(A228>Inputs!$C$62,"",C228*AE228) | AC228: =IF(AD228=0,0,R228/(AD228*Inputs!$C$16)) | AD228: =IF(A228>Inputs!$C$62,"",B228+C228) | AE228: =IF(A228>Inputs!$C$62,"", Inputs!$C$65*(1+Inputs!$C$89*POWER(MIN(1,IF(Inputs!$C$88=0,0,B228/Inputs!$C$88)),Inputs!$C$90))) | AF228: =IF(A228>Inputs!$C$62,"",IF(A228=1,Inputs!$C$86,MIN(Inputs!$C$86,Inputs!$C$87*M227))) | AG228: =IF(A228>Inputs!$C$62,"",MIN(0.5,MAX(0, Inputs!$C$67*L228 + Inputs!$C$68*(1-K228) + Inputs!$C$69*Inputs!$C$10))) | AH228: =IF(A228>Inputs!$C$62,"",INDEX(CapacityPlan!$G$7:$G$266,A228)) | AI228: =IF(A228>Inputs!$C$62,"",INDEX(CapacityPlan!$J$7:$J$266,A228)) | AJ228: =IF(A228>Inputs!$C$62,"",IF(I228=0,"",G228/I228))
A229: 207 | B229: =IF(A229>Inputs!$C$62,"",IF(Inputs!$C$80=1,INDEX(Cohorts!$B$67:$B$326,A229),IF(A229=1,Inputs!$C$63,F228))) | C229: =IF(A229>Inputs!$C$62,"",IF(Inputs!$C$85=0,Inputs!$C$64,MIN(Inputs!$C$91,IF(AE229=0,0,AF229/AE229)))) | D229: =IF(A229>Inputs!$C$62,"",IF(Inputs!$C$80=1,INDEX(Cohorts!$G$67:$G$326,A229),MAX(0, Inputs!$C$66 + Inputs!$C$67*L229 + Inputs!$C$68*(1-K229) + Inputs!$C$69*Inputs!$C$10))) | E229: =IF(A229>Inputs!$C$62,"",IF(Inputs!$C$80=1,INDEX(Cohorts!$H$67:$H$326,A229),D229*AD229)) | F229: =IF(A229>Inputs!$C$62,"",IF(Inputs!$C$80=1,INDEX(Cohorts!$I$67:$I$326,A229),AD229-E229)) | G229: =IF(A229>Inputs!$C$62,"",AD229) | H229: =IF(A229>Inputs!$C$62,"",INDEX(CapacityPlan!$E$7:$E$266,A229)) | I229: =IF(A229>Inputs!$C$62,"",INDEX(CapacityPlan!$I$7:$I$266,A229)) | J229: =IF(A229>Inputs!$C$62,"",IF(G229>I229,I229,G229)) | K229: =IF(A229>Inputs!$C$62,"",IF(G229=0,1,J229/G229)) | M229: =IF(A229>Inputs!$C$62,"",J229*Inputs!$C$7*(1-Inputs!$C$8)*(1-L229)) | N229: =IF(A229>Inputs!$C$62,"",J229*UnitEconomics!$B$32*AI229 + (G229-J229)*Inputs!$C$71) | P229: =IF(A229>Inputs!$C$62,"",Inputs!$C$40 + H229*Inputs!$C$41) | R229: =IF(A229>Inputs!$C$62,"",AD229*Inputs!$C$16*(Inputs!$C$9 + Inputs!$C$10*Inputs!$C$11 + Inputs!$C$12)*(1 + VLOOKUP(Inputs!$C$15,Lookups!$A$2:$B$20,2,TRUE)*(Scale!$B$9/IF(Scale!$B$8=0,1,Scale!$B$8)) + Inputs!$C$52)) | Y229: =IF(A229>Inputs!$C$62,"",C229*AE229) | AC229: =IF(AD229=0,0,R229/(AD229*Inputs!$C$16)) | AD229: =IF(A229>Inputs!$C$62,"",B229+C229) | AE229: =IF(A229>Inputs!$C$62,"", Inputs!$C$65*(1+Inputs!$C$89*POWER(MIN(1,IF(Inputs!$C$88=0,0,B229/Inputs!$C$88)),Inputs!$C$90))) | AF229: =IF(A229>Inputs!$C$62,"",IF(A229=1,Inputs!$C$86,MIN(Inputs!$C$86,Inputs!$C$87*M228))) | AG229: =IF(A229>Inputs!$C$62,"",MIN(0.5,MAX(0, Inputs!$C$67*L229 + Inputs!$C$68*(1-K229) + Inputs!$C$69*Inputs!$C$10))) | AH229: =IF(A229>Inputs!$C$62,"",INDEX(CapacityPlan!$G$7:$G$266,A229)) | AI229: =IF(A229>Inputs!$C$62,"",INDEX(CapacityPlan!$J$7:$J$266,A229)) | AJ229: =IF(A229>Inputs!$C$62,"",IF(I229=0,"",G229/I229))
A230: 208 | B230: =IF(A230>Inputs!$C$62,"",IF(Inputs!$C$80=1,INDEX(Cohorts!$B$67:$B$326,A230),IF(A230=1,Inputs!$C$63,F229))) | C230: =IF(A230>Inputs!$C$62,"",IF(Inputs!$C$85=0,Inputs!$C$64,MIN(Inputs!$C$91,IF(AE230=0,0,AF230/AE230)))) | D230: =IF(A230>Inputs!$C$62,"",IF(Inputs!$C$80=1,INDEX(Cohorts!$G$67:$G$326,A230),MAX(0, Inputs!$C$66 + Inputs!$C$67*L230 + Inputs!$C$68*(1-K230) + Inputs!$C$69*Inputs!$C$10))) | E230: =IF(A230>Inputs!$C$62,"",IF(Inputs!$C$80=1,INDEX(Cohorts!$H$67:$H$326,A230),D230*AD230)) | F230: =IF(A230>Inputs!$C$62,"",IF(Inputs!$C$80=1,INDEX(Cohorts!$I$67:$I$326,A230),AD230-E230)) | G230: =IF(A230>Inputs!$C$62,"",AD230) | H230: =IF(A230>Inputs!$C$62,"",INDEX(CapacityPlan!$E$7:$E$266,A230)) | I230: =IF(A230>Inputs!$C$62,"",INDEX(CapacityPlan!$I$7:$I$266,A230)) | J230: =IF(A230>Inputs!$C$62,"",IF(G230>I230,I230,G230)) | K230: =IF(A230>Inputs!$C$62,"",IF(G230=0,1,J230/G230)) | M230: =IF(A230>Inputs!$C$62,"",J230*Inputs!$C$7*(1-Inputs!$C$8)*(1-L230)) | N230: =IF(A230>Inputs!$C$62,"",J230*UnitEconomics!$B$32*AI230 + (G230-J230)*Inputs!$C$71) | P230: =IF(A230>Inputs!$C$62,"",Inputs!$C$40 + H230*Inputs!$C$41) | R230: =IF(A230>Inputs!$C$62,"",AD230*Inputs!$C$16*(Inputs!$C$9 + Inputs!$C$10*Inputs!$C$11 + Inputs!$C$12)*(1 + VLOOKUP(Inputs!$C$15,Lookups!$A$2:$B$20,2,TRUE)*(Scale!$B$9/IF(Scale!$B$8=0,1,Scale!$B$8)) + Inputs!$C$52)) | Y230: =IF(A230>Inputs!$C$62,"",C230*AE230) | AC230: =IF(AD230=0,0,R230/(AD230*Inputs!$C$16)) | AD230: =IF(A230>Inputs!$C$62,"",B230+C230) | AE230: =IF(A230>Inputs!$C$62,"", Inputs!$C$65*(1+Inputs!$C$89*POWER(MIN(1,IF(Inputs!$C$88=0,0,B230/Inputs!$C$88)),Inputs!$C$90))) | AF230: =IF(A230>Inputs!$C$62,"",IF(A230=1,Inputs!$C$86,MIN(Inputs!$C$86,Inputs!$C$87*M229))) | AG230: =IF(A230>Inputs!$C$62,"",MIN(0.5,MAX(0, Inputs!$C$67*L230 + Inputs!$C$68*(1-K230) + Inputs!$C$69*Inputs!$C$10))) | AH230: =IF(A230>Inputs!$C$62,"",INDEX(CapacityPlan!$G$7:$G$266,A230)) | AI230: =IF(A230>Inputs!$C$62,"",INDEX(CapacityPlan!$J$7:$J$266,A230)) | AJ230: =IF(A230>Inputs!$C$62,"",IF(I230=0,"",G230/I230))
A231: 209 | B231: =IF(A231>Inputs!$C$62,"",IF(Inputs!$C$80=1,INDEX(Cohorts!$B$67:$B$326,A231),IF(A231=1,Inputs!$C$63,F230))) | C231: =IF(A231>Inputs!$C$62,"",IF(Inputs!$C$85=0,Inputs!$C$64,MIN(Inputs!$C$91,IF(AE231=0,0,AF231/AE231)))) | D231: =IF(A231>Inputs!$C$62,"",IF(Inputs!$C$80=1,INDEX(Cohorts!$G$67:$G$326,A231),MAX(0, Inputs!$C$66 + Inputs!$C$67*L231 + Inputs!$C$68*(1-K231) + Inputs!$C$69*Inputs!$C$10))) | E231: =IF(A231>Inputs!$C$62,"",IF(Inputs!$C$80=1,INDEX(Cohorts!$H$67:$H$326,A231),D231*AD231)) | F231: =IF(A231>Inputs!$C$62,"",IF(Inputs!$C$80=1,INDEX(Cohorts!$I$67:$I$326,A231),AD231-E231)) | G231: =IF(A231>Inputs!$C$62,"",AD231) | H231: =IF(A231>Inputs!$C$62,"",INDEX(CapacityPlan!$E$7:$E$266,A231)) | I231: =IF(A231>Inputs!$C$62,"",INDEX(CapacityPlan!$I$7:$I$266,A231)) | J231: =IF(A231>Inputs!$C$62,"",IF(G231>I231,I231,G231)) | K231: =IF(A231>Inputs!$C$62,"",IF(G231=0,1,J231/G231)) | M231: =IF(A231>Inputs!$C$62,"",J231*Inputs!$C$7*(1-Inputs!$C$8)*(1-L231)) | N231: =IF(A231>Inputs!$C$62,"",J231*UnitEconomics!$B$32*AI231 + (G231-J231)*Inputs!$C$71) | P231: =IF(A231>Inputs!$C$62,"",Inputs!$C$40 + H231*Inputs!$C$41) | R231: =IF(A231>Inputs!$C$62,"",AD231*Inputs!$C$16*(Inputs!$C$9 + Inputs!$C$10*Inputs!$C$11 + Inputs!$C$12)*(1 + VLOOKUP(Inputs!$C$15,Lookups!$A$2:$B$20,2,TRUE)*(Scale!$B$9/IF(Scale!$B$8=0,1,Scale!$B$8)) + Inputs!$C$52)) | Y231: =IF(A231>Inputs!$C$62,"",C231*AE231) | AC231: =IF(AD231=0,0,R231/(AD231*Inputs!$C$16)) | AD231: =IF(A231>Inputs!$C$62,"",B231+C231) | AE231: =IF(A231>Inputs!$C$62,"", Inputs!$C$65*(1+Inputs!$C$89*POWER(MIN(1,IF(Inputs!$C$88=0,0,B231/Inputs!$C$88)),Inputs!$C$90))) | AF231: =IF(A231>Inputs!$C$62,"",IF(A231=1,Inputs!$C$86,MIN(Inputs!$C$86,Inputs!$C$87*M230))) | AG231: =IF(A231>Inputs!$C$62,"",MIN(0.5,MAX(0, Inputs!$C$67*L231 + Inputs!$C$68*(1-K231) + Inputs!$C$69*Inputs!$C$10))) | AH231: =IF(A231>Inputs!$C$62,"",INDEX(CapacityPlan!$G$7:$G$266,A231)) | AI231: =IF(A231>Inputs!$C$62,"",INDEX(CapacityPlan!$J$7:$J$266,A231)) | AJ231: =IF(A231>Inputs!$C$62,"",IF(I231=0,"",G231/I231))
A232: 210 | B232: =IF(A232>Inputs!$C$62,"",IF(Inputs!$C$80=1,INDEX(Cohorts!$B$67:$B$326,A232),IF(A232=1,Inputs!$C$63,F231))) | C232: =IF(A232>Inputs!$C$62,"",IF(Inputs!$C$85=0,Inputs!$C$64,MIN(Inputs!$C$91,IF(AE232=0,0,AF232/AE232)))) | D232: =IF(A232>Inputs!$C$62,"",IF(Inputs!$C$80=1,INDEX(Cohorts!$G$67:$G$326,A232),MAX(0, Inputs!$C$66 + Inputs!$C$67*L232 + Inputs!$C$68*(1-K232) + Inputs!$C$69*Inputs!$C$10))) | E232: =IF(A232>Inputs!$C$62,"",IF(Inputs!$C$80=1,INDEX(Cohorts!$H$67:$H$326,A232),D232*AD232)) | F232: =IF(A232>Inputs!$C$62,"",IF(Inputs!$C$80=1,INDEX(Cohorts!$I$67:$I$326,A232),AD232-E232)) | G232: =IF(A232>Inputs!$C$62,"",AD232) | H232: =IF(A232>Inputs!$C$62,"",INDEX(CapacityPlan!$E$7:$E$266,A232)) | I232: =IF(A232>Inputs!$C$62,"",INDEX(CapacityPlan!$I$7:$I$266,A232)) | J232: =IF(A232>Inputs!$C$62,"",IF(G232>I232,I232,G232)) | K232: =IF(A232>Inputs!$C$62,"",IF(G232=0,1,J232/G232)) | M232: =IF(A232>Inputs!$C$62,"",J232*Inputs!$C$7*(1-Inputs!$C$8)*(1-L232)) | N232: =IF(A232>Inputs!$C$62,"",J232*UnitEconomics!$B$32*AI232 + (G232-J232)*Inputs!$C$71) | P232: =IF(A232>Inputs!$C$62,"",Inputs!$C$40 + H232*Inputs!$C$41) | R232: =IF(A232>Inputs!$C$62,"",AD232*Inputs!$C$16*(Inputs!$C$9 + Inputs!$C$10*Inputs!$C$11 + Inputs!$C$12)*(1 + VLOOKUP(Inputs!$C$15,Lookups!$A$2:$B$20,2,TRUE)*(Scale!$B$9/IF(Scale!$B$8=0,1,Scale!$B$8)) + Inputs!$C$52)) | Y232: =IF(A232>Inputs!$C$62,"",C232*AE232) | AC232: =IF(AD232=0,0,R232/(AD232*Inputs!$C$16)) | AD232: =IF(A232>Inputs!$C$62,"",B232+C232) | AE232: =IF(A232>Inputs!$C$62,"", Inputs!$C$65*(1+Inputs!$C$89*POWER(MIN(1,IF(Inputs!$C$88=0,0,B232/Inputs!$C$88)),Inputs!$C$90))) | AF232: =IF(A232>Inputs!$C$62,"",IF(A232=1,Inputs!$C$86,MIN(Inputs!$C$86,Inputs!$C$87*M231))) | AG232: =IF(A232>Inputs!$C$62,"",MIN(0.5,MAX(0, Inputs!$C$67*L232 + Inputs!$C$68*(1-K232) + Inputs!$C$69*Inputs!$C$10))) | AH232: =IF(A232>Inputs!$C$62,"",INDEX(CapacityPlan!$G$7:$G$266,A232)) | AI232: =IF(A232>Inputs!$C$62,"",INDEX(CapacityPlan!$J$7:$J$266,A232)) | AJ232: =IF(A232>Inputs!$C$62,"",IF(I232=0,"",G232/I232))
A233: 211 | B233: =IF(A233>Inputs!$C$62,"",IF(Inputs!$C$80=1,INDEX(Cohorts!$B$67:$B$326,A233),IF(A233=1,Inputs!$C$63,F232))) | C233: =IF(A233>Inputs!$C$62,"",IF(Inputs!$C$85=0,Inputs!$C$64,MIN(Inputs!$C$91,IF(AE233=0,0,AF233/AE233)))) | D233: =IF(A233>Inputs!$C$62,"",IF(Inputs!$C$80=1,INDEX(Cohorts!$G$67:$G$326,A233),MAX(0, Inputs!$C$66 + Inputs!$C$67*L233 + Inputs!$C$68*(1-K233) + Inputs!$C$69*Inputs!$C$10))) | E233: =IF(A233>Inputs!$C$62,"",IF(Inputs!$C$80=1,INDEX(Cohorts!$H$67:$H$326,A233),D233*AD233)) | F233: =IF(A233>Inputs!$C$62,"",IF(Inputs!$C$80=1,INDEX(Cohorts!$I$67:$I$326,A233),AD233-E233)) | G233: =IF(A233>Inputs!$C$62,"",AD233) | H233: =IF(A233>Inputs!$C$62,"",INDEX(CapacityPlan!$E$7:$E$266,A233)) | I233: =IF(A233>Inputs!$C$62,"",INDEX(CapacityPlan!$I$7:$I$266,A233)) | J233: =IF(A233>Inputs!$C$62,"",IF(G233>I233,I233,G233)) | K233: =IF(A233>Inputs!$C$62,"",IF(G233=0,1,J233/G233)) | M233: =IF(A233>Inputs!$C$62,"",J233*Inputs!$C$7*(1-Inputs!$C$8)*(1-L233)) | N233: =IF(A233>Inputs!$C$62,"",J233*UnitEconomics!$B$32*AI233 + (G233-J233)*Inputs!$C$71) | P233: =IF(A233>Inputs!$C$62,"",Inputs!$C$40 + H233*Inputs!$C$41) | R233: =IF(A233>Inputs!$C$62,"",AD233*Inputs!$C$16*(Inputs!$C$9 + Inputs!$C$10*Inputs!$C$11 + Inputs!$C$12)*(1 + VLOOKUP(Inputs!$C$15,Lookups!$A$2:$B$20,2,TRUE)*(Scale!$B$9/IF(Scale!$B$8=0,1,Scale!$B$8)) + Inputs!$C$52)) | Y233: =IF(A233>Inputs!$C$62,"",C233*AE233) | AC233: =IF(AD233=0,0,R233/(AD233*Inputs!$C$16)) | AD233: =IF(A233>Inputs!$C$62,"",B233+C233) | AE233: =IF(A233>Inputs!$C$62,"", Inputs!$C$65*(1+Inputs!$C$89*POWER(MIN(1,IF(Inputs!$C$88=0,0,B233/Inputs!$C$88)),Inputs!$C$90))) | AF233: =IF(A233>Inputs!$C$62,"",IF(A233=1,Inputs!$C$86,MIN(Inputs!$C$86,Inputs!$C$87*M232))) | AG233: =IF(A233>Inputs!$C$62,"",MIN(0.5,MAX(0, Inputs!$C$67*L233 + Inputs!$C$68*(1-K233) + Inputs!$C$69*Inputs!$C$10))) | AH233: =IF(A233>Inputs!$C$62,"",INDEX(CapacityPlan!$G$7:$G$266,A233)) | AI233: =IF(A233>Inputs!$C$62,"",INDEX(CapacityPlan!$J$7:$J$266,A233)) | AJ233: =IF(A233>Inputs!$C$62,"",IF(I233=0,"",G233/I233))
A234: 212 | B234: =IF(A234>Inputs!$C$62,"",IF(Inputs!$C$80=1,INDEX(Cohorts!$B$67:$B$326,A234),IF(A234=1,Inputs!$C$63,F233))) | C234: =IF(A234>Inputs!$C$62,"",IF(Inputs!$C$85=0,Inputs!$C$64,MIN(Inputs!$C$91,IF(AE234=0,0,AF234/AE234)))) | D234: =IF(A234>Inputs!$C$62,"",IF(Inputs!$C$80=1,INDEX(Cohorts!$G$67:$G$326,A234),MAX(0, Inputs!$C$66 + Inputs!$C$67*L234 + Inputs!$C$68*(1-K234) + Inputs!$C$69*Inputs!$C$10))) | E234: =IF(A234>Inputs!$C$62,"",IF(Inputs!$C$80=1,INDEX(Cohorts!$H$67:$H$326,A234),D234*AD234)) | F234: =IF(A234>Inputs!$C$62,"",IF(Inputs!$C$80=1,INDEX(Cohorts!$I$67:$I$326,A234),AD234-E234)) | G234: =IF(A234>Inputs!$C$62,"",AD234) | H234: =IF(A234>Inputs!$C$62,"",INDEX(CapacityPlan!$E$7:$E$266,A234)) | I234: =IF(A234>Inputs!$C$62,"",INDEX(CapacityPlan!$I$7:$I$266,A234)) | J234: =IF(A234>Inputs!$C$62,"",IF(G234>I234,I234,G234)) | K234: =IF(A234>Inputs!$C$62,"",IF(G234=0,1,J234/G234)) | M234: =IF(A234>Inputs!$C$62,"",J234*Inputs!$C$7*(1-Inputs!$C$8)*(1-L234)) | N234: =IF(A234>Inputs!$C$62,"",J234*UnitEconomics!$B$32*AI234 + (G234-J234)*Inputs!$C$71) | P234: =IF(A234>Inputs!$C$62,"",Inputs!$C$40 + H234*Inputs!$C$41) | R234: =IF(A234>Inputs!$C$62,"",AD234*Inputs!$C$16*(Inputs!$C$9 + Inputs!$C$10*Inputs!$C$11 + Inputs!$C$12)*(1 + VLOOKUP(Inputs!$C$15,Lookups!$A$2:$B$20,2,TRUE)*(Scale!$B$9/IF(Scale!$B$8=0,1,Scale!$B$8)) + Inputs!$C$52)) | Y234: =IF(A234>Inputs!$C$62,"",C234*AE234) | AC234: =IF(AD234=0,0,R234/(AD234*Inputs!$C$16)) | AD234: =IF(A234>Inputs!$C$62,"",B234+C234) | AE234: =IF(A234>Inputs!$C$62,"", Inputs!$C$65*(1+Inputs!$C$89*POWER(MIN(1,IF(Inputs!$C$88=0,0,B234/Inputs!$C$88)),Inputs!$C$90))) | AF234: =IF(A234>Inputs!$C$62,"",IF(A234=1,Inputs!$C$86,MIN(Inputs!$C$86,Inputs!$C$87*M233))) | AG234: =IF(A234>Inputs!$C$62,"",MIN(0.5,MAX(0, Inputs!$C$67*L234 + Inputs!$C$68*(1-K234) + Inputs!$C$69*Inputs!$C$10))) | AH234: =IF(A234>Inputs!$C$62,"",INDEX(CapacityPlan!$G$7:$G$266,A234)) | AI234: =IF(A234>Inputs!$C$62,"",INDEX(CapacityPlan!$J$7:$J$266,A234)) | AJ234: =IF(A234>Inputs!$C$62,"",IF(I234=0,"",G234/I234))
... A282: 260 | B282: =IF(A282>Inputs!$C$62,"",IF(Inputs!$C$80=1,INDEX(Cohorts!$B$67:$B$326,A282),IF(A282=1,Inputs!$C$63,F281))) | C282: =IF(A282>Inputs!$C$62,"",IF(Inputs!$C$85=0,Inputs!$C$64,MIN(Inputs!$C$91,IF(AE282=0,0,AF282/AE282)))) | D282: =IF(A282>Inputs!$C$62,"",IF(Inputs!$C$80=1,INDEX(Cohorts!$G$67:$G$326,A282),MAX(0, Inputs!$C$66 + Inputs!$C$67*L282 + Inputs!$C$68*(1-K282) + Inputs!$C$69*Inputs!$C$10))) | E282: =IF(A282>Inputs!$C$62,"",IF(Inputs!$C$80=1,INDEX(Cohorts!$H$67:$H$326,A282),D282*AD282)) | F282: =IF(A282>Inputs!$C$62,"",IF(Inputs!$C$80=1,INDEX(Cohorts!$I$67:$I$326,A282),AD282-E282)) | G282: =IF(A282>Inputs!$C$62,"",AD282) | H282: =IF(A282>Inputs!$C$62,"",INDEX(CapacityPlan!$E$7:$E$266,A282)) | I282: =IF(A282>Inputs!$C$62,"",INDEX(CapacityPlan!$I$7:$I$266,A282)) | J282: =IF(A282>Inputs!$C$62,"",IF(G282>I282,I282,G282)) | K282: =IF(A282>Inputs!$C$62,"",IF(G282=0,1,J282/G282)) | M282: =IF(A282>Inputs!$C$62,"",J282*Inputs!$C$7*(1-Inputs!$C$8)*(1-L282)) | N282: =IF(A282>Inputs!$C$62,"",J282*UnitEconomics!$B$32*AI282 + (G282-J282)*Inputs!$C$71) | P282: =IF(A282>Inputs!$C$62,"",Inputs!$C$40 + H282*Inputs!$C$41) | R282: =IF(A282>Inputs!$C$62,"",AD282*Inputs!$C$16*(Inputs!$C$9 + Inputs!$C$10*Inputs!$C$11 + Inputs!$C$12)*(1 + VLOOKUP(Inputs!$C$15,Lookups!$A$2:$B$20,2,TRUE)*(Scale!$B$9/IF(Scale!$B$8=0,1,Scale!$B$8)) + Inputs!$C$52)) | Y282: =IF(A282>Inputs!$C$62,"",C282*AE282) | AC282: =IF(AD282=0,0,R282/(AD282*Inputs!$C$16)) | AD282: =IF(A282>Inputs!$C$62,"",B282+C282) | AE282: =IF(A282>Inputs!$C$62,"", Inputs!$C$65*(1+Inputs!$C$89*POWER(MIN(1,IF(Inputs!$C$88=0,0,B282/Inputs!$C$88)),Inputs!$C$90))) | AF282: =IF(A282>Inputs!$C$62,"",IF(A282=1,Inputs!$C$86,MIN(Inputs!$C$86,Inputs!$C$87*M281))) | AG282: =IF(A282>Inputs!$C$62,"",MIN(0.5,MAX(0, Inputs!$C$67*L282 + Inputs!$C$68*(1-K282) + Inputs!$C$69*Inputs!$C$10))) | AH282: =IF(A282>Inputs!$C$62,"",INDEX(CapacityPlan!$G$7:$G$266,A282)) | AI282: =IF(A282>Inputs!$C$62,"",INDEX(CapacityPlan!$J$7:$J$266,A282)) | AJ282: =IF(A282>Inputs!$C$62,"",IF(I282=0,"",G282/I282))

Sheet MonteCarlo
A1: Monte Carlo (per-cycle). Variance + discrete friction (loss/damage/miship/late).
A3: Runs | B3: 100 | D3: Summary | N3: Constants
D4: Mean CM | E4: =AVERAGE(K6:K105) | N4: BASE_REV | O4: =Inputs!$C$7*(1-Inputs!$C$8)
A5: Run | B5: Return wks | C5: Clean wks | D5: Cycle wks | E5: =PERCENTILE.INC(K6:K105,0.10) | F5: Miship? | G5: Loss ct | H5: Damage ct | I5: Damage retire ct | J5: Refund % | K5: CM (USD) | L5: Revenue | M5: Costs | N5: CLEAN_QA | O5: =Inputs!$C$16*(UnitEconomics!$B$6+Inputs!$C$24) | P5: NegFlag
A6: 1 | B6: =MAX(0.1, NORM.INV(RAND(), Inputs!$C$9, Inputs!$C$13) + E6*Inputs!$C$11) | C6: =MAX(0.05, NORM.INV(RAND(), Inputs!$C$12, Inputs!$C$14)) | D6: =B6+C6 | E6: =PERCENTILE.INC(K6:K105,0.50) | F6: =IF(RAND()<UnitEconomics!$B$12,1,0) | G6: =BINOM.INV(Inputs!$C$16, Inputs!$C$19, RAND()) | H6: =BINOM.INV(Inputs!$C$16, Inputs!$C$20, RAND()) | I6: =BINOM.INV(H6, Inputs!$C$21, RAND()) | J6: =IF( Inputs!$C$36 + F6*Inputs!$C$37 + E6*Inputs!$C$38>1,1, Inputs!$C$36 + F6*Inputs!$C$37 + E6*Inputs!$C$38) | K6: =L6-M6 | L6: =$O$4*(1-J6) | M6: =$O$5+$O$6+$O$7+$O$8+$O$9+F6*$O$10+E6*$O$11+$O$12+G6*$O$13+H6*$O$14+I6*$O$13+$O$15*L6+$O$16 | N6: SHIP | O6: =UnitEconomics!$B$10+UnitEconomics!$B$11 | P6: =IF(K6<0,1,0)
A7: 2 | B7: =MAX(0.1, NORM.INV(RAND(), Inputs!$C$9, Inputs!$C$13) + E7*Inputs!$C$11) | C7: =MAX(0.05, NORM.INV(RAND(), Inputs!$C$12, Inputs!$C$14)) | D7: =B7+C7 | E7: =PERCENTILE.INC(K6:K105,0.90) | F7: =IF(RAND()<UnitEconomics!$B$12,1,0) | G7: =BINOM.INV(Inputs!$C$16, Inputs!$C$19, RAND()) | H7: =BINOM.INV(Inputs!$C$16, Inputs!$C$20, RAND()) | I7: =BINOM.INV(H7, Inputs!$C$21, RAND()) | J7: =IF( Inputs!$C$36 + F7*Inputs!$C$37 + E7*Inputs!$C$38>1,1, Inputs!$C$36 + F7*Inputs!$C$37 + E7*Inputs!$C$38) | K7: =L7-M7 | L7: =$O$4*(1-J7) | M7: =$O$5+$O$6+$O$7+$O$8+$O$9+F7*$O$10+E7*$O$11+$O$12+G7*$O$13+H7*$O$14+I7*$O$13+$O$15*L7+$O$16 | N7: LABOR | O7: =UnitEconomics!$B$7+UnitEconomics!$B$8 | P7: =IF(K7<0,1,0)
A8: 3 | B8: =MAX(0.1, NORM.INV(RAND(), Inputs!$C$9, Inputs!$C$13) + E8*Inputs!$C$11) | C8: =MAX(0.05, NORM.INV(RAND(), Inputs!$C$12, Inputs!$C$14)) | D8: =B8+C8 | E8: =SUM(P6:P105)/100 | F8: =IF(RAND()<UnitEconomics!$B$12,1,0) | G8: =BINOM.INV(Inputs!$C$16, Inputs!$C$19, RAND()) | H8: =BINOM.INV(Inputs!$C$16, Inputs!$C$20, RAND()) | I8: =BINOM.INV(H8, Inputs!$C$21, RAND()) | J8: =IF( Inputs!$C$36 + F8*Inputs!$C$37 + E8*Inputs!$C$38>1,1, Inputs!$C$36 + F8*Inputs!$C$37 + E8*Inputs!$C$38) | K8: =L8-M8 | L8: =$O$4*(1-J8) | M8: =$O$5+$O$6+$O$7+$O$8+$O$9+F8*$O$10+E8*$O$11+$O$12+G8*$O$13+H8*$O$14+I8*$O$13+$O$15*L8+$O$16 | N8: SUPPORT | O8: =UnitEconomics!$B$9 | P8: =IF(K8<0,1,0)
A9: 4 | B9: =MAX(0.1, NORM.INV(RAND(), Inputs!$C$9, Inputs!$C$13) + E9*Inputs!$C$11) | C9: =MAX(0.05, NORM.INV(RAND(), Inputs!$C$12, Inputs!$C$14)) | D9: =B9+C9 | E9: =--(RAND()<Inputs!$C$10) | F9: =IF(RAND()<UnitEconomics!$B$12,1,0) | G9: =BINOM.INV(Inputs!$C$16, Inputs!$C$19, RAND()) | H9: =BINOM.INV(Inputs!$C$16, Inputs!$C$20, RAND()) | I9: =BINOM.INV(H9, Inputs!$C$21, RAND()) | J9: =IF( Inputs!$C$36 + F9*Inputs!$C$37 + E9*Inputs!$C$38>1,1, Inputs!$C$36 + F9*Inputs!$C$37 + E9*Inputs!$C$38) | K9: =L9-M9 | L9: =$O$4*(1-J9) | M9: =$O$5+$O$6+$O$7+$O$8+$O$9+F9*$O$10+E9*$O$11+$O$12+G9*$O$13+H9*$O$14+I9*$O$13+$O$15*L9+$O$16 | N9: PACK | O9: =Inputs!$C$23 | P9: =IF(K9<0,1,0)
A10: 5 | B10: =MAX(0.1, NORM.INV(RAND(), Inputs!$C$9, Inputs!$C$13) + E10*Inputs!$C$11) | C10: =MAX(0.05, NORM.INV(RAND(), Inputs!$C$12, Inputs!$C$14)) | D10: =B10+C10 | E10: =--(RAND()<Inputs!$C$10) | F10: =IF(RAND()<UnitEconomics!$B$12,1,0) | G10: =BINOM.INV(Inputs!$C$16, Inputs!$C$19, RAND()) | H10: =BINOM.INV(Inputs!$C$16, Inputs!$C$20, RAND()) | I10: =BINOM.INV(H10, Inputs!$C$21, RAND()) | J10: =IF( Inputs!$C$36 + F10*Inputs!$C$37 + E10*Inputs!$C$38>1,1, Inputs!$C$36 + F10*Inputs!$C$37 + E10*Inputs!$C$38) | K10: =L10-M10 | L10: =$O$4*(1-J10) | M10: =$O$5+$O$6+$O$7+$O$8+$O$9+F10*$O$10+E10*$O$11+$O$12+G10*$O$13+H10*$O$14+I10*$O$13+$O$15*L10+$O$16 | N10: MISHIP_COST | O10: =Inputs!$C$34 | P10: =IF(K10<0,1,0)
A11: 6 | B11: =MAX(0.1, NORM.INV(RAND(), Inputs!$C$9, Inputs!$C$13) + E11*Inputs!$C$11) | C11: =MAX(0.05, NORM.INV(RAND(), Inputs!$C$12, Inputs!$C$14)) | D11: =B11+C11 | E11: =--(RAND()<Inputs!$C$10) | F11: =IF(RAND()<UnitEconomics!$B$12,1,0) | G11: =BINOM.INV(Inputs!$C$16, Inputs!$C$19, RAND()) | H11: =BINOM.INV(Inputs!$C$16, Inputs!$C$20, RAND()) | I11: =BINOM.INV(H11, Inputs!$C$21, RAND()) | J11: =IF( Inputs!$C$36 + F11*Inputs!$C$37 + E11*Inputs!$C$38>1,1, Inputs!$C$36 + F11*Inputs!$C$37 + E11*Inputs!$C$38) | K11: =L11-M11 | L11: =$O$4*(1-J11) | M11: =$O$5+$O$6+$O$7+$O$8+$O$9+F11*$O$10+E11*$O$11+$O$12+G11*$O$13+H11*$O$14+I11*$O$13+$O$15*L11+$O$16 | N11: LATE_COST | O11: =Inputs!$C$35 | P11: =IF(K11<0,1,0)
A12: 7 | B12: =MAX(0.1, NORM.INV(RAND(), Inputs!$C$9, Inputs!$C$13) + E12*Inputs!$C$11) | C12: =MAX(0.05, NORM.INV(RAND(), Inputs!$C$12, Inputs!$C$14)) | D12: =B12+C12 | E12: =--(RAND()<Inputs!$C$10) | F12: =IF(RAND()<UnitEconomics!$B$12,1,0) | G12: =BINOM.INV(Inputs!$C$16, Inputs!$C$19, RAND()) | H12: =BINOM.INV(Inputs!$C$16, Inputs!$C$20, RAND()) | I12: =BINOM.INV(H12, Inputs!$C$21, RAND()) | J12: =IF( Inputs!$C$36 + F12*Inputs!$C$37 + E12*Inputs!$C$38>1,1, Inputs!$C$36 + F12*Inputs!$C$37 + E12*Inputs!$C$38) | K12: =L12-M12 | L12: =$O$4*(1-J12) | M12: =$O$5+$O$6+$O$7+$O$8+$O$9+F12*$O$10+E12*$O$11+$O$12+G12*$O$13+H12*$O$14+I12*$O$13+$O$15*L12+$O$16 | N12: WEAR_REPL | O12: =Inputs!$C$16*(1/Inputs!$C$18)*Inputs!$C$17 | P12: =IF(K12<0,1,0)
A13: 8 | B13: =MAX(0.1, NORM.INV(RAND(), Inputs!$C$9, Inputs!$C$13) + E13*Inputs!$C$11) | C13: =MAX(0.05, NORM.INV(RAND(), Inputs!$C$12, Inputs!$C$14)) | D13: =B13+C13 | E13: =--(RAND()<Inputs!$C$10) | F13: =IF(RAND()<UnitEconomics!$B$12,1,0) | G13: =BINOM.INV(Inputs!$C$16, Inputs!$C$19, RAND()) | H13: =BINOM.INV(Inputs!$C$16, Inputs!$C$20, RAND()) | I13: =BINOM.INV(H13, Inputs!$C$21, RAND()) | J13: =IF( Inputs!$C$36 + F13*Inputs!$C$37 + E13*Inputs!$C$38>1,1, Inputs!$C$36 + F13*Inputs!$C$37 + E13*Inputs!$C$38) | K13: =L13-M13 | L13: =$O$4*(1-J13) | M13: =$O$5+$O$6+$O$7+$O$8+$O$9+F13*$O$10+E13*$O$11+$O$12+G13*$O$13+H13*$O$14+I13*$O$13+$O$15*L13+$O$16 | N13: ACQ | O13: =Inputs!$C$17 | P13: =IF(K13<0,1,0)
A14: 9 | B14: =MAX(0.1, NORM.INV(RAND(), Inputs!$C$9, Inputs!$C$13) + E14*Inputs!$C$11) | C14: =MAX(0.05, NORM.INV(RAND(), Inputs!$C$12, Inputs!$C$14)) | D14: =B14+C14 | E14: =--(RAND()<Inputs!$C$10) | F14: =IF(RAND()<UnitEconomics!$B$12,1,0) | G14: =BINOM.INV(Inputs!$C$16, Inputs!$C$19, RAND()) | H14: =BINOM.INV(Inputs!$C$16, Inputs!$C$20, RAND()) | I14: =BINOM.INV(H14, Inputs!$C$21, RAND()) | J14: =IF( Inputs!$C$36 + F14*Inputs!$C$37 + E14*Inputs!$C$38>1,1, Inputs!$C$36 + F14*Inputs!$C$37 + E14*Inputs!$C$38) | K14: =L14-M14 | L14: =$O$4*(1-J14) | M14: =$O$5+$O$6+$O$7+$O$8+$O$9+F14*$O$10+E14*$O$11+$O$12+G14*$O$13+H14*$O$14+I14*$O$13+$O$15*L14+$O$16 | N14: REPAIR | O14: =Inputs!$C$22 | P14: =IF(K14<0,1,0)
A15: 10 | B15: =MAX(0.1, NORM.INV(RAND(), Inputs!$C$9, Inputs!$C$13) + E15*Inputs!$C$11) | C15: =MAX(0.05, NORM.INV(RAND(), Inputs!$C$12, Inputs!$C$14)) | D15: =B15+C15 | E15: =--(RAND()<Inputs!$C$10) | F15: =IF(RAND()<UnitEconomics!$B$12,1,0) | G15: =BINOM.INV(Inputs!$C$16, Inputs!$C$19, RAND()) | H15: =BINOM.INV(Inputs!$C$16, Inputs!$C$20, RAND()) | I15: =BINOM.INV(H15, Inputs!$C$21, RAND()) | J15: =IF( Inputs!$C$36 + F15*Inputs!$C$37 + E15*Inputs!$C$38>1,1, Inputs!$C$36 + F15*Inputs!$C$37 + E15*Inputs!$C$38) | K15: =L15-M15 | L15: =$O$4*(1-J15) | M15: =$O$5+$O$6+$O$7+$O$8+$O$9+F15*$O$10+E15*$O$11+$O$12+G15*$O$13+H15*$O$14+I15*$O$13+$O$15*L15+$O$16 | N15: PAY_RATE | O15: =Inputs!$C$31 | P15: =IF(K15<0,1,0)
A16: 11 | B16: =MAX(0.1, NORM.INV(RAND(), Inputs!$C$9, Inputs!$C$13) + E16*Inputs!$C$11) | C16: =MAX(0.05, NORM.INV(RAND(), Inputs!$C$12, Inputs!$C$14)) | D16: =B16+C16 | E16: =--(RAND()<Inputs!$C$10) | F16: =IF(RAND()<UnitEconomics!$B$12,1,0) | G16: =BINOM.INV(Inputs!$C$16, Inputs!$C$19, RAND()) | H16: =BINOM.INV(Inputs!$C$16, Inputs!$C$20, RAND()) | I16: =BINOM.INV(H16, Inputs!$C$21, RAND()) | J16: =IF( Inputs!$C$36 + F16*Inputs!$C$37 + E16*Inputs!$C$38>1,1, Inputs!$C$36 + F16*Inputs!$C$37 + E16*Inputs!$C$38) | K16: =L16-M16 | L16: =$O$4*(1-J16) | M16: =$O$5+$O$6+$O$7+$O$8+$O$9+F16*$O$10+E16*$O$11+$O$12+G16*$O$13+H16*$O$14+I16*$O$13+$O$15*L16+$O$16 | N16: PAY_FIXED | O16: =Inputs!$C$32 | P16: =IF(K16<0,1,0)
A17: 12 | B17: =MAX(0.1, NORM.INV(RAND(), Inputs!$C$9, Inputs!$C$13) + E17*Inputs!$C$11) | C17: =MAX(0.05, NORM.INV(RAND(), Inputs!$C$12, Inputs!$C$14)) | D17: =B17+C17 | E17: =--(RAND()<Inputs!$C$10) | F17: =IF(RAND()<UnitEconomics!$B$12,1,0) | G17: =BINOM.INV(Inputs!$C$16, Inputs!$C$19, RAND()) | H17: =BINOM.INV(Inputs!$C$16, Inputs!$C$20, RAND()) | I17: =BINOM.INV(H17, Inputs!$C$21, RAND()) | J17: =IF( Inputs!$C$36 + F17*Inputs!$C$37 + E17*Inputs!$C$38>1,1, Inputs!$C$36 + F17*Inputs!$C$37 + E17*Inputs!$C$38) | K17: =L17-M17 | L17: =$O$4*(1-J17) | M17: =$O$5+$O$6+$O$7+$O$8+$O$9+F17*$O$10+E17*$O$11+$O$12+G17*$O$13+H17*$O$14+I17*$O$13+$O$15*L17+$O$16 | P17: =IF(K17<0,1,0)
A18: 13 | B18: =MAX(0.1, NORM.INV(RAND(), Inputs!$C$9, Inputs!$C$13) + E18*Inputs!$C$11) | C18: =MAX(0.05, NORM.INV(RAND(), Inputs!$C$12, Inputs!$C$14)) | D18: =B18+C18 | E18: =--(RAND()<Inputs!$C$10) | F18: =IF(RAND()<UnitEconomics!$B$12,1,0) | G18: =BINOM.INV(Inputs!$C$16, Inputs!$C$19, RAND()) | H18: =BINOM.INV(Inputs!$C$16, Inputs!$C$20, RAND()) | I18: =BINOM.INV(H18, Inputs!$C$21, RAND()) | J18: =IF( Inputs!$C$36 + F18*Inputs!$C$37 + E18*Inputs!$C$38>1,1, Inputs!$C$36 + F18*Inputs!$C$37 + E18*Inputs!$C$38) | K18: =L18-M18 | L18: =$O$4*(1-J18) | M18: =$O$5+$O$6+$O$7+$O$8+$O$9+F18*$O$10+E18*$O$11+$O$12+G18*$O$13+H18*$O$14+I18*$O$13+$O$15*L18+$O$16 | P18: =IF(K18<0,1,0)
A19: 14 | B19: =MAX(0.1, NORM.INV(RAND(), Inputs!$C$9, Inputs!$C$13) + E19*Inputs!$C$11) | C19: =MAX(0.05, NORM.INV(RAND(), Inputs!$C$12, Inputs!$C$14)) | D19: =B19+C19 | E19: =--(RAND()<Inputs!$C$10) | F19: =IF(RAND()<UnitEconomics!$B$12,1,0) | G19: =BINOM.INV(Inputs!$C$16, Inputs!$C$19, RAND()) | H19: =BINOM.INV(Inputs!$C$16, Inputs!$C$20, RAND()) | I19: =BINOM.INV(H19, Inputs!$C$21, RAND()) | J19: =IF( Inputs!$C$36 + F19*Inputs!$C$37 + E19*Inputs!$C$38>1,1, Inputs!$C$36 + F19*Inputs!$C$37 + E19*Inputs!$C$38) | K19: =L19-M19 | L19: =$O$4*(1-J19) | M19: =$O$5+$O$6+$O$7+$O$8+$O$9+F19*$O$10+E19*$O$11+$O$12+G19*$O$13+H19*$O$14+I19*$O$13+$O$15*L19+$O$16 | P19: =IF(K19<0,1,0)
A20: 15 | B20: =MAX(0.1, NORM.INV(RAND(), Inputs!$C$9, Inputs!$C$13) + E20*Inputs!$C$11) | C20: =MAX(0.05, NORM.INV(RAND(), Inputs!$C$12, Inputs!$C$14)) | D20: =B20+C20 | E20: =--(RAND()<Inputs!$C$10) | F20: =IF(RAND()<UnitEconomics!$B$12,1,0) | G20: =BINOM.INV(Inputs!$C$16, Inputs!$C$19, RAND()) | H20: =BINOM.INV(Inputs!$C$16, Inputs!$C$20, RAND()) | I20: =BINOM.INV(H20, Inputs!$C$21, RAND()) | J20: =IF( Inputs!$C$36 + F20*Inputs!$C$37 + E20*Inputs!$C$38>1,1, Inputs!$C$36 + F20*Inputs!$C$37 + E20*Inputs!$C$38) | K20: =L20-M20 | L20: =$O$4*(1-J20) | M20: =$O$5+$O$6+$O$7+$O$8+$O$9+F20*$O$10+E20*$O$11+$O$12+G20*$O$13+H20*$O$14+I20*$O$13+$O$15*L20+$O$16 | P20: =IF(K20<0,1,0)
A21: 16 | B21: =MAX(0.1, NORM.INV(RAND(), Inputs!$C$9, Inputs!$C$13) + E21*Inputs!$C$11) | C21: =MAX(0.05, NORM.INV(RAND(), Inputs!$C$12, Inputs!$C$14)) | D21: =B21+C21 | E21: =--(RAND()<Inputs!$C$10) | F21: =IF(RAND()<UnitEconomics!$B$12,1,0) | G21: =BINOM.INV(Inputs!$C$16, Inputs!$C$19, RAND()) | H21: =BINOM.INV(Inputs!$C$16, Inputs!$C$20, RAND()) | I21: =BINOM.INV(H21, Inputs!$C$21, RAND()) | J21: =IF( Inputs!$C$36 + F21*Inputs!$C$37 + E21*Inputs!$C$38>1,1, Inputs!$C$36 + F21*Inputs!$C$37 + E21*Inputs!$C$38) | K21: =L21-M21 | L21: =$O$4*(1-J21) | M21: =$O$5+$O$6+$O$7+$O$8+$O$9+F21*$O$10+E21*$O$11+$O$12+G21*$O$13+H21*$O$14+I21*$O$13+$O$15*L21+$O$16 | P21: =IF(K21<0,1,0)
A22: 17 | B22: =MAX(0.1, NORM.INV(RAND(), Inputs!$C$9, Inputs!$C$13) + E22*Inputs!$C$11) | C22: =MAX(0.05, NORM.INV(RAND(), Inputs!$C$12, Inputs!$C$14)) | D22: =B22+C22 | E22: =--(RAND()<Inputs!$C$10) | F22: =IF(RAND()<UnitEconomics!$B$12,1,0) | G22: =BINOM.INV(Inputs!$C$16, Inputs!$C$19, RAND()) | H22: =BINOM.INV(Inputs!$C$16, Inputs!$C$20, RAND()) | I22: =BINOM.INV(H22, Inputs!$C$21, RAND()) | J22: =IF( Inputs!$C$36 + F22*Inputs!$C$37 + E22*Inputs!$C$38>1,1, Inputs!$C$36 + F22*Inputs!$C$37 + E22*Inputs!$C$38) | K22: =L22-M22 | L22: =$O$4*(1-J22) | M22: =$O$5+$O$6+$O$7+$O$8+$O$9+F22*$O$10+E22*$O$11+$O$12+G22*$O$13+H22*$O$14+I22*$O$13+$O$15*L22+$O$16 | P22: =IF(K22<0,1,0)
A23: 18 | B23: =MAX(0.1, NORM.INV(RAND(), Inputs!$C$9, Inputs!$C$13) + E23*Inputs!$C$11) | C23: =MAX(0.05, NORM.INV(RAND(), Inputs!$C$12, Inputs!$C$14)) | D23: =B23+C23 | E23: =--(RAND()<Inputs!$C$10) | F23: =IF(RAND()<UnitEconomics!$B$12,1,0) | G23: =BINOM.INV(Inputs!$C$16, Inputs!$C$19, RAND()) | H23: =BINOM.INV(Inputs!$C$16, Inputs!$C$20, RAND()) | I23: =BINOM.INV(H23, Inputs!$C$21, RAND()) | J23: =IF( Inputs!$C$36 + F23*Inputs!$C$37 + E23*Inputs!$C$38>1,1, Inputs!$C$36 + F23*Inputs!$C$37 + E23*Inputs!$C$38) | K23: =L23-M23 | L23: =$O$4*(1-J23) | M23: =$O$5+$O$6+$O$7+$O$8+$O$9+F23*$O$10+E23*$O$11+$O$12+G23*$O$13+H23*$O$14+I23*$O$13+$O$15*L23+$O$16 | P23: =IF(K23<0,1,0)
A24: 19 | B24: =MAX(0.1, NORM.INV(RAND(), Inputs!$C$9, Inputs!$C$13) + E24*Inputs!$C$11) | C24: =MAX(0.05, NORM.INV(RAND(), Inputs!$C$12, Inputs!$C$14)) | D24: =B24+C24 | E24: =--(RAND()<Inputs!$C$10) | F24: =IF(RAND()<UnitEconomics!$B$12,1,0) | G24: =BINOM.INV(Inputs!$C$16, Inputs!$C$19, RAND()) | H24: =BINOM.INV(Inputs!$C$16, Inputs!$C$20, RAND()) | I24: =BINOM.INV(H24, Inputs!$C$21, RAND()) | J24: =IF( Inputs!$C$36 + F24*Inputs!$C$37 + E24*Inputs!$C$38>1,1, Inputs!$C$36 + F24*Inputs!$C$37 + E24*Inputs!$C$38) | K24: =L24-M24 | L24: =$O$4*(1-J24) | M24: =$O$5+$O$6+$O$7+$O$8+$O$9+F24*$O$10+E24*$O$11+$O$12+G24*$O$13+H24*$O$14+I24*$O$13+$O$15*L24+$O$16 | P24: =IF(K24<0,1,0)
A25: 20 | B25: =MAX(0.1, NORM.INV(RAND(), Inputs!$C$9, Inputs!$C$13) + E25*Inputs!$C$11) | C25: =MAX(0.05, NORM.INV(RAND(), Inputs!$C$12, Inputs!$C$14)) | D25: =B25+C25 | E25: =--(RAND()<Inputs!$C$10) | F25: =IF(RAND()<UnitEconomics!$B$12,1,0) | G25: =BINOM.INV(Inputs!$C$16, Inputs!$C$19, RAND()) | H25: =BINOM.INV(Inputs!$C$16, Inputs!$C$20, RAND()) | I25: =BINOM.INV(H25, Inputs!$C$21, RAND()) | J25: =IF( Inputs!$C$36 + F25*Inputs!$C$37 + E25*Inputs!$C$38>1,1, Inputs!$C$36 + F25*Inputs!$C$37 + E25*Inputs!$C$38) | K25: =L25-M25 | L25: =$O$4*(1-J25) | M25: =$O$5+$O$6+$O$7+$O$8+$O$9+F25*$O$10+E25*$O$11+$O$12+G25*$O$13+H25*$O$14+I25*$O$13+$O$15*L25+$O$16 | P25: =IF(K25<0,1,0)
A26: 21 | B26: =MAX(0.1, NORM.INV(RAND(), Inputs!$C$9, Inputs!$C$13) + E26*Inputs!$C$11) | C26: =MAX(0.05, NORM.INV(RAND(), Inputs!$C$12, Inputs!$C$14)) | D26: =B26+C26 | E26: =--(RAND()<Inputs!$C$10) | F26: =IF(RAND()<UnitEconomics!$B$12,1,0) | G26: =BINOM.INV(Inputs!$C$16, Inputs!$C$19, RAND()) | H26: =BINOM.INV(Inputs!$C$16, Inputs!$C$20, RAND()) | I26: =BINOM.INV(H26, Inputs!$C$21, RAND()) | J26: =IF( Inputs!$C$36 + F26*Inputs!$C$37 + E26*Inputs!$C$38>1,1, Inputs!$C$36 + F26*Inputs!$C$37 + E26*Inputs!$C$38) | K26: =L26-M26 | L26: =$O$4*(1-J26) | M26: =$O$5+$O$6+$O$7+$O$8+$O$9+F26*$O$10+E26*$O$11+$O$12+G26*$O$13+H26*$O$14+I26*$O$13+$O$15*L26+$O$16 | P26: =IF(K26<0,1,0)
A27: 22 | B27: =MAX(0.1, NORM.INV(RAND(), Inputs!$C$9, Inputs!$C$13) + E27*Inputs!$C$11) | C27: =MAX(0.05, NORM.INV(RAND(), Inputs!$C$12, Inputs!$C$14)) | D27: =B27+C27 | E27: =--(RAND()<Inputs!$C$10) | F27: =IF(RAND()<UnitEconomics!$B$12,1,0) | G27: =BINOM.INV(Inputs!$C$16, Inputs!$C$19, RAND()) | H27: =BINOM.INV(Inputs!$C$16, Inputs!$C$20, RAND()) | I27: =BINOM.INV(H27, Inputs!$C$21, RAND()) | J27: =IF( Inputs!$C$36 + F27*Inputs!$C$37 + E27*Inputs!$C$38>1,1, Inputs!$C$36 + F27*Inputs!$C$37 + E27*Inputs!$C$38) | K27: =L27-M27 | L27: =$O$4*(1-J27) | M27: =$O$5+$O$6+$O$7+$O$8+$O$9+F27*$O$10+E27*$O$11+$O$12+G27*$O$13+H27*$O$14+I27*$O$13+$O$15*L27+$O$16 | P27: =IF(K27<0,1,0)
A28: 23 | B28: =MAX(0.1, NORM.INV(RAND(), Inputs!$C$9, Inputs!$C$13) + E28*Inputs!$C$11) | C28: =MAX(0.05, NORM.INV(RAND(), Inputs!$C$12, Inputs!$C$14)) | D28: =B28+C28 | E28: =--(RAND()<Inputs!$C$10) | F28: =IF(RAND()<UnitEconomics!$B$12,1,0) | G28: =BINOM.INV(Inputs!$C$16, Inputs!$C$19, RAND()) | H28: =BINOM.INV(Inputs!$C$16, Inputs!$C$20, RAND()) | I28: =BINOM.INV(H28, Inputs!$C$21, RAND()) | J28: =IF( Inputs!$C$36 + F28*Inputs!$C$37 + E28*Inputs!$C$38>1,1, Inputs!$C$36 + F28*Inputs!$C$37 + E28*Inputs!$C$38) | K28: =L28-M28 | L28: =$O$4*(1-J28) | M28: =$O$5+$O$6+$O$7+$O$8+$O$9+F28*$O$10+E28*$O$11+$O$12+G28*$O$13+H28*$O$14+I28*$O$13+$O$15*L28+$O$16 | P28: =IF(K28<0,1,0)
... A35: 30 | B35: =MAX(0.1, NORM.INV(RAND(), Inputs!$C$9, Inputs!$C$13) + E35*Inputs!$C$11) | C35: =MAX(0.05, NORM.INV(RAND(), Inputs!$C$12, Inputs!$C$14)) | D35: =B35+C35 | E35: =--(RAND()<Inputs!$C$10) | F35: =IF(RAND()<UnitEconomics!$B$12,1,0) | G35: =BINOM.INV(Inputs!$C$16, Inputs!$C$19, RAND()) | H35: =BINOM.INV(Inputs!$C$16, Inputs!$C$20, RAND()) | I35: =BINOM.INV(H35, Inputs!$C$21, RAND()) | J35: =IF( Inputs!$C$36 + F35*Inputs!$C$37 + E35*Inputs!$C$38>1,1, Inputs!$C$36 + F35*Inputs!$C$37 + E35*Inputs!$C$38) | K35: =L35-M35 | L35: =$O$4*(1-J35) | M35: =$O$5+$O$6+$O$7+$O$8+$O$9+F35*$O$10+E35*$O$11+$O$12+G35*$O$13+H35*$O$14+I35*$O$13+$O$15*L35+$O$16 | P35: =IF(K35<0,1,0)
K36: =L36-M36 | L36: =$O$4*(1-J36) | M36: =$O$5+$O$6+$O$7+$O$8+$O$9+F36*$O$10+E36*$O$11+$O$12+G36*$O$13+H36*$O$14+I36*$O$13+$O$15*L36+$O$16 | P36: =IF(K36<0,1,0)
K37: =L37-M37 | L37: =$O$4*(1-J37) | M37: =$O$5+$O$6+$O$7+$O$8+$O$9+F37*$O$10+E37*$O$11+$O$12+G37*$O$13+H37*$O$14+I37*$O$13+$O$15*L37+$O$16 | P37: =IF(K37<0,1,0)
K38: =L38-M38 | L38: =$O$4*(1-J38) | M38: =$O$5+$O$6+$O$7+$O$8+$O$9+F38*$O$10+E38*$O$11+$O$12+G38*$O$13+H38*$O$14+I38*$O$13+$O$15*L38+$O$16 | P38: =IF(K38<0,1,0)
K39: =L39-M39 | L39: =$O$4*(1-J39) | M39: =$O$5+$O$6+$O$7+$O$8+$O$9+F39*$O$10+E39*$O$11+$O$12+G39*$O$13+H39*$O$14+I39*$O$13+$O$15*L39+$O$16 | P39: =IF(K39<0,1,0)
K40: =L40-M40 | L40: =$O$4*(1-J40) | M40: =$O$5+$O$6+$O$7+$O$8+$O$9+F40*$O$10+E40*$O$11+$O$12+G40*$O$13+H40*$O$14+I40*$O$13+$O$15*L40+$O$16 | P40: =IF(K40<0,1,0)
K41: =L41-M41 | L41: =$O$4*(1-J41) | M41: =$O$5+$O$6+$O$7+$O$8+$O$9+F41*$O$10+E41*$O$11+$O$12+G41*$O$13+H41*$O$14+I41*$O$13+$O$15*L41+$O$16 | P41: =IF(K41<0,1,0)
K42: =L42-M42 | L42: =$O$4*(1-J42) | M42: =$O$5+$O$6+$O$7+$O$8+$O$9+F42*$O$10+E42*$O$11+$O$12+G42*$O$13+H42*$O$14+I42*$O$13+$O$15*L42+$O$16 | P42: =IF(K42<0,1,0)
K43: =L43-M43 | L43: =$O$4*(1-J43) | M43: =$O$5+$O$6+$O$7+$O$8+$O$9+F43*$O$10+E43*$O$11+$O$12+G43*$O$13+H43*$O$14+I43*$O$13+$O$15*L43+$O$16 | P43: =IF(K43<0,1,0)
K44: =L44-M44 | L44: =$O$4*(1-J44) | M44: =$O$5+$O$6+$O$7+$O$8+$O$9+F44*$O$10+E44*$O$11+$O$12+G44*$O$13+H44*$O$14+I44*$O$13+$O$15*L44+$O$16 | P44: =IF(K44<0,1,0)
K45: =L45-M45 | L45: =$O$4*(1-J45) | M45: =$O$5+$O$6+$O$7+$O$8+$O$9+F45*$O$10+E45*$O$11+$O$12+G45*$O$13+H45*$O$14+I45*$O$13+$O$15*L45+$O$16 | P45: =IF(K45<0,1,0)
K46: =L46-M46 | L46: =$O$4*(1-J46) | M46: =$O$5+$O$6+$O$7+$O$8+$O$9+F46*$O$10+E46*$O$11+$O$12+G46*$O$13+H46*$O$14+I46*$O$13+$O$15*L46+$O$16 | P46: =IF(K46<0,1,0)
K47: =L47-M47 | L47: =$O$4*(1-J47) | M47: =$O$5+$O$6+$O$7+$O$8+$O$9+F47*$O$10+E47*$O$11+$O$12+G47*$O$13+H47*$O$14+I47*$O$13+$O$15*L47+$O$16 | P47: =IF(K47<0,1,0)
... K105: =L105-M105 | L105: =$O$4*(1-J105) | M105: =$O$5+$O$6+$O$7+$O$8+$O$9+F105*$O$10+E105*$O$11+$O$12+G105*$O$13+H105*$O$14+I105*$O$13+$O$15*L105+$O$16 | P105: =IF(K105<0,1,0)

Sheet KillConditions
A1: Economic Kill Conditions (structural non-viability triggers)
A2: Condition | B2: Value | C2: Threshold | D2: Status
A3: CM per cycle ≤ 0 | B3: =UnitEconomics!$B$33 | C3: ≤ 0 | D3: =IF(B3<=0,"KILL","OK")
A4: Economic CM per cycle ≤ 0 | B4: =UnitEconomics!$B$35 | C4: ≤ 0 | D4: =IF(B4<=0,"KILL","OK")
A5: Inventory multiple exceeds threshold | B5: =Scale!$B$12 | C5: > Inputs!$C$53 | D5: =IF(B5>Inputs!$C$53,"KILL","OK")
A6: Logistics+ops share exceeds threshold | B6: =IF(UnitEconomics!$B$18=0,1,(UnitEconomics!$B$19+UnitEconomics!$B$20+UnitEconomics!$B$21+UnitEconomics!$B$22+UnitEconomics!$B$23+UnitEconomics!$B$24)/UnitEconomics!$B$18) | C6: > Inputs!$C$54 | D6: =IF(B6>Inputs!$C$54,"KILL","OK")
A7: Replacement share exceeds threshold | B7: =IF(UnitEconomics!$B$18=0,1,(UnitEconomics!$B$27+UnitEconomics!$B$28+UnitEconomics!$B$29)/UnitEconomics!$B$18) | C7: > Inputs!$C$55 | D7: =IF(B7>Inputs!$C$55,"KILL","OK")
A8: Monte Carlo Pr(CM<0) exceeds threshold | B8: =MonteCarlo!$E$8 | C8: > Inputs!$C$57 | D8: =IF(B8>Inputs!$C$57,"KILL","OK")
A9: Trajectory cash-out occurs within horizon | B9: =IF(Trajectory!$E$4<0,1,0)
A10: Trajectory min fulfill rate < MIN_FULFILL_RATE | B10: =IF(Trajectory!$E$6<Inputs!$C$56,1,0)
A11: Trajectory max inventory multiple exceeds threshold | B11: =Trajectory!$E$8
A12: Trajectory max inventory multiple > MAX_INVENTORY_MULTIPLE | B12: =IF(Trajectory!$E$8>Inputs!$C$53,1,0)
A13: Trajectory min fulfill rate (value) | B13: =Trajectory!$E$6
